Workbook

Sheet Start Here
A1: Domain Investing — Rubric & Portfolio Tracker
A4: HOW TO USE THIS FILE
A5: 1. Assumptions | B5: Set your commission rate, sell-through rate and holding horizon FIRST. Every max-bid and break-even number in the file is driven off this tab.
A6: 2. Rubric | B6: Read the scoring definitions. Adjust the six weights if you disagree — they must sum to 100%. The Weight Check cell turns red if they don't.
A7: 3. Candidates | B7: One row per name you are considering. Score the five manual criteria 1-5, enter your acquisition cost and honest resale estimate. The sheet returns a weighted score, a max rational bid, and a verdict.
A8: 4. Portfolio | B8: One row per name you actually own. Tracks cumulative renewal carry and the list price you need to break even after commission.
A9: 5. Sales Log | B9: One row per sale. Feeds realised P&L and your true sell-through rate.
A10: 6. Dashboard | B10: Read-only summary. The number to watch is Annual Renewal Burden vs. Realised Net Profit.
A11: 7. Comps | B11: Reference sales and market benchmarks with sources, for calibrating the Comp Support score.
A12: 8. Market Frequency | B12: How often domains actually sell and for how much, with the derivation behind the sell-through rate and a calibrator that turns a break-even into a percentile.
A13: 9. Closeout Screener | B13: Expired names in GoDaddy's $11-to-$5 closeout window. Scores name quality and asset quality separately, then gives bid timing.
A15: COLOUR LEGEND
A16: Blue text | B16: You type here. These are inputs.
A17: Yellow fill | B17: Key assumption — the numbers most worth arguing about.
A18: Black text | B18: Formula. Do not overwrite.
A19: Green text | B19: Formula that pulls from another sheet. Do not overwrite.
A20: Orange row | B20: EXAMPLE ROW showing the expected format. Delete it before you start.
A22: THE ONE THING TO REMEMBER
A23: Carry kills portfolios | B23: At a 1% sell-through rate you sell roughly one name per hundred per year, while paying renewals on all hundred. A name is only worth owning if its expected net proceeds beat its expected carry over your holding horizon. That comparison is the Max Rational Bid column on the Candidates tab — if your acquisition cost is above it, the name loses money on average no matter how good it sounds.
A24: Availability | B24: This file does not check whether a domain is registered. Column A holds the full domain, so select it, copy, and paste straight into GoDaddy's bulk search (up to 500 at a time), then mark the result in the Availability column. The Ext column derives itself from column A — do not type into it.
A25: Appraisals | B25: GoDaddy's automated appraisal is not evidence. Use the Comp Support score instead — it asks whether comparable names have actually sold, which is the only valuation signal with a buyer behind it.
A27: Built | B27: 2026-08-06. Market benchmarks on the Comps tab are as-published; re-check before relying on them.

Sheet Assumptions
A1: Assumptions — set these before anything else
A3: Assumption | B3: Value | C3: Unit | D3: Why it matters / source
A4: Commission rate on sale | B4: 0.2 | C4: % | D4: Afternic/GoDaddy: 30% on Boost, 25% Basic; drops to 20% (Boost) or 15% (Basic) if you point the domain at GoDaddy aftermarket nameservers. 20% assumes Boost + GD nameservers.
A5: Minimum commission per sale | B5: 15 | C5: USD | D5: GoDaddy applies a $15 floor. Only bites on sub-$100 sales.
A6: Expected sell-through rate (per year) | B6: 0.01 | C6: % | D6: DERIVED, see the Market Frequency tab. About 256,600 reported sales a year above $100 against 20m+ listings on Afternic alone gives 1.28%; against 25-30m unique listings across venues it is 0.86-1.03%. 1.00% is the middle of that. The commonly quoted 1.5-2% is measured on curated portfolios or is simply optimistic - assuming you beat the market before you have evidence is the same error as guessing a resale value. Raise it only when your own Sales Log earns it.
A7: Holding horizon (years) | B7: 5 | C7: years | D7: Typical time-to-sale for ordinary inventory is 5-10 years. This is the window the max-bid maths assumes you are willing to fund renewals for.
A8: Default annual renewal — .com | B8: 11 | C8: USD | D8: Typical .com renewal. Override per name where different.
A9: Default annual renewal — premium TLD | B9: 35 | C9: USD | D9: .ai/.io renewals run far higher and are the main reason trendy-TLD portfolios lose money at low sell-through rates.
A10: Required return multiple on cost | B10: 10 | C10: x | D10: Minimum sale-price-to-acquisition-cost ratio you will accept, used to set target list prices. 10x on a $12 hand-reg is a $120 name — set this high, most names never sell at all.
A11: Quality pivot score (neutral) | B11: 3 | C11: years | D11: A name scoring exactly this gets the base sell-through rate above. Better names get a higher rate, worse names a lower one.
A12: Quality sensitivity (0 = off) | B12: 1 | C12: years | D12: MODELLING ASSUMPTION, NOT MEASURED DATA. Effective rate = base rate x (score / pivot) ^ this. At 1.0 the relationship is linear: a 4.5 name is assumed to sell 1.5x as often as a 3.0 name. Set to 0 to disable and give every name the same probability — which is what the first version of this model did, and it was wrong, because it made name quality irrelevant to the economics.
A13: Safety multiple required for BUY | B13: 2 | C13: x | D13: How far above break-even a valuation must sit before the verdict is BUY. At 2.0 the name must be worth twice what the maths strictly requires — headroom for the valuation being wrong.
A15: DERIVED — do not edit
A16: Probability a listed name sells within the horizon | B16: =1-(1-$B$6)^$B$7 -> 0.04900995 | D16: 1 minus the chance it fails to sell every year running. This single number is why most portfolios lose money: over 5 years at a 2% annual rate, roughly 9 names in 10 do not sell at all.
A17: Expected renewal carry per name over horizon (.com) | B17: =$B$8*$B$7 -> 55 | D17: What you pay to keep one .com alive for the full horizon, win or lose.

Sheet Rubric
A1: Scoring Rubric — six weighted criteria, scored 1 to 5
A3: Weights drive the Candidates tab. Edit the blue cells if you disagree; they must sum to 100%.
A4: Criterion | B4: Weight | C4: Score 1 — avoid | D4: Score 3 — marginal | E4: Score 5 — strong
A5: Extension | B5: 0.22 | C5: New gTLD (.shop, .xyz, .link) or an obscure ccTLD. Supply is about to expand further when ICANN reopens the new-gTLD window. | D5: .co, .net, .org, or a strong country ccTLD. Sells, but at a fraction of .com. | E5: .com. Every one of 2026's largest sales was a .com. .ai is a genuine second tier for AI-native buyers but carries a much higher renewal.
A6: Commercial intent | B6: 0.3 | C6: Hobby, meme, or personal-interest term. Nobody monetises it, so nobody bids. | D6: Real commercial term, but low customer value or a thin buyer pool. | E6: Term in a sector where one customer is worth thousands — finance, insurance, legal, medical, real estate, B2B SaaS. A $3k domain is a rounding error to that buyer.
A7: Comp support | B7: 0.22 | C7: No comparable sale you can point to. You are guessing. | D7: Loosely similar names have sold, but at scattered prices or years ago. | E7: Several closely comparable names sold recently at prices you can cite. This is the only valuation input with an actual buyer behind it.
A8: Length & memorability | B8: 0.16 | C8: Four or more words, over ~20 characters, or a forgettable string. | D8: Two or three words, reasonable length, unremarkable. | E8: One strong dictionary word, or a tight two-word pairing. Short 4-5 character .com remains the most valuable class there is.
A9: Radio test | B9: 0.1 | C9: Has to be spelled out. Homophone traps, doubled letters, invented spellings. | D9: Mostly clear, occasional spelling correction needed. | E9: Say it once on a phone call and the other person types it correctly.
A10: Weight check | B10: =SUM(B5:B9) -> 1 | C10: =IF(ABS(B10-1)<0.0001,"OK — weights sum to 100%","ERROR — weights must sum to 100%") -> OK — weights sum to 100%
A12: EXTENSION LOOKUP — used automatically by the Candidates tab
A13: Extension | B13: Score | C13: Typical annual renewal | D13: Note
A14: com | B14: 5 | C14: 11 | D14: The default. Dominates every top-sales chart.
A15: ai | B15: 4 | C15: 90 | D15: Real demand, premium resale averages around $6.5k — but the renewal is the trap.
A16: io | B16: 3 | C16: 40 | D16: Startup-friendly, high renewal, softening as .ai takes the tech mindshare.
A17: co | B17: 3 | C17: 30 | D17: Credible .com alternative, sells at a steep discount to it.
A18: net | B18: 3 | C18: 13 | D18: Old and trusted, limited upside.
A19: org | B19: 3 | C19: 13 | D19: Strong for nonprofit/institutional buyers, narrow otherwise.
A20: app | B20: 2 | C20: 18 | D20: Niche, mostly end-user rather than investor demand.
A21: dev | B21: 2 | C21: 15 | D21: Same — developer tools, thin aftermarket.
A22: xyz | B22: 1 | C22: 12 | D22: High volume, low realised prices.
A23: other | B23: 1 | C23: 25 | D23: Default for anything unlisted. Assume the market is thin.
A25: HARD FILTERS — any one of these rejects the name regardless of score
A26: REJECT if: | B26: Trademark risk — contains or closely mimics an existing brand. A UDRP complaint costs you the name and the legal fee, and intent to resell is exactly what the process punishes.
A27: REJECT if: | B27: Contains a hyphen or a digit. Both collapse resale value and fail the radio test.
A28: REJECT if: | B28: Four or more words.
A29: REJECT if: | B29: Plural/singular confusion with an established site you would be trading off.
A31: VERDICT THRESHOLDS
A32: Verdict | B32: Condition | C32: Meaning
A33: BUY | B33: Score >= 4.00 and cost <= max rational bid | C33: Passes both the quality bar and the maths.
A34: BUY IF CHEAPER | B34: Score >= 4.00 but cost > max rational bid | C34: Good name, wrong price. Bid the max rational bid and walk if it goes higher.
A35: WATCH | B35: Score 3.20 - 3.99 | C35: Borderline. Only take it at a low acquisition cost.
A36: PASS | B36: Score < 3.20 | C36: Below the bar.
A37: REJECT | B37: Any hard filter failed | C37: Do not buy at any price.

Sheet Candidates
A1: Candidate Pipeline — names under consideration
A2: Rows 5-112: equipment finance, checked 2026-08-03 — a mature niche, nothing clearing. Rows 113+: batch 3, emerging categories researched 2026-08-04 (agentic AI, GEO/AEO, slop provenance, longevity, creator economy) plus three viral-slang controls. Est. Resale Value stays EMPTY until you have a sourced number; work from BREAK-EVEN RESALE, which needs no estimate.
A4: Domain (full, e.g. name.com) | B4: Ext | C4: Ext Score | D4: Commercial Intent (1-5) | E4: Comp Support (1-5) | F4: Length & Memorability (1-5) | G4: Radio Test (1-5) | H4: TM Risk? (Y/N) | I4: Hyphen/Digit? (Y/N) | J4: Acquisition Cost | K4: Est. Resale Value | L4: Valuation Source | M4: Annual Renewal | N4: Weighted Score | O4: Hard Filter | P4: Effective STR /yr | Q4: P(sale in horizon) | R4: Expected Carry | S4: BREAK-EVEN RESALE | T4: Value Ratio | U4: Max Rational Bid | V4: Verdict | W4: Availability | X4: Notes
A5: workingcapital.com | B5: =IF($A5="","",IF(ISERROR(FIND(".",$A5)),"",LOWER(MID($A5,FIND(CHAR(1),SUBSTITUTE($A5,".",CHAR(1),LEN($A5)-LEN(SUBSTITUTE($A5,".",""))))+1,LEN($A5))))) -> com | C5: =IF($B5="","",IFERROR(INDEX(Rubric!$B$14:$B$23,MATCH($B5,Rubric!$A$14:$A$23,0)),INDEX(Rubric!$B$14:$B$23,MATCH("other",Rubric!$A$14:$A$23,0)))) -> 5 | D5: 5 | E5: 4 | F5: 4 | G5: 5 | H5: N | I5: N | M5: =IF($B5="","",IFERROR(INDEX(Rubric!$C$14:$C$23,MATCH($B5,Rubric!$A$14:$A$23,0)),INDEX(Rubric!$C$14:$C$23,MATCH("other",Rubric!$A$14:$A$23,0)))) -> 11 | N5: =IF(OR($A5="",$C5=""),"",$C5*Rubric!$B$5+$D5*Rubric!$B$6+$E5*Rubric!$B$7+$F5*Rubric!$B$8+$G5*Rubric!$B$9) -> 4.62 | O5: =IF($A5="","",IF(OR(UPPER($H5)="Y",UPPER($I5)="Y"),"FAIL","PASS")) -> PASS | P5: =IF($N5="","",Assumptions!$B$6*MAX(0.05,($N5/Assumptions!$B$11)^Assumptions!$B$12)) -> 0.0154 | Q5: =IF($P5="","",1-(1-$P5)^Assumptions!$B$7) -> 0.074664642 | R5: =IF($M5="","",$M5*Assumptions!$B$7) -> 55 | S5: =IF(OR($J5="",$Q5="",$Q5=0),"",($J5+$R5)/($Q5*(1-Assumptions!$B$4))) | T5: =IF(OR($K5="",$S5="",$S5=0),"",$K5/$S5) | U5: =IF(OR($K5="",$Q5=""),"",MAX(0,($K5-MAX($K5*Assumptions!$B$4,Assumptions!$B$5))*$Q5-$R5)) | V5: =IF($A5="","",IF($O5="FAIL","REJECT",IF($J5="","NEEDS PRICE",IF(OR($K5="",$L5=""),"NEEDS VALUATION",IF($T5>=Assumptions!$B$13,"BUY",IF($T5>=1,"MARGINAL","PASS")))))) -> NEEDS PRICE | W5: Taken | X5: [T1] Core term, huge buyer pool. Certainly registered — auction/broker target only.
A6: commerciallending.com | B6: =IF($A6="","",IF(ISERROR(FIND(".",$A6)),"",LOWER(MID($A6,FIND(CHAR(1),SUBSTITUTE($A6,".",CHAR(1),LEN($A6)-LEN(SUBSTITUTE($A6,".",""))))+1,LEN($A6))))) -> com | C6: =IF($B6="","",IFERROR(INDEX(Rubric!$B$14:$B$23,MATCH($B6,Rubric!$A$14:$A$23,0)),INDEX(Rubric!$B$14:$B$23,MATCH("other",Rubric!$A$14:$A$23,0)))) -> 5 | D6: 5 | E6: 3 | F6: 3 | G6: 4 | H6: N | I6: N | M6: =IF($B6="","",IFERROR(INDEX(Rubric!$C$14:$C$23,MATCH($B6,Rubric!$A$14:$A$23,0)),INDEX(Rubric!$C$14:$C$23,MATCH("other",Rubric!$A$14:$A$23,0)))) -> 11 | N6: =IF(OR($A6="",$C6=""),"",$C6*Rubric!$B$5+$D6*Rubric!$B$6+$E6*Rubric!$B$7+$F6*Rubric!$B$8+$G6*Rubric!$B$9) -> 4.14 | O6: =IF($A6="","",IF(OR(UPPER($H6)="Y",UPPER($I6)="Y"),"FAIL","PASS")) -> PASS | P6: =IF($N6="","",Assumptions!$B$6*MAX(0.05,($N6/Assumptions!$B$11)^Assumptions!$B$12)) -> 0.0138 | Q6: =IF($P6="","",1-(1-$P6)^Assumptions!$B$7) -> 0.0671217 | R6: =IF($M6="","",$M6*Assumptions!$B$7) -> 55 | S6: =IF(OR($J6="",$Q6="",$Q6=0),"",($J6+$R6)/($Q6*(1-Assumptions!$B$4))) | T6: =IF(OR($K6="",$S6="",$S6=0),"",$K6/$S6) | U6: =IF(OR($K6="",$Q6=""),"",MAX(0,($K6-MAX($K6*Assumptions!$B$4,Assumptions!$B$5))*$Q6-$R6)) | V6: =IF($A6="","",IF($O6="FAIL","REJECT",IF($J6="","NEEDS PRICE",IF(OR($K6="",$L6=""),"NEEDS VALUATION",IF($T6>=Assumptions!$B$13,"BUY",IF($T6>=1,"MARGINAL","PASS")))))) -> NEEDS PRICE | W6: Taken | X6: [T1] Category-defining term. Aftermarket only.
A7: equipmentfinancing.com | B7: =IF($A7="","",IF(ISERROR(FIND(".",$A7)),"",LOWER(MID($A7,FIND(CHAR(1),SUBSTITUTE($A7,".",CHAR(1),LEN($A7)-LEN(SUBSTITUTE($A7,".",""))))+1,LEN($A7))))) -> com | C7: =IF($B7="","",IFERROR(INDEX(Rubric!$B$14:$B$23,MATCH($B7,Rubric!$A$14:$A$23,0)),INDEX(Rubric!$B$14:$B$23,MATCH("other",Rubric!$A$14:$A$23,0)))) -> 5 | D7: 5 | E7: 3 | F7: 3 | G7: 5 | H7: N | I7: N | M7: =IF($B7="","",IFERROR(INDEX(Rubric!$C$14:$C$23,MATCH($B7,Rubric!$A$14:$A$23,0)),INDEX(Rubric!$C$14:$C$23,MATCH("other",Rubric!$A$14:$A$23,0)))) -> 11 | N7: =IF(OR($A7="",$C7=""),"",$C7*Rubric!$B$5+$D7*Rubric!$B$6+$E7*Rubric!$B$7+$F7*Rubric!$B$8+$G7*Rubric!$B$9) -> 4.24 | O7: =IF($A7="","",IF(OR(UPPER($H7)="Y",UPPER($I7)="Y"),"FAIL","PASS")) -> PASS | P7: =IF($N7="","",Assumptions!$B$6*MAX(0.05,($N7/Assumptions!$B$11)^Assumptions!$B$12)) -> 0.014133333 | Q7: =IF($P7="","",1-(1-$P7)^Assumptions!$B$7) -> 0.068697188 | R7: =IF($M7="","",$M7*Assumptions!$B$7) -> 55 | S7: =IF(OR($J7="",$Q7="",$Q7=0),"",($J7+$R7)/($Q7*(1-Assumptions!$B$4))) | T7: =IF(OR($K7="",$S7="",$S7=0),"",$K7/$S7) | U7: =IF(OR($K7="",$Q7=""),"",MAX(0,($K7-MAX($K7*Assumptions!$B$4,Assumptions!$B$5))*$Q7-$R7)) | V7: =IF($A7="","",IF($O7="FAIL","REJECT",IF($J7="","NEEDS PRICE",IF(OR($K7="",$L7=""),"NEEDS VALUATION",IF($T7>=Assumptions!$B$13,"BUY",IF($T7>=1,"MARGINAL","PASS")))))) -> NEEDS PRICE | W7: Taken | X7: [T1] The exact-match phrase for the niche. Aftermarket only.
A8: equipmentleasing.com | B8: =IF($A8="","",IF(ISERROR(FIND(".",$A8)),"",LOWER(MID($A8,FIND(CHAR(1),SUBSTITUTE($A8,".",CHAR(1),LEN($A8)-LEN(SUBSTITUTE($A8,".",""))))+1,LEN($A8))))) -> com | C8: =IF($B8="","",IFERROR(INDEX(Rubric!$B$14:$B$23,MATCH($B8,Rubric!$A$14:$A$23,0)),INDEX(Rubric!$B$14:$B$23,MATCH("other",Rubric!$A$14:$A$23,0)))) -> 5 | D8: 5 | E8: 3 | F8: 3 | G8: 5 | H8: N | I8: N | M8: =IF($B8="","",IFERROR(INDEX(Rubric!$C$14:$C$23,MATCH($B8,Rubric!$A$14:$A$23,0)),INDEX(Rubric!$C$14:$C$23,MATCH("other",Rubric!$A$14:$A$23,0)))) -> 11 | N8: =IF(OR($A8="",$C8=""),"",$C8*Rubric!$B$5+$D8*Rubric!$B$6+$E8*Rubric!$B$7+$F8*Rubric!$B$8+$G8*Rubric!$B$9) -> 4.24 | O8: =IF($A8="","",IF(OR(UPPER($H8)="Y",UPPER($I8)="Y"),"FAIL","PASS")) -> PASS | P8: =IF($N8="","",Assumptions!$B$6*MAX(0.05,($N8/Assumptions!$B$11)^Assumptions!$B$12)) -> 0.014133333 | Q8: =IF($P8="","",1-(1-$P8)^Assumptions!$B$7) -> 0.068697188 | R8: =IF($M8="","",$M8*Assumptions!$B$7) -> 55 | S8: =IF(OR($J8="",$Q8="",$Q8=0),"",($J8+$R8)/($Q8*(1-Assumptions!$B$4))) | T8: =IF(OR($K8="",$S8="",$S8=0),"",$K8/$S8) | U8: =IF(OR($K8="",$Q8=""),"",MAX(0,($K8-MAX($K8*Assumptions!$B$4,Assumptions!$B$5))*$Q8-$R8)) | V8: =IF($A8="","",IF($O8="FAIL","REJECT",IF($J8="","NEEDS PRICE",IF(OR($K8="",$L8=""),"NEEDS VALUATION",IF($T8>=Assumptions!$B$13,"BUY",IF($T8>=1,"MARGINAL","PASS")))))) -> NEEDS PRICE | W8: Taken | X8: [T1] ELFA's own vocabulary. Aftermarket only.
A9: invoicefactoring.com | B9: =IF($A9="","",IF(ISERROR(FIND(".",$A9)),"",LOWER(MID($A9,FIND(CHAR(1),SUBSTITUTE($A9,".",CHAR(1),LEN($A9)-LEN(SUBSTITUTE($A9,".",""))))+1,LEN($A9))))) -> com | C9: =IF($B9="","",IFERROR(INDEX(Rubric!$B$14:$B$23,MATCH($B9,Rubric!$A$14:$A$23,0)),INDEX(Rubric!$B$14:$B$23,MATCH("other",Rubric!$A$14:$A$23,0)))) -> 5 | D9: 5 | E9: 3 | F9: 3 | G9: 5 | H9: N | I9: N | M9: =IF($B9="","",IFERROR(INDEX(Rubric!$C$14:$C$23,MATCH($B9,Rubric!$A$14:$A$23,0)),INDEX(Rubric!$C$14:$C$23,MATCH("other",Rubric!$A$14:$A$23,0)))) -> 11 | N9: =IF(OR($A9="",$C9=""),"",$C9*Rubric!$B$5+$D9*Rubric!$B$6+$E9*Rubric!$B$7+$F9*Rubric!$B$8+$G9*Rubric!$B$9) -> 4.24 | O9: =IF($A9="","",IF(OR(UPPER($H9)="Y",UPPER($I9)="Y"),"FAIL","PASS")) -> PASS | P9: =IF($N9="","",Assumptions!$B$6*MAX(0.05,($N9/Assumptions!$B$11)^Assumptions!$B$12)) -> 0.014133333 | Q9: =IF($P9="","",1-(1-$P9)^Assumptions!$B$7) -> 0.068697188 | R9: =IF($M9="","",$M9*Assumptions!$B$7) -> 55 | S9: =IF(OR($J9="",$Q9="",$Q9=0),"",($J9+$R9)/($Q9*(1-Assumptions!$B$4))) | T9: =IF(OR($K9="",$S9="",$S9=0),"",$K9/$S9) | U9: =IF(OR($K9="",$Q9=""),"",MAX(0,($K9-MAX($K9*Assumptions!$B$4,Assumptions!$B$5))*$Q9-$R9)) | V9: =IF($A9="","",IF($O9="FAIL","REJECT",IF($J9="","NEEDS PRICE",IF(OR($K9="",$L9=""),"NEEDS VALUATION",IF($T9>=Assumptions!$B$13,"BUY",IF($T9>=1,"MARGINAL","PASS")))))) -> NEEDS PRICE | W9: Taken | X9: [T1] High-CPC lending vertical. Aftermarket only.
A10: merchantcashadvance.com | B10: =IF($A10="","",IF(ISERROR(FIND(".",$A10)),"",LOWER(MID($A10,FIND(CHAR(1),SUBSTITUTE($A10,".",CHAR(1),LEN($A10)-LEN(SUBSTITUTE($A10,".",""))))+1,LEN($A10))))) -> com | C10: =IF($B10="","",IFERROR(INDEX(Rubric!$B$14:$B$23,MATCH($B10,Rubric!$A$14:$A$23,0)),INDEX(Rubric!$B$14:$B$23,MATCH("other",Rubric!$A$14:$A$23,0)))) -> 5 | D10: 5 | E10: 3 | F10: 2 | G10: 4 | H10: N | I10: N | M10: =IF($B10="","",IFERROR(INDEX(Rubric!$C$14:$C$23,MATCH($B10,Rubric!$A$14:$A$23,0)),INDEX(Rubric!$C$14:$C$23,MATCH("other",Rubric!$A$14:$A$23,0)))) -> 11 | N10: =IF(OR($A10="",$C10=""),"",$C10*Rubric!$B$5+$D10*Rubric!$B$6+$E10*Rubric!$B$7+$F10*Rubric!$B$8+$G10*Rubric!$B$9) -> 3.98 | O10: =IF($A10="","",IF(OR(UPPER($H10)="Y",UPPER($I10)="Y"),"FAIL","PASS")) -> PASS | P10: =IF($N10="","",Assumptions!$B$6*MAX(0.05,($N10/Assumptions!$B$11)^Assumptions!$B$12)) -> 0.013266667 | Q10: =IF($P10="","",1-(1-$P10)^Assumptions!$B$7) -> 0.064596484 | R10: =IF($M10="","",$M10*Assumptions!$B$7) -> 55 | S10: =IF(OR($J10="",$Q10="",$Q10=0),"",($J10+$R10)/($Q10*(1-Assumptions!$B$4))) | T10: =IF(OR($K10="",$S10="",$S10=0),"",$K10/$S10) | U10: =IF(OR($K10="",$Q10=""),"",MAX(0,($K10-MAX($K10*Assumptions!$B$4,Assumptions!$B$5))*$Q10-$R10)) | V10: =IF($A10="","",IF($O10="FAIL","REJECT",IF($J10="","NEEDS PRICE",IF(OR($K10="",$L10=""),"NEEDS VALUATION",IF($T10>=Assumptions!$B$13,"BUY",IF($T10>=1,"MARGINAL","PASS")))))) -> NEEDS PRICE | W10: Taken | X10: [T1] Very high CPC, long string. Aftermarket only.
A11: assetbasedlending.com | B11: =IF($A11="","",IF(ISERROR(FIND(".",$A11)),"",LOWER(MID($A11,FIND(CHAR(1),SUBSTITUTE($A11,".",CHAR(1),LEN($A11)-LEN(SUBSTITUTE($A11,".",""))))+1,LEN($A11))))) -> com | C11: =IF($B11="","",IFERROR(INDEX(Rubric!$B$14:$B$23,MATCH($B11,Rubric!$A$14:$A$23,0)),INDEX(Rubric!$B$14:$B$23,MATCH("other",Rubric!$A$14:$A$23,0)))) -> 5 | D11: 5 | E11: 3 | F11: 2 | G11: 4 | H11: N | I11: N | M11: =IF($B11="","",IFERROR(INDEX(Rubric!$C$14:$C$23,MATCH($B11,Rubric!$A$14:$A$23,0)),INDEX(Rubric!$C$14:$C$23,MATCH("other",Rubric!$A$14:$A$23,0)))) -> 11 | N11: =IF(OR($A11="",$C11=""),"",$C11*Rubric!$B$5+$D11*Rubric!$B$6+$E11*Rubric!$B$7+$F11*Rubric!$B$8+$G11*Rubric!$B$9) -> 3.98 | O11: =IF($A11="","",IF(OR(UPPER($H11)="Y",UPPER($I11)="Y"),"FAIL","PASS")) -> PASS | P11: =IF($N11="","",Assumptions!$B$6*MAX(0.05,($N11/Assumptions!$B$11)^Assumptions!$B$12)) -> 0.013266667 | Q11: =IF($P11="","",1-(1-$P11)^Assumptions!$B$7) -> 0.064596484 | R11: =IF($M11="","",$M11*Assumptions!$B$7) -> 55 | S11: =IF(OR($J11="",$Q11="",$Q11=0),"",($J11+$R11)/($Q11*(1-Assumptions!$B$4))) | T11: =IF(OR($K11="",$S11="",$S11=0),"",$K11/$S11) | U11: =IF(OR($K11="",$Q11=""),"",MAX(0,($K11-MAX($K11*Assumptions!$B$4,Assumptions!$B$5))*$Q11-$R11)) | V11: =IF($A11="","",IF($O11="FAIL","REJECT",IF($J11="","NEEDS PRICE",IF(OR($K11="",$L11=""),"NEEDS VALUATION",IF($T11>=Assumptions!$B$13,"BUY",IF($T11>=1,"MARGINAL","PASS")))))) -> NEEDS PRICE | W11: Taken | X11: [T1] ABL is a real institutional category. Aftermarket only.
A12: saleleaseback.com | B12: =IF($A12="","",IF(ISERROR(FIND(".",$A12)),"",LOWER(MID($A12,FIND(CHAR(1),SUBSTITUTE($A12,".",CHAR(1),LEN($A12)-LEN(SUBSTITUTE($A12,".",""))))+1,LEN($A12))))) -> com | C12: =IF($B12="","",IFERROR(INDEX(Rubric!$B$14:$B$23,MATCH($B12,Rubric!$A$14:$A$23,0)),INDEX(Rubric!$B$14:$B$23,MATCH("other",Rubric!$A$14:$A$23,0)))) -> 5 | D12: 4 | E12: 2 | F12: 3 | G12: 4 | H12: N | I12: N | M12: =IF($B12="","",IFERROR(INDEX(Rubric!$C$14:$C$23,MATCH($B12,Rubric!$A$14:$A$23,0)),INDEX(Rubric!$C$14:$C$23,MATCH("other",Rubric!$A$14:$A$23,0)))) -> 11 | N12: =IF(OR($A12="",$C12=""),"",$C12*Rubric!$B$5+$D12*Rubric!$B$6+$E12*Rubric!$B$7+$F12*Rubric!$B$8+$G12*Rubric!$B$9) -> 3.62 | O12: =IF($A12="","",IF(OR(UPPER($H12)="Y",UPPER($I12)="Y"),"FAIL","PASS")) -> PASS | P12: =IF($N12="","",Assumptions!$B$6*MAX(0.05,($N12/Assumptions!$B$11)^Assumptions!$B$12)) -> 0.012066667 | Q12: =IF($P12="","",1-(1-$P12)^Assumptions!$B$7) -> 0.058894753 | R12: =IF($M12="","",$M12*Assumptions!$B$7) -> 55 | S12: =IF(OR($J12="",$Q12="",$Q12=0),"",($J12+$R12)/($Q12*(1-Assumptions!$B$4))) | T12: =IF(OR($K12="",$S12="",$S12=0),"",$K12/$S12) | U12: =IF(OR($K12="",$Q12=""),"",MAX(0,($K12-MAX($K12*Assumptions!$B$4,Assumptions!$B$5))*$Q12-$R12)) | V12: =IF($A12="","",IF($O12="FAIL","REJECT",IF($J12="","NEEDS PRICE",IF(OR($K12="",$L12=""),"NEEDS VALUATION",IF($T12>=Assumptions!$B$13,"BUY",IF($T12>=1,"MARGINAL","PASS")))))) -> NEEDS PRICE | W12: Taken | X12: [T1] Structure term; narrower buyer pool than it looks.
A13: vendorfinancing.com | B13: =IF($A13="","",IF(ISERROR(FIND(".",$A13)),"",LOWER(MID($A13,FIND(CHAR(1),SUBSTITUTE($A13,".",CHAR(1),LEN($A13)-LEN(SUBSTITUTE($A13,".",""))))+1,LEN($A13))))) -> com | C13: =IF($B13="","",IFERROR(INDEX(Rubric!$B$14:$B$23,MATCH($B13,Rubric!$A$14:$A$23,0)),INDEX(Rubric!$B$14:$B$23,MATCH("other",Rubric!$A$14:$A$23,0)))) -> 5 | D13: 4 | E13: 2 | F13: 3 | G13: 5 | H13: N | I13: N | M13: =IF($B13="","",IFERROR(INDEX(Rubric!$C$14:$C$23,MATCH($B13,Rubric!$A$14:$A$23,0)),INDEX(Rubric!$C$14:$C$23,MATCH("other",Rubric!$A$14:$A$23,0)))) -> 11 | N13: =IF(OR($A13="",$C13=""),"",$C13*Rubric!$B$5+$D13*Rubric!$B$6+$E13*Rubric!$B$7+$F13*Rubric!$B$8+$G13*Rubric!$B$9) -> 3.72 | O13: =IF($A13="","",IF(OR(UPPER($H13)="Y",UPPER($I13)="Y"),"FAIL","PASS")) -> PASS | P13: =IF($N13="","",Assumptions!$B$6*MAX(0.05,($N13/Assumptions!$B$11)^Assumptions!$B$12)) -> 0.0124 | Q13: =IF($P13="","",1-(1-$P13)^Assumptions!$B$7) -> 0.060481348 | R13: =IF($M13="","",$M13*Assumptions!$B$7) -> 55 | S13: =IF(OR($J13="",$Q13="",$Q13=0),"",($J13+$R13)/($Q13*(1-Assumptions!$B$4))) | T13: =IF(OR($K13="",$S13="",$S13=0),"",$K13/$S13) | U13: =IF(OR($K13="",$Q13=""),"",MAX(0,($K13-MAX($K13*Assumptions!$B$4,Assumptions!$B$5))*$Q13-$R13)) | V13: =IF($A13="","",IF($O13="FAIL","REJECT",IF($J13="","NEEDS PRICE",IF(OR($K13="",$L13=""),"NEEDS VALUATION",IF($T13>=Assumptions!$B$13,"BUY",IF($T13>=1,"MARGINAL","PASS")))))) -> NEEDS PRICE | W13: Taken | X13: [T1] Vendor programs are a major equipment-finance channel.
A14: equipmentloans.com | B14: =IF($A14="","",IF(ISERROR(FIND(".",$A14)),"",LOWER(MID($A14,FIND(CHAR(1),SUBSTITUTE($A14,".",CHAR(1),LEN($A14)-LEN(SUBSTITUTE($A14,".",""))))+1,LEN($A14))))) -> com | C14: =IF($B14="","",IFERROR(INDEX(Rubric!$B$14:$B$23,MATCH($B14,Rubric!$A$14:$A$23,0)),INDEX(Rubric!$B$14:$B$23,MATCH("other",Rubric!$A$14:$A$23,0)))) -> 5 | D14: 5 | E14: 3 | F14: 4 | G14: 5 | H14: N | I14: N | M14: =IF($B14="","",IFERROR(INDEX(Rubric!$C$14:$C$23,MATCH($B14,Rubric!$A$14:$A$23,0)),INDEX(Rubric!$C$14:$C$23,MATCH("other",Rubric!$A$14:$A$23,0)))) -> 11 | N14: =IF(OR($A14="",$C14=""),"",$C14*Rubric!$B$5+$D14*Rubric!$B$6+$E14*Rubric!$B$7+$F14*Rubric!$B$8+$G14*Rubric!$B$9) -> 4.4 | O14: =IF($A14="","",IF(OR(UPPER($H14)="Y",UPPER($I14)="Y"),"FAIL","PASS")) -> PASS | P14: =IF($N14="","",Assumptions!$B$6*MAX(0.05,($N14/Assumptions!$B$11)^Assumptions!$B$12)) -> 0.014666667 | Q14: =IF($P14="","",1-(1-$P14)^Assumptions!$B$7) -> 0.071213541 | R14: =IF($M14="","",$M14*Assumptions!$B$7) -> 55 | S14: =IF(OR($J14="",$Q14="",$Q14=0),"",($J14+$R14)/($Q14*(1-Assumptions!$B$4))) | T14: =IF(OR($K14="",$S14="",$S14=0),"",$K14/$S14) | U14: =IF(OR($K14="",$Q14=""),"",MAX(0,($K14-MAX($K14*Assumptions!$B$4,Assumptions!$B$5))*$Q14-$R14)) | V14: =IF($A14="","",IF($O14="FAIL","REJECT",IF($J14="","NEEDS PRICE",IF(OR($K14="",$L14=""),"NEEDS VALUATION",IF($T14>=Assumptions!$B$13,"BUY",IF($T14>=1,"MARGINAL","PASS")))))) -> NEEDS PRICE | W14: Taken | X14: [T1] Shorter and cleaner than 'financing'. Aftermarket only.
A15: machineryfinancing.com | B15: =IF($A15="","",IF(ISERROR(FIND(".",$A15)),"",LOWER(MID($A15,FIND(CHAR(1),SUBSTITUTE($A15,".",CHAR(1),LEN($A15)-LEN(SUBSTITUTE($A15,".",""))))+1,LEN($A15))))) -> com | C15: =IF($B15="","",IFERROR(INDEX(Rubric!$B$14:$B$23,MATCH($B15,Rubric!$A$14:$A$23,0)),INDEX(Rubric!$B$14:$B$23,MATCH("other",Rubric!$A$14:$A$23,0)))) -> 5 | D15: 4 | E15: 3 | F15: 3 | G15: 4 | H15: N | I15: N | M15: =IF($B15="","",IFERROR(INDEX(Rubric!$C$14:$C$23,MATCH($B15,Rubric!$A$14:$A$23,0)),INDEX(Rubric!$C$14:$C$23,MATCH("other",Rubric!$A$14:$A$23,0)))) -> 11 | N15: =IF(OR($A15="",$C15=""),"",$C15*Rubric!$B$5+$D15*Rubric!$B$6+$E15*Rubric!$B$7+$F15*Rubric!$B$8+$G15*Rubric!$B$9) -> 3.84 | O15: =IF($A15="","",IF(OR(UPPER($H15)="Y",UPPER($I15)="Y"),"FAIL","PASS")) -> PASS | P15: =IF($N15="","",Assumptions!$B$6*MAX(0.05,($N15/Assumptions!$B$11)^Assumptions!$B$12)) -> 0.0128 | Q15: =IF($P15="","",1-(1-$P15)^Assumptions!$B$7) -> 0.062382438 | R15: =IF($M15="","",$M15*Assumptions!$B$7) -> 55 | S15: =IF(OR($J15="",$Q15="",$Q15=0),"",($J15+$R15)/($Q15*(1-Assumptions!$B$4))) | T15: =IF(OR($K15="",$S15="",$S15=0),"",$K15/$S15) | U15: =IF(OR($K15="",$Q15=""),"",MAX(0,($K15-MAX($K15*Assumptions!$B$4,Assumptions!$B$5))*$Q15-$R15)) | V15: =IF($A15="","",IF($O15="FAIL","REJECT",IF($J15="","NEEDS PRICE",IF(OR($K15="",$L15=""),"NEEDS VALUATION",IF($T15>=Assumptions!$B$13,"BUY",IF($T15>=1,"MARGINAL","PASS")))))) -> NEEDS PRICE | W15: Taken | X15: [T2] Machine tools / CNC buyers. Check availability.
A16: forkliftfinancing.com | B16: =IF($A16="","",IF(ISERROR(FIND(".",$A16)),"",LOWER(MID($A16,FIND(CHAR(1),SUBSTITUTE($A16,".",CHAR(1),LEN($A16)-LEN(SUBSTITUTE($A16,".",""))))+1,LEN($A16))))) -> com | C16: =IF($B16="","",IFERROR(INDEX(Rubric!$B$14:$B$23,MATCH($B16,Rubric!$A$14:$A$23,0)),INDEX(Rubric!$B$14:$B$23,MATCH("other",Rubric!$A$14:$A$23,0)))) -> 5 | D16: 4 | E16: 3 | F16: 3 | G16: 5 | H16: N | I16: N | M16: =IF($B16="","",IFERROR(INDEX(Rubric!$C$14:$C$23,MATCH($B16,Rubric!$A$14:$A$23,0)),INDEX(Rubric!$C$14:$C$23,MATCH("other",Rubric!$A$14:$A$23,0)))) -> 11 | N16: =IF(OR($A16="",$C16=""),"",$C16*Rubric!$B$5+$D16*Rubric!$B$6+$E16*Rubric!$B$7+$F16*Rubric!$B$8+$G16*Rubric!$B$9) -> 3.94 | O16: =IF($A16="","",IF(OR(UPPER($H16)="Y",UPPER($I16)="Y"),"FAIL","PASS")) -> PASS | P16: =IF($N16="","",Assumptions!$B$6*MAX(0.05,($N16/Assumptions!$B$11)^Assumptions!$B$12)) -> 0.013133333 | Q16: =IF($P16="","",1-(1-$P16)^Assumptions!$B$7) -> 0.063964327 | R16: =IF($M16="","",$M16*Assumptions!$B$7) -> 55 | S16: =IF(OR($J16="",$Q16="",$Q16=0),"",($J16+$R16)/($Q16*(1-Assumptions!$B$4))) | T16: =IF(OR($K16="",$S16="",$S16=0),"",$K16/$S16) | U16: =IF(OR($K16="",$Q16=""),"",MAX(0,($K16-MAX($K16*Assumptions!$B$4,Assumptions!$B$5))*$Q16-$R16)) | V16: =IF($A16="","",IF($O16="FAIL","REJECT",IF($J16="","NEEDS PRICE",IF(OR($K16="",$L16=""),"NEEDS VALUATION",IF($T16>=Assumptions!$B$13,"BUY",IF($T16>=1,"MARGINAL","PASS")))))) -> NEEDS PRICE | W16: Taken | X16: [T2] Material handling is a large, financeable category.
A17: fleetfinancing.com | B17: =IF($A17="","",IF(ISERROR(FIND(".",$A17)),"",LOWER(MID($A17,FIND(CHAR(1),SUBSTITUTE($A17,".",CHAR(1),LEN($A17)-LEN(SUBSTITUTE($A17,".",""))))+1,LEN($A17))))) -> com | C17: =IF($B17="","",IFERROR(INDEX(Rubric!$B$14:$B$23,MATCH($B17,Rubric!$A$14:$A$23,0)),INDEX(Rubric!$B$14:$B$23,MATCH("other",Rubric!$A$14:$A$23,0)))) -> 5 | D17: 5 | E17: 3 | F17: 4 | G17: 5 | H17: N | I17: N | M17: =IF($B17="","",IFERROR(INDEX(Rubric!$C$14:$C$23,MATCH($B17,Rubric!$A$14:$A$23,0)),INDEX(Rubric!$C$14:$C$23,MATCH("other",Rubric!$A$14:$A$23,0)))) -> 11 | N17: =IF(OR($A17="",$C17=""),"",$C17*Rubric!$B$5+$D17*Rubric!$B$6+$E17*Rubric!$B$7+$F17*Rubric!$B$8+$G17*Rubric!$B$9) -> 4.4 | O17: =IF($A17="","",IF(OR(UPPER($H17)="Y",UPPER($I17)="Y"),"FAIL","PASS")) -> PASS | P17: =IF($N17="","",Assumptions!$B$6*MAX(0.05,($N17/Assumptions!$B$11)^Assumptions!$B$12)) -> 0.014666667 | Q17: =IF($P17="","",1-(1-$P17)^Assumptions!$B$7) -> 0.071213541 | R17: =IF($M17="","",$M17*Assumptions!$B$7) -> 55 | S17: =IF(OR($J17="",$Q17="",$Q17=0),"",($J17+$R17)/($Q17*(1-Assumptions!$B$4))) | T17: =IF(OR($K17="",$S17="",$S17=0),"",$K17/$S17) | U17: =IF(OR($K17="",$Q17=""),"",MAX(0,($K17-MAX($K17*Assumptions!$B$4,Assumptions!$B$5))*$Q17-$R17)) | V17: =IF($A17="","",IF($O17="FAIL","REJECT",IF($J17="","NEEDS PRICE",IF(OR($K17="",$L17=""),"NEEDS VALUATION",IF($T17>=Assumptions!$B$13,"BUY",IF($T17>=1,"MARGINAL","PASS")))))) -> NEEDS PRICE | W17: Taken | X17: [T2] Fleet is high-ticket and repeat-purchase.
A18: cranefinancing.com | B18: =IF($A18="","",IF(ISERROR(FIND(".",$A18)),"",LOWER(MID($A18,FIND(CHAR(1),SUBSTITUTE($A18,".",CHAR(1),LEN($A18)-LEN(SUBSTITUTE($A18,".",""))))+1,LEN($A18))))) -> com | C18: =IF($B18="","",IFERROR(INDEX(Rubric!$B$14:$B$23,MATCH($B18,Rubric!$A$14:$A$23,0)),INDEX(Rubric!$B$14:$B$23,MATCH("other",Rubric!$A$14:$A$23,0)))) -> 5 | D18: 4 | E18: 2 | F18: 4 | G18: 5 | H18: N | I18: N | J18: 5000 | M18: =IF($B18="","",IFERROR(INDEX(Rubric!$C$14:$C$23,MATCH($B18,Rubric!$A$14:$A$23,0)),INDEX(Rubric!$C$14:$C$23,MATCH("other",Rubric!$A$14:$A$23,0)))) -> 11 | N18: =IF(OR($A18="",$C18=""),"",$C18*Rubric!$B$5+$D18*Rubric!$B$6+$E18*Rubric!$B$7+$F18*Rubric!$B$8+$G18*Rubric!$B$9) -> 3.88 | O18: =IF($A18="","",IF(OR(UPPER($H18)="Y",UPPER($I18)="Y"),"FAIL","PASS")) -> PASS | P18: =IF($N18="","",Assumptions!$B$6*MAX(0.05,($N18/Assumptions!$B$11)^Assumptions!$B$12)) -> 0.012933333 | Q18: =IF($P18="","",1-(1-$P18)^Assumptions!$B$7) -> 0.06301545 | R18: =IF($M18="","",$M18*Assumptions!$B$7) -> 55 | S18: =IF(OR($J18="",$Q18="",$Q18=0),"",($J18+$R18)/($Q18*(1-Assumptions!$B$4))) -> 100273.03 | T18: =IF(OR($K18="",$S18="",$S18=0),"",$K18/$S18) | U18: =IF(OR($K18="",$Q18=""),"",MAX(0,($K18-MAX($K18*Assumptions!$B$4,Assumptions!$B$5))*$Q18-$R18)) | V18: =IF($A18="","",IF($O18="FAIL","REJECT",IF($J18="","NEEDS PRICE",IF(OR($K18="",$L18=""),"NEEDS VALUATION",IF($T18>=Assumptions!$B$13,"BUY",IF($T18>=1,"MARGINAL","PASS")))))) -> NEEDS VALUATION | W18: Available - premium | X18: [T2] Heavy construction niche, small but wealthy buyer pool.
A19: truckfinancing.com | B19: =IF($A19="","",IF(ISERROR(FIND(".",$A19)),"",LOWER(MID($A19,FIND(CHAR(1),SUBSTITUTE($A19,".",CHAR(1),LEN($A19)-LEN(SUBSTITUTE($A19,".",""))))+1,LEN($A19))))) -> com | C19: =IF($B19="","",IFERROR(INDEX(Rubric!$B$14:$B$23,MATCH($B19,Rubric!$A$14:$A$23,0)),INDEX(Rubric!$B$14:$B$23,MATCH("other",Rubric!$A$14:$A$23,0)))) -> 5 | D19: 5 | E19: 3 | F19: 4 | G19: 5 | H19: N | I19: N | J19: 375000 | M19: =IF($B19="","",IFERROR(INDEX(Rubric!$C$14:$C$23,MATCH($B19,Rubric!$A$14:$A$23,0)),INDEX(Rubric!$C$14:$C$23,MATCH("other",Rubric!$A$14:$A$23,0)))) -> 11 | N19: =IF(OR($A19="",$C19=""),"",$C19*Rubric!$B$5+$D19*Rubric!$B$6+$E19*Rubric!$B$7+$F19*Rubric!$B$8+$G19*Rubric!$B$9) -> 4.4 | O19: =IF($A19="","",IF(OR(UPPER($H19)="Y",UPPER($I19)="Y"),"FAIL","PASS")) -> PASS | P19: =IF($N19="","",Assumptions!$B$6*MAX(0.05,($N19/Assumptions!$B$11)^Assumptions!$B$12)) -> 0.014666667 | Q19: =IF($P19="","",1-(1-$P19)^Assumptions!$B$7) -> 0.071213541 | R19: =IF($M19="","",$M19*Assumptions!$B$7) -> 55 | S19: =IF(OR($J19="",$Q19="",$Q19=0),"",($J19+$R19)/($Q19*(1-Assumptions!$B$4))) -> 6583281 | T19: =IF(OR($K19="",$S19="",$S19=0),"",$K19/$S19) | U19: =IF(OR($K19="",$Q19=""),"",MAX(0,($K19-MAX($K19*Assumptions!$B$4,Assumptions!$B$5))*$Q19-$R19)) | V19: =IF($A19="","",IF($O19="FAIL","REJECT",IF($J19="","NEEDS PRICE",IF(OR($K19="",$L19=""),"NEEDS VALUATION",IF($T19>=Assumptions!$B$13,"BUY",IF($T19>=1,"MARGINAL","PASS")))))) -> NEEDS VALUATION | W19: Available - premium | X19: [T2] Trucking is the single biggest equipment-finance vertical.
A20: trailerfinancing.com | B20: =IF($A20="","",IF(ISERROR(FIND(".",$A20)),"",LOWER(MID($A20,FIND(CHAR(1),SUBSTITUTE($A20,".",CHAR(1),LEN($A20)-LEN(SUBSTITUTE($A20,".",""))))+1,LEN($A20))))) -> com | C20: =IF($B20="","",IFERROR(INDEX(Rubric!$B$14:$B$23,MATCH($B20,Rubric!$A$14:$A$23,0)),INDEX(Rubric!$B$14:$B$23,MATCH("other",Rubric!$A$14:$A$23,0)))) -> 5 | D20: 4 | E20: 2 | F20: 3 | G20: 5 | H20: N | I20: N | J20: 4888 | M20: =IF($B20="","",IFERROR(INDEX(Rubric!$C$14:$C$23,MATCH($B20,Rubric!$A$14:$A$23,0)),INDEX(Rubric!$C$14:$C$23,MATCH("other",Rubric!$A$14:$A$23,0)))) -> 11 | N20: =IF(OR($A20="",$C20=""),"",$C20*Rubric!$B$5+$D20*Rubric!$B$6+$E20*Rubric!$B$7+$F20*Rubric!$B$8+$G20*Rubric!$B$9) -> 3.72 | O20: =IF($A20="","",IF(OR(UPPER($H20)="Y",UPPER($I20)="Y"),"FAIL","PASS")) -> PASS | P20: =IF($N20="","",Assumptions!$B$6*MAX(0.05,($N20/Assumptions!$B$11)^Assumptions!$B$12)) -> 0.0124 | Q20: =IF($P20="","",1-(1-$P20)^Assumptions!$B$7) -> 0.060481348 | R20: =IF($M20="","",$M20*Assumptions!$B$7) -> 55 | S20: =IF(OR($J20="",$Q20="",$Q20=0),"",($J20+$R20)/($Q20*(1-Assumptions!$B$4))) -> 102159.59 | T20: =IF(OR($K20="",$S20="",$S20=0),"",$K20/$S20) | U20: =IF(OR($K20="",$Q20=""),"",MAX(0,($K20-MAX($K20*Assumptions!$B$4,Assumptions!$B$5))*$Q20-$R20)) | V20: =IF($A20="","",IF($O20="FAIL","REJECT",IF($J20="","NEEDS PRICE",IF(OR($K20="",$L20=""),"NEEDS VALUATION",IF($T20>=Assumptions!$B$13,"BUY",IF($T20>=1,"MARGINAL","PASS")))))) -> NEEDS VALUATION | W20: Available - premium | X20: [T2] Adjacent to trucking.
A21: dentalfinancing.com | B21: =IF($A21="","",IF(ISERROR(FIND(".",$A21)),"",LOWER(MID($A21,FIND(CHAR(1),SUBSTITUTE($A21,".",CHAR(1),LEN($A21)-LEN(SUBSTITUTE($A21,".",""))))+1,LEN($A21))))) -> com | C21: =IF($B21="","",IFERROR(INDEX(Rubric!$B$14:$B$23,MATCH($B21,Rubric!$A$14:$A$23,0)),INDEX(Rubric!$B$14:$B$23,MATCH("other",Rubric!$A$14:$A$23,0)))) -> 5 | D21: 4 | E21: 3 | F21: 3 | G21: 5 | H21: N | I21: N | M21: =IF($B21="","",IFERROR(INDEX(Rubric!$C$14:$C$23,MATCH($B21,Rubric!$A$14:$A$23,0)),INDEX(Rubric!$C$14:$C$23,MATCH("other",Rubric!$A$14:$A$23,0)))) -> 11 | N21: =IF(OR($A21="",$C21=""),"",$C21*Rubric!$B$5+$D21*Rubric!$B$6+$E21*Rubric!$B$7+$F21*Rubric!$B$8+$G21*Rubric!$B$9) -> 3.94 | O21: =IF($A21="","",IF(OR(UPPER($H21)="Y",UPPER($I21)="Y"),"FAIL","PASS")) -> PASS | P21: =IF($N21="","",Assumptions!$B$6*MAX(0.05,($N21/Assumptions!$B$11)^Assumptions!$B$12)) -> 0.013133333 | Q21: =IF($P21="","",1-(1-$P21)^Assumptions!$B$7) -> 0.063964327 | R21: =IF($M21="","",$M21*Assumptions!$B$7) -> 55 | S21: =IF(OR($J21="",$Q21="",$Q21=0),"",($J21+$R21)/($Q21*(1-Assumptions!$B$4))) | T21: =IF(OR($K21="",$S21="",$S21=0),"",$K21/$S21) | U21: =IF(OR($K21="",$Q21=""),"",MAX(0,($K21-MAX($K21*Assumptions!$B$4,Assumptions!$B$5))*$Q21-$R21)) | V21: =IF($A21="","",IF($O21="FAIL","REJECT",IF($J21="","NEEDS PRICE",IF(OR($K21="",$L21=""),"NEEDS VALUATION",IF($T21>=Assumptions!$B$13,"BUY",IF($T21>=1,"MARGINAL","PASS")))))) -> NEEDS PRICE | W21: Taken | X21: [T2] Dental practices finance chairs and imaging constantly.
A22: medicalleasing.com | B22: =IF($A22="","",IF(ISERROR(FIND(".",$A22)),"",LOWER(MID($A22,FIND(CHAR(1),SUBSTITUTE($A22,".",CHAR(1),LEN($A22)-LEN(SUBSTITUTE($A22,".",""))))+1,LEN($A22))))) -> com | C22: =IF($B22="","",IFERROR(INDEX(Rubric!$B$14:$B$23,MATCH($B22,Rubric!$A$14:$A$23,0)),INDEX(Rubric!$B$14:$B$23,MATCH("other",Rubric!$A$14:$A$23,0)))) -> 5 | D22: 4 | E22: 3 | F22: 4 | G22: 4 | H22: N | I22: N | M22: =IF($B22="","",IFERROR(INDEX(Rubric!$C$14:$C$23,MATCH($B22,Rubric!$A$14:$A$23,0)),INDEX(Rubric!$C$14:$C$23,MATCH("other",Rubric!$A$14:$A$23,0)))) -> 11 | N22: =IF(OR($A22="",$C22=""),"",$C22*Rubric!$B$5+$D22*Rubric!$B$6+$E22*Rubric!$B$7+$F22*Rubric!$B$8+$G22*Rubric!$B$9) -> 4 | O22: =IF($A22="","",IF(OR(UPPER($H22)="Y",UPPER($I22)="Y"),"FAIL","PASS")) -> PASS | P22: =IF($N22="","",Assumptions!$B$6*MAX(0.05,($N22/Assumptions!$B$11)^Assumptions!$B$12)) -> 0.013333333 | Q22: =IF($P22="","",1-(1-$P22)^Assumptions!$B$7) -> 0.064912435 | R22: =IF($M22="","",$M22*Assumptions!$B$7) -> 55 | S22: =IF(OR($J22="",$Q22="",$Q22=0),"",($J22+$R22)/($Q22*(1-Assumptions!$B$4))) | T22: =IF(OR($K22="",$S22="",$S22=0),"",$K22/$S22) | U22: =IF(OR($K22="",$Q22=""),"",MAX(0,($K22-MAX($K22*Assumptions!$B$4,Assumptions!$B$5))*$Q22-$R22)) | V22: =IF($A22="","",IF($O22="FAIL","REJECT",IF($J22="","NEEDS PRICE",IF(OR($K22="",$L22=""),"NEEDS VALUATION",IF($T22>=Assumptions!$B$13,"BUY",IF($T22>=1,"MARGINAL","PASS")))))) -> NEEDS PRICE | W22: Taken | X22: [T2] Imaging and diagnostic equipment leasing.
A23: solarfinancing.com | B23: =IF($A23="","",IF(ISERROR(FIND(".",$A23)),"",LOWER(MID($A23,FIND(CHAR(1),SUBSTITUTE($A23,".",CHAR(1),LEN($A23)-LEN(SUBSTITUTE($A23,".",""))))+1,LEN($A23))))) -> com | C23: =IF($B23="","",IFERROR(INDEX(Rubric!$B$14:$B$23,MATCH($B23,Rubric!$A$14:$A$23,0)),INDEX(Rubric!$B$14:$B$23,MATCH("other",Rubric!$A$14:$A$23,0)))) -> 5 | D23: 4 | E23: 3 | F23: 4 | G23: 5 | H23: N | I23: N | M23: =IF($B23="","",IFERROR(INDEX(Rubric!$C$14:$C$23,MATCH($B23,Rubric!$A$14:$A$23,0)),INDEX(Rubric!$C$14:$C$23,MATCH("other",Rubric!$A$14:$A$23,0)))) -> 11 | N23: =IF(OR($A23="",$C23=""),"",$C23*Rubric!$B$5+$D23*Rubric!$B$6+$E23*Rubric!$B$7+$F23*Rubric!$B$8+$G23*Rubric!$B$9) -> 4.1 | O23: =IF($A23="","",IF(OR(UPPER($H23)="Y",UPPER($I23)="Y"),"FAIL","PASS")) -> PASS | P23: =IF($N23="","",Assumptions!$B$6*MAX(0.05,($N23/Assumptions!$B$11)^Assumptions!$B$12)) -> 0.013666667 | Q23: =IF($P23="","",1-(1-$P23)^Assumptions!$B$7) -> 0.066490908 | R23: =IF($M23="","",$M23*Assumptions!$B$7) -> 55 | S23: =IF(OR($J23="",$Q23="",$Q23=0),"",($J23+$R23)/($Q23*(1-Assumptions!$B$4))) | T23: =IF(OR($K23="",$S23="",$S23=0),"",$K23/$S23) | U23: =IF(OR($K23="",$Q23=""),"",MAX(0,($K23-MAX($K23*Assumptions!$B$4,Assumptions!$B$5))*$Q23-$R23)) | V23: =IF($A23="","",IF($O23="FAIL","REJECT",IF($J23="","NEEDS PRICE",IF(OR($K23="",$L23=""),"NEEDS VALUATION",IF($T23>=Assumptions!$B$13,"BUY",IF($T23>=1,"MARGINAL","PASS")))))) -> NEEDS PRICE | W23: Taken | X23: [T2] Commercial solar is heavily financed.
A24: brewingfinancing.com | B24: =IF($A24="","",IF(ISERROR(FIND(".",$A24)),"",LOWER(MID($A24,FIND(CHAR(1),SUBSTITUTE($A24,".",CHAR(1),LEN($A24)-LEN(SUBSTITUTE($A24,".",""))))+1,LEN($A24))))) -> com | C24: =IF($B24="","",IFERROR(INDEX(Rubric!$B$14:$B$23,MATCH($B24,Rubric!$A$14:$A$23,0)),INDEX(Rubric!$B$14:$B$23,MATCH("other",Rubric!$A$14:$A$23,0)))) -> 5 | D24: 3 | E24: 2 | F24: 3 | G24: 4 | H24: N | I24: N | J24: 22.99 | K24: 285 | L24: HumbleWorth brokerage 2026-08-03 (mktpl $59, auction $0) | M24: =IF($B24="","",IFERROR(INDEX(Rubric!$C$14:$C$23,MATCH($B24,Rubric!$A$14:$A$23,0)),INDEX(Rubric!$C$14:$C$23,MATCH("other",Rubric!$A$14:$A$23,0)))) -> 11 | N24: =IF(OR($A24="",$C24=""),"",$C24*Rubric!$B$5+$D24*Rubric!$B$6+$E24*Rubric!$B$7+$F24*Rubric!$B$8+$G24*Rubric!$B$9) -> 3.32 | O24: =IF($A24="","",IF(OR(UPPER($H24)="Y",UPPER($I24)="Y"),"FAIL","PASS")) -> PASS | P24: =IF($N24="","",Assumptions!$B$6*MAX(0.05,($N24/Assumptions!$B$11)^Assumptions!$B$12)) -> 0.011066667 | Q24: =IF($P24="","",1-(1-$P24)^Assumptions!$B$7) -> 0.054122101 | R24: =IF($M24="","",$M24*Assumptions!$B$7) -> 55 | S24: =IF(OR($J24="",$Q24="",$Q24=0),"",($J24+$R24)/($Q24*(1-Assumptions!$B$4))) -> 1801.2512 | T24: =IF(OR($K24="",$S24="",$S24=0),"",$K24/$S24) -> 0.15822335 | U24: =IF(OR($K24="",$Q24=""),"",MAX(0,($K24-MAX($K24*Assumptions!$B$4,Assumptions!$B$5))*$Q24-$R24)) -> 0 | V24: =IF($A24="","",IF($O24="FAIL","REJECT",IF($J24="","NEEDS PRICE",IF(OR($K24="",$L24=""),"NEEDS VALUATION",IF($T24>=Assumptions!$B$13,"BUY",IF($T24>=1,"MARGINAL","PASS")))))) -> PASS | W24: Available - reg | X24: [T2] Narrow. Included as a deliberate low-scorer for contrast.
A25: kitchenfinancing.com | B25: =IF($A25="","",IF(ISERROR(FIND(".",$A25)),"",LOWER(MID($A25,FIND(CHAR(1),SUBSTITUTE($A25,".",CHAR(1),LEN($A25)-LEN(SUBSTITUTE($A25,".",""))))+1,LEN($A25))))) -> com | C25: =IF($B25="","",IFERROR(INDEX(Rubric!$B$14:$B$23,MATCH($B25,Rubric!$A$14:$A$23,0)),INDEX(Rubric!$B$14:$B$23,MATCH("other",Rubric!$A$14:$A$23,0)))) -> 5 | D25: 3 | E25: 2 | F25: 3 | G25: 4 | H25: N | I25: N | J25: 2788 | M25: =IF($B25="","",IFERROR(INDEX(Rubric!$C$14:$C$23,MATCH($B25,Rubric!$A$14:$A$23,0)),INDEX(Rubric!$C$14:$C$23,MATCH("other",Rubric!$A$14:$A$23,0)))) -> 11 | N25: =IF(OR($A25="",$C25=""),"",$C25*Rubric!$B$5+$D25*Rubric!$B$6+$E25*Rubric!$B$7+$F25*Rubric!$B$8+$G25*Rubric!$B$9) -> 3.32 | O25: =IF($A25="","",IF(OR(UPPER($H25)="Y",UPPER($I25)="Y"),"FAIL","PASS")) -> PASS | P25: =IF($N25="","",Assumptions!$B$6*MAX(0.05,($N25/Assumptions!$B$11)^Assumptions!$B$12)) -> 0.011066667 | Q25: =IF($P25="","",1-(1-$P25)^Assumptions!$B$7) -> 0.054122101 | R25: =IF($M25="","",$M25*Assumptions!$B$7) -> 55 | S25: =IF(OR($J25="",$Q25="",$Q25=0),"",($J25+$R25)/($Q25*(1-Assumptions!$B$4))) -> 65661.716 | T25: =IF(OR($K25="",$S25="",$S25=0),"",$K25/$S25) | U25: =IF(OR($K25="",$Q25=""),"",MAX(0,($K25-MAX($K25*Assumptions!$B$4,Assumptions!$B$5))*$Q25-$R25)) | V25: =IF($A25="","",IF($O25="FAIL","REJECT",IF($J25="","NEEDS PRICE",IF(OR($K25="",$L25=""),"NEEDS VALUATION",IF($T25>=Assumptions!$B$13,"BUY",IF($T25>=1,"MARGINAL","PASS")))))) -> NEEDS VALUATION | W25: Available - premium | X25: [T2] Restaurant build-outs. Ambiguous — reads residential.
A26: hvacfinancing.com | B26: =IF($A26="","",IF(ISERROR(FIND(".",$A26)),"",LOWER(MID($A26,FIND(CHAR(1),SUBSTITUTE($A26,".",CHAR(1),LEN($A26)-LEN(SUBSTITUTE($A26,".",""))))+1,LEN($A26))))) -> com | C26: =IF($B26="","",IFERROR(INDEX(Rubric!$B$14:$B$23,MATCH($B26,Rubric!$A$14:$A$23,0)),INDEX(Rubric!$B$14:$B$23,MATCH("other",Rubric!$A$14:$A$23,0)))) -> 5 | D26: 4 | E26: 3 | F26: 4 | G26: 4 | H26: N | I26: N | M26: =IF($B26="","",IFERROR(INDEX(Rubric!$C$14:$C$23,MATCH($B26,Rubric!$A$14:$A$23,0)),INDEX(Rubric!$C$14:$C$23,MATCH("other",Rubric!$A$14:$A$23,0)))) -> 11 | N26: =IF(OR($A26="",$C26=""),"",$C26*Rubric!$B$5+$D26*Rubric!$B$6+$E26*Rubric!$B$7+$F26*Rubric!$B$8+$G26*Rubric!$B$9) -> 4 | O26: =IF($A26="","",IF(OR(UPPER($H26)="Y",UPPER($I26)="Y"),"FAIL","PASS")) -> PASS | P26: =IF($N26="","",Assumptions!$B$6*MAX(0.05,($N26/Assumptions!$B$11)^Assumptions!$B$12)) -> 0.013333333 | Q26: =IF($P26="","",1-(1-$P26)^Assumptions!$B$7) -> 0.064912435 | R26: =IF($M26="","",$M26*Assumptions!$B$7) -> 55 | S26: =IF(OR($J26="",$Q26="",$Q26=0),"",($J26+$R26)/($Q26*(1-Assumptions!$B$4))) | T26: =IF(OR($K26="",$S26="",$S26=0),"",$K26/$S26) | U26: =IF(OR($K26="",$Q26=""),"",MAX(0,($K26-MAX($K26*Assumptions!$B$4,Assumptions!$B$5))*$Q26-$R26)) | V26: =IF($A26="","",IF($O26="FAIL","REJECT",IF($J26="","NEEDS PRICE",IF(OR($K26="",$L26=""),"NEEDS VALUATION",IF($T26>=Assumptions!$B$13,"BUY",IF($T26>=1,"MARGINAL","PASS")))))) -> NEEDS PRICE | W26: Taken | X26: [T2] Contractor equipment plus consumer-facing crossover.
A27: printfinancing.com | B27: =IF($A27="","",IF(ISERROR(FIND(".",$A27)),"",LOWER(MID($A27,FIND(CHAR(1),SUBSTITUTE($A27,".",CHAR(1),LEN($A27)-LEN(SUBSTITUTE($A27,".",""))))+1,LEN($A27))))) -> com | C27: =IF($B27="","",IFERROR(INDEX(Rubric!$B$14:$B$23,MATCH($B27,Rubric!$A$14:$A$23,0)),INDEX(Rubric!$B$14:$B$23,MATCH("other",Rubric!$A$14:$A$23,0)))) -> 5 | D27: 3 | E27: 2 | F27: 4 | G27: 4 | H27: N | I27: N | J27: 22.99 | M27: =IF($B27="","",IFERROR(INDEX(Rubric!$C$14:$C$23,MATCH($B27,Rubric!$A$14:$A$23,0)),INDEX(Rubric!$C$14:$C$23,MATCH("other",Rubric!$A$14:$A$23,0)))) -> 11 | N27: =IF(OR($A27="",$C27=""),"",$C27*Rubric!$B$5+$D27*Rubric!$B$6+$E27*Rubric!$B$7+$F27*Rubric!$B$8+$G27*Rubric!$B$9) -> 3.48 | O27: =IF($A27="","",IF(OR(UPPER($H27)="Y",UPPER($I27)="Y"),"FAIL","PASS")) -> PASS | P27: =IF($N27="","",Assumptions!$B$6*MAX(0.05,($N27/Assumptions!$B$11)^Assumptions!$B$12)) -> 0.0116 | Q27: =IF($P27="","",1-(1-$P27)^Assumptions!$B$7) -> 0.056669919 | R27: =IF($M27="","",$M27*Assumptions!$B$7) -> 55 | S27: =IF(OR($J27="",$Q27="",$Q27=0),"",($J27+$R27)/($Q27*(1-Assumptions!$B$4))) -> 1720.2689 | T27: =IF(OR($K27="",$S27="",$S27=0),"",$K27/$S27) | U27: =IF(OR($K27="",$Q27=""),"",MAX(0,($K27-MAX($K27*Assumptions!$B$4,Assumptions!$B$5))*$Q27-$R27)) | V27: =IF($A27="","",IF($O27="FAIL","REJECT",IF($J27="","NEEDS PRICE",IF(OR($K27="",$L27=""),"NEEDS VALUATION",IF($T27>=Assumptions!$B$13,"BUY",IF($T27>=1,"MARGINAL","PASS")))))) -> NEEDS VALUATION | W27: Available - reg | X27: [T2] Commercial printing is a shrinking sector.
A28: laundryfinancing.com | B28: =IF($A28="","",IF(ISERROR(FIND(".",$A28)),"",LOWER(MID($A28,FIND(CHAR(1),SUBSTITUTE($A28,".",CHAR(1),LEN($A28)-LEN(SUBSTITUTE($A28,".",""))))+1,LEN($A28))))) -> com | C28: =IF($B28="","",IFERROR(INDEX(Rubric!$B$14:$B$23,MATCH($B28,Rubric!$A$14:$A$23,0)),INDEX(Rubric!$B$14:$B$23,MATCH("other",Rubric!$A$14:$A$23,0)))) -> 5 | D28: 3 | E28: 2 | F28: 3 | G28: 4 | H28: N | I28: N | M28: =IF($B28="","",IFERROR(INDEX(Rubric!$C$14:$C$23,MATCH($B28,Rubric!$A$14:$A$23,0)),INDEX(Rubric!$C$14:$C$23,MATCH("other",Rubric!$A$14:$A$23,0)))) -> 11 | N28: =IF(OR($A28="",$C28=""),"",$C28*Rubric!$B$5+$D28*Rubric!$B$6+$E28*Rubric!$B$7+$F28*Rubric!$B$8+$G28*Rubric!$B$9) -> 3.32 | O28: =IF($A28="","",IF(OR(UPPER($H28)="Y",UPPER($I28)="Y"),"FAIL","PASS")) -> PASS | P28: =IF($N28="","",Assumptions!$B$6*MAX(0.05,($N28/Assumptions!$B$11)^Assumptions!$B$12)) -> 0.011066667 | Q28: =IF($P28="","",1-(1-$P28)^Assumptions!$B$7) -> 0.054122101 | R28: =IF($M28="","",$M28*Assumptions!$B$7) -> 55 | S28: =IF(OR($J28="",$Q28="",$Q28=0),"",($J28+$R28)/($Q28*(1-Assumptions!$B$4))) | T28: =IF(OR($K28="",$S28="",$S28=0),"",$K28/$S28) | U28: =IF(OR($K28="",$Q28=""),"",MAX(0,($K28-MAX($K28*Assumptions!$B$4,Assumptions!$B$5))*$Q28-$R28)) | V28: =IF($A28="","",IF($O28="FAIL","REJECT",IF($J28="","NEEDS PRICE",IF(OR($K28="",$L28=""),"NEEDS VALUATION",IF($T28>=Assumptions!$B$13,"BUY",IF($T28>=1,"MARGINAL","PASS")))))) -> NEEDS PRICE | W28: Taken | X28: [T2] Laundromat equipment is genuinely financed, small pool.
A29: gymfinancing.com | B29: =IF($A29="","",IF(ISERROR(FIND(".",$A29)),"",LOWER(MID($A29,FIND(CHAR(1),SUBSTITUTE($A29,".",CHAR(1),LEN($A29)-LEN(SUBSTITUTE($A29,".",""))))+1,LEN($A29))))) -> com | C29: =IF($B29="","",IFERROR(INDEX(Rubric!$B$14:$B$23,MATCH($B29,Rubric!$A$14:$A$23,0)),INDEX(Rubric!$B$14:$B$23,MATCH("other",Rubric!$A$14:$A$23,0)))) -> 5 | D29: 3 | E29: 2 | F29: 4 | G29: 4 | H29: N | I29: N | J29: 18800 | M29: =IF($B29="","",IFERROR(INDEX(Rubric!$C$14:$C$23,MATCH($B29,Rubric!$A$14:$A$23,0)),INDEX(Rubric!$C$14:$C$23,MATCH("other",Rubric!$A$14:$A$23,0)))) -> 11 | N29: =IF(OR($A29="",$C29=""),"",$C29*Rubric!$B$5+$D29*Rubric!$B$6+$E29*Rubric!$B$7+$F29*Rubric!$B$8+$G29*Rubric!$B$9) -> 3.48 | O29: =IF($A29="","",IF(OR(UPPER($H29)="Y",UPPER($I29)="Y"),"FAIL","PASS")) -> PASS | P29: =IF($N29="","",Assumptions!$B$6*MAX(0.05,($N29/Assumptions!$B$11)^Assumptions!$B$12)) -> 0.0116 | Q29: =IF($P29="","",1-(1-$P29)^Assumptions!$B$7) -> 0.056669919 | R29: =IF($M29="","",$M29*Assumptions!$B$7) -> 55 | S29: =IF(OR($J29="",$Q29="",$Q29=0),"",($J29+$R29)/($Q29*(1-Assumptions!$B$4))) -> 415895.25 | T29: =IF(OR($K29="",$S29="",$S29=0),"",$K29/$S29) | U29: =IF(OR($K29="",$Q29=""),"",MAX(0,($K29-MAX($K29*Assumptions!$B$4,Assumptions!$B$5))*$Q29-$R29)) | V29: =IF($A29="","",IF($O29="FAIL","REJECT",IF($J29="","NEEDS PRICE",IF(OR($K29="",$L29=""),"NEEDS VALUATION",IF($T29>=Assumptions!$B$13,"BUY",IF($T29>=1,"MARGINAL","PASS")))))) -> NEEDS VALUATION | W29: Available - premium | X29: [T2] Fitness equipment leasing.
A30: farmfinancing.com | B30: =IF($A30="","",IF(ISERROR(FIND(".",$A30)),"",LOWER(MID($A30,FIND(CHAR(1),SUBSTITUTE($A30,".",CHAR(1),LEN($A30)-LEN(SUBSTITUTE($A30,".",""))))+1,LEN($A30))))) -> com | C30: =IF($B30="","",IFERROR(INDEX(Rubric!$B$14:$B$23,MATCH($B30,Rubric!$A$14:$A$23,0)),INDEX(Rubric!$B$14:$B$23,MATCH("other",Rubric!$A$14:$A$23,0)))) -> 5 | D30: 4 | E30: 3 | F30: 4 | G30: 5 | H30: N | I30: N | M30: =IF($B30="","",IFERROR(INDEX(Rubric!$C$14:$C$23,MATCH($B30,Rubric!$A$14:$A$23,0)),INDEX(Rubric!$C$14:$C$23,MATCH("other",Rubric!$A$14:$A$23,0)))) -> 11 | N30: =IF(OR($A30="",$C30=""),"",$C30*Rubric!$B$5+$D30*Rubric!$B$6+$E30*Rubric!$B$7+$F30*Rubric!$B$8+$G30*Rubric!$B$9) -> 4.1 | O30: =IF($A30="","",IF(OR(UPPER($H30)="Y",UPPER($I30)="Y"),"FAIL","PASS")) -> PASS | P30: =IF($N30="","",Assumptions!$B$6*MAX(0.05,($N30/Assumptions!$B$11)^Assumptions!$B$12)) -> 0.013666667 | Q30: =IF($P30="","",1-(1-$P30)^Assumptions!$B$7) -> 0.066490908 | R30: =IF($M30="","",$M30*Assumptions!$B$7) -> 55 | S30: =IF(OR($J30="",$Q30="",$Q30=0),"",($J30+$R30)/($Q30*(1-Assumptions!$B$4))) | T30: =IF(OR($K30="",$S30="",$S30=0),"",$K30/$S30) | U30: =IF(OR($K30="",$Q30=""),"",MAX(0,($K30-MAX($K30*Assumptions!$B$4,Assumptions!$B$5))*$Q30-$R30)) | V30: =IF($A30="","",IF($O30="FAIL","REJECT",IF($J30="","NEEDS PRICE",IF(OR($K30="",$L30=""),"NEEDS VALUATION",IF($T30>=Assumptions!$B$13,"BUY",IF($T30>=1,"MARGINAL","PASS")))))) -> NEEDS PRICE | W30: Taken | X30: [T2] Ag equipment is a major financed category.
A31: agequipmentloans.com | B31: =IF($A31="","",IF(ISERROR(FIND(".",$A31)),"",LOWER(MID($A31,FIND(CHAR(1),SUBSTITUTE($A31,".",CHAR(1),LEN($A31)-LEN(SUBSTITUTE($A31,".",""))))+1,LEN($A31))))) -> com | C31: =IF($B31="","",IFERROR(INDEX(Rubric!$B$14:$B$23,MATCH($B31,Rubric!$A$14:$A$23,0)),INDEX(Rubric!$B$14:$B$23,MATCH("other",Rubric!$A$14:$A$23,0)))) -> 5 | D31: 3 | E31: 2 | F31: 3 | G31: 3 | H31: N | I31: N | J31: 22.99 | M31: =IF($B31="","",IFERROR(INDEX(Rubric!$C$14:$C$23,MATCH($B31,Rubric!$A$14:$A$23,0)),INDEX(Rubric!$C$14:$C$23,MATCH("other",Rubric!$A$14:$A$23,0)))) -> 11 | N31: =IF(OR($A31="",$C31=""),"",$C31*Rubric!$B$5+$D31*Rubric!$B$6+$E31*Rubric!$B$7+$F31*Rubric!$B$8+$G31*Rubric!$B$9) -> 3.22 | O31: =IF($A31="","",IF(OR(UPPER($H31)="Y",UPPER($I31)="Y"),"FAIL","PASS")) -> PASS | P31: =IF($N31="","",Assumptions!$B$6*MAX(0.05,($N31/Assumptions!$B$11)^Assumptions!$B$12)) -> 0.010733333 | Q31: =IF($P31="","",1-(1-$P31)^Assumptions!$B$7) -> 0.052526921 | R31: =IF($M31="","",$M31*Assumptions!$B$7) -> 55 | S31: =IF(OR($J31="",$Q31="",$Q31=0),"",($J31+$R31)/($Q31*(1-Assumptions!$B$4))) -> 1855.9531 | T31: =IF(OR($K31="",$S31="",$S31=0),"",$K31/$S31) | U31: =IF(OR($K31="",$Q31=""),"",MAX(0,($K31-MAX($K31*Assumptions!$B$4,Assumptions!$B$5))*$Q31-$R31)) | V31: =IF($A31="","",IF($O31="FAIL","REJECT",IF($J31="","NEEDS PRICE",IF(OR($K31="",$L31=""),"NEEDS VALUATION",IF($T31>=Assumptions!$B$13,"BUY",IF($T31>=1,"MARGINAL","PASS")))))) -> NEEDS VALUATION | W31: Available - reg | X31: [T2] 'ag' reads as ambiguous when spoken. Weak radio test.
A32: minefinancing.com | B32: =IF($A32="","",IF(ISERROR(FIND(".",$A32)),"",LOWER(MID($A32,FIND(CHAR(1),SUBSTITUTE($A32,".",CHAR(1),LEN($A32)-LEN(SUBSTITUTE($A32,".",""))))+1,LEN($A32))))) -> com | C32: =IF($B32="","",IFERROR(INDEX(Rubric!$B$14:$B$23,MATCH($B32,Rubric!$A$14:$A$23,0)),INDEX(Rubric!$B$14:$B$23,MATCH("other",Rubric!$A$14:$A$23,0)))) -> 5 | D32: 3 | E32: 2 | F32: 4 | G32: 3 | H32: N | I32: N | J32: 22.99 | M32: =IF($B32="","",IFERROR(INDEX(Rubric!$C$14:$C$23,MATCH($B32,Rubric!$A$14:$A$23,0)),INDEX(Rubric!$C$14:$C$23,MATCH("other",Rubric!$A$14:$A$23,0)))) -> 11 | N32: =IF(OR($A32="",$C32=""),"",$C32*Rubric!$B$5+$D32*Rubric!$B$6+$E32*Rubric!$B$7+$F32*Rubric!$B$8+$G32*Rubric!$B$9) -> 3.38 | O32: =IF($A32="","",IF(OR(UPPER($H32)="Y",UPPER($I32)="Y"),"FAIL","PASS")) -> PASS | P32: =IF($N32="","",Assumptions!$B$6*MAX(0.05,($N32/Assumptions!$B$11)^Assumptions!$B$12)) -> 0.011266667 | Q32: =IF($P32="","",1-(1-$P32)^Assumptions!$B$7) -> 0.055078177 | R32: =IF($M32="","",$M32*Assumptions!$B$7) -> 55 | S32: =IF(OR($J32="",$Q32="",$Q32=0),"",($J32+$R32)/($Q32*(1-Assumptions!$B$4))) -> 1769.9842 | T32: =IF(OR($K32="",$S32="",$S32=0),"",$K32/$S32) | U32: =IF(OR($K32="",$Q32=""),"",MAX(0,($K32-MAX($K32*Assumptions!$B$4,Assumptions!$B$5))*$Q32-$R32)) | V32: =IF($A32="","",IF($O32="FAIL","REJECT",IF($J32="","NEEDS PRICE",IF(OR($K32="",$L32=""),"NEEDS VALUATION",IF($T32>=Assumptions!$B$13,"BUY",IF($T32>=1,"MARGINAL","PASS")))))) -> NEEDS VALUATION | W32: Available - reg | X32: [T2] Mining equipment. 'mine' is a homophone trap.
A33: equipmentcapital.com | B33: =IF($A33="","",IF(ISERROR(FIND(".",$A33)),"",LOWER(MID($A33,FIND(CHAR(1),SUBSTITUTE($A33,".",CHAR(1),LEN($A33)-LEN(SUBSTITUTE($A33,".",""))))+1,LEN($A33))))) -> com | C33: =IF($B33="","",IFERROR(INDEX(Rubric!$B$14:$B$23,MATCH($B33,Rubric!$A$14:$A$23,0)),INDEX(Rubric!$B$14:$B$23,MATCH("other",Rubric!$A$14:$A$23,0)))) -> 5 | D33: 5 | E33: 3 | F33: 4 | G33: 5 | H33: N | I33: N | M33: =IF($B33="","",IFERROR(INDEX(Rubric!$C$14:$C$23,MATCH($B33,Rubric!$A$14:$A$23,0)),INDEX(Rubric!$C$14:$C$23,MATCH("other",Rubric!$A$14:$A$23,0)))) -> 11 | N33: =IF(OR($A33="",$C33=""),"",$C33*Rubric!$B$5+$D33*Rubric!$B$6+$E33*Rubric!$B$7+$F33*Rubric!$B$8+$G33*Rubric!$B$9) -> 4.4 | O33: =IF($A33="","",IF(OR(UPPER($H33)="Y",UPPER($I33)="Y"),"FAIL","PASS")) -> PASS | P33: =IF($N33="","",Assumptions!$B$6*MAX(0.05,($N33/Assumptions!$B$11)^Assumptions!$B$12)) -> 0.014666667 | Q33: =IF($P33="","",1-(1-$P33)^Assumptions!$B$7) -> 0.071213541 | R33: =IF($M33="","",$M33*Assumptions!$B$7) -> 55 | S33: =IF(OR($J33="",$Q33="",$Q33=0),"",($J33+$R33)/($Q33*(1-Assumptions!$B$4))) | T33: =IF(OR($K33="",$S33="",$S33=0),"",$K33/$S33) | U33: =IF(OR($K33="",$Q33=""),"",MAX(0,($K33-MAX($K33*Assumptions!$B$4,Assumptions!$B$5))*$Q33-$R33)) | V33: =IF($A33="","",IF($O33="FAIL","REJECT",IF($J33="","NEEDS PRICE",IF(OR($K33="",$L33=""),"NEEDS VALUATION",IF($T33>=Assumptions!$B$13,"BUY",IF($T33>=1,"MARGINAL","PASS")))))) -> NEEDS PRICE | W33: Taken | X33: [T3] Reads like a lender's own name — strong end-user appeal.
A34: equipmentfunding.com | B34: =IF($A34="","",IF(ISERROR(FIND(".",$A34)),"",LOWER(MID($A34,FIND(CHAR(1),SUBSTITUTE($A34,".",CHAR(1),LEN($A34)-LEN(SUBSTITUTE($A34,".",""))))+1,LEN($A34))))) -> com | C34: =IF($B34="","",IFERROR(INDEX(Rubric!$B$14:$B$23,MATCH($B34,Rubric!$A$14:$A$23,0)),INDEX(Rubric!$B$14:$B$23,MATCH("other",Rubric!$A$14:$A$23,0)))) -> 5 | D34: 5 | E34: 3 | F34: 4 | G34: 5 | H34: N | I34: N | M34: =IF($B34="","",IFERROR(INDEX(Rubric!$C$14:$C$23,MATCH($B34,Rubric!$A$14:$A$23,0)),INDEX(Rubric!$C$14:$C$23,MATCH("other",Rubric!$A$14:$A$23,0)))) -> 11 | N34: =IF(OR($A34="",$C34=""),"",$C34*Rubric!$B$5+$D34*Rubric!$B$6+$E34*Rubric!$B$7+$F34*Rubric!$B$8+$G34*Rubric!$B$9) -> 4.4 | O34: =IF($A34="","",IF(OR(UPPER($H34)="Y",UPPER($I34)="Y"),"FAIL","PASS")) -> PASS | P34: =IF($N34="","",Assumptions!$B$6*MAX(0.05,($N34/Assumptions!$B$11)^Assumptions!$B$12)) -> 0.014666667 | Q34: =IF($P34="","",1-(1-$P34)^Assumptions!$B$7) -> 0.071213541 | R34: =IF($M34="","",$M34*Assumptions!$B$7) -> 55 | S34: =IF(OR($J34="",$Q34="",$Q34=0),"",($J34+$R34)/($Q34*(1-Assumptions!$B$4))) | T34: =IF(OR($K34="",$S34="",$S34=0),"",$K34/$S34) | U34: =IF(OR($K34="",$Q34=""),"",MAX(0,($K34-MAX($K34*Assumptions!$B$4,Assumptions!$B$5))*$Q34-$R34)) | V34: =IF($A34="","",IF($O34="FAIL","REJECT",IF($J34="","NEEDS PRICE",IF(OR($K34="",$L34=""),"NEEDS VALUATION",IF($T34>=Assumptions!$B$13,"BUY",IF($T34>=1,"MARGINAL","PASS")))))) -> NEEDS PRICE | W34: Taken | X34: [T3] Same pattern as above.
A35: equipmentlending.com | B35: =IF($A35="","",IF(ISERROR(FIND(".",$A35)),"",LOWER(MID($A35,FIND(CHAR(1),SUBSTITUTE($A35,".",CHAR(1),LEN($A35)-LEN(SUBSTITUTE($A35,".",""))))+1,LEN($A35))))) -> com | C35: =IF($B35="","",IFERROR(INDEX(Rubric!$B$14:$B$23,MATCH($B35,Rubric!$A$14:$A$23,0)),INDEX(Rubric!$B$14:$B$23,MATCH("other",Rubric!$A$14:$A$23,0)))) -> 5 | D35: 5 | E35: 3 | F35: 4 | G35: 5 | H35: N | I35: N | M35: =IF($B35="","",IFERROR(INDEX(Rubric!$C$14:$C$23,MATCH($B35,Rubric!$A$14:$A$23,0)),INDEX(Rubric!$C$14:$C$23,MATCH("other",Rubric!$A$14:$A$23,0)))) -> 11 | N35: =IF(OR($A35="",$C35=""),"",$C35*Rubric!$B$5+$D35*Rubric!$B$6+$E35*Rubric!$B$7+$F35*Rubric!$B$8+$G35*Rubric!$B$9) -> 4.4 | O35: =IF($A35="","",IF(OR(UPPER($H35)="Y",UPPER($I35)="Y"),"FAIL","PASS")) -> PASS | P35: =IF($N35="","",Assumptions!$B$6*MAX(0.05,($N35/Assumptions!$B$11)^Assumptions!$B$12)) -> 0.014666667 | Q35: =IF($P35="","",1-(1-$P35)^Assumptions!$B$7) -> 0.071213541 | R35: =IF($M35="","",$M35*Assumptions!$B$7) -> 55 | S35: =IF(OR($J35="",$Q35="",$Q35=0),"",($J35+$R35)/($Q35*(1-Assumptions!$B$4))) | T35: =IF(OR($K35="",$S35="",$S35=0),"",$K35/$S35) | U35: =IF(OR($K35="",$Q35=""),"",MAX(0,($K35-MAX($K35*Assumptions!$B$4,Assumptions!$B$5))*$Q35-$R35)) | V35: =IF($A35="","",IF($O35="FAIL","REJECT",IF($J35="","NEEDS PRICE",IF(OR($K35="",$L35=""),"NEEDS VALUATION",IF($T35>=Assumptions!$B$13,"BUY",IF($T35>=1,"MARGINAL","PASS")))))) -> NEEDS PRICE | W35: Taken | X35: [T3] Same pattern as above.
A36: leasingcapital.com | B36: =IF($A36="","",IF(ISERROR(FIND(".",$A36)),"",LOWER(MID($A36,FIND(CHAR(1),SUBSTITUTE($A36,".",CHAR(1),LEN($A36)-LEN(SUBSTITUTE($A36,".",""))))+1,LEN($A36))))) -> com | C36: =IF($B36="","",IFERROR(INDEX(Rubric!$B$14:$B$23,MATCH($B36,Rubric!$A$14:$A$23,0)),INDEX(Rubric!$B$14:$B$23,MATCH("other",Rubric!$A$14:$A$23,0)))) -> 5 | D36: 4 | E36: 3 | F36: 4 | G36: 5 | H36: N | I36: N | J36: 6495 | M36: =IF($B36="","",IFERROR(INDEX(Rubric!$C$14:$C$23,MATCH($B36,Rubric!$A$14:$A$23,0)),INDEX(Rubric!$C$14:$C$23,MATCH("other",Rubric!$A$14:$A$23,0)))) -> 11 | N36: =IF(OR($A36="",$C36=""),"",$C36*Rubric!$B$5+$D36*Rubric!$B$6+$E36*Rubric!$B$7+$F36*Rubric!$B$8+$G36*Rubric!$B$9) -> 4.1 | O36: =IF($A36="","",IF(OR(UPPER($H36)="Y",UPPER($I36)="Y"),"FAIL","PASS")) -> PASS | P36: =IF($N36="","",Assumptions!$B$6*MAX(0.05,($N36/Assumptions!$B$11)^Assumptions!$B$12)) -> 0.013666667 | Q36: =IF($P36="","",1-(1-$P36)^Assumptions!$B$7) -> 0.066490908 | R36: =IF($M36="","",$M36*Assumptions!$B$7) -> 55 | S36: =IF(OR($J36="",$Q36="",$Q36=0),"",($J36+$R36)/($Q36*(1-Assumptions!$B$4))) -> 123137.14 | T36: =IF(OR($K36="",$S36="",$S36=0),"",$K36/$S36) | U36: =IF(OR($K36="",$Q36=""),"",MAX(0,($K36-MAX($K36*Assumptions!$B$4,Assumptions!$B$5))*$Q36-$R36)) | V36: =IF($A36="","",IF($O36="FAIL","REJECT",IF($J36="","NEEDS PRICE",IF(OR($K36="",$L36=""),"NEEDS VALUATION",IF($T36>=Assumptions!$B$13,"BUY",IF($T36>=1,"MARGINAL","PASS")))))) -> NEEDS VALUATION | W36: Available - premium | X36: [T3] Generic enough to suit many lessors.
A37: lendingdesk.com | B37: =IF($A37="","",IF(ISERROR(FIND(".",$A37)),"",LOWER(MID($A37,FIND(CHAR(1),SUBSTITUTE($A37,".",CHAR(1),LEN($A37)-LEN(SUBSTITUTE($A37,".",""))))+1,LEN($A37))))) -> com | C37: =IF($B37="","",IFERROR(INDEX(Rubric!$B$14:$B$23,MATCH($B37,Rubric!$A$14:$A$23,0)),INDEX(Rubric!$B$14:$B$23,MATCH("other",Rubric!$A$14:$A$23,0)))) -> 5 | D37: 4 | E37: 3 | F37: 5 | G37: 5 | H37: N | I37: N | M37: =IF($B37="","",IFERROR(INDEX(Rubric!$C$14:$C$23,MATCH($B37,Rubric!$A$14:$A$23,0)),INDEX(Rubric!$C$14:$C$23,MATCH("other",Rubric!$A$14:$A$23,0)))) -> 11 | N37: =IF(OR($A37="",$C37=""),"",$C37*Rubric!$B$5+$D37*Rubric!$B$6+$E37*Rubric!$B$7+$F37*Rubric!$B$8+$G37*Rubric!$B$9) -> 4.26 | O37: =IF($A37="","",IF(OR(UPPER($H37)="Y",UPPER($I37)="Y"),"FAIL","PASS")) -> PASS | P37: =IF($N37="","",Assumptions!$B$6*MAX(0.05,($N37/Assumptions!$B$11)^Assumptions!$B$12)) -> 0.0142 | Q37: =IF($P37="","",1-(1-$P37)^Assumptions!$B$7) -> 0.06901203 | R37: =IF($M37="","",$M37*Assumptions!$B$7) -> 55 | S37: =IF(OR($J37="",$Q37="",$Q37=0),"",($J37+$R37)/($Q37*(1-Assumptions!$B$4))) | T37: =IF(OR($K37="",$S37="",$S37=0),"",$K37/$S37) | U37: =IF(OR($K37="",$Q37=""),"",MAX(0,($K37-MAX($K37*Assumptions!$B$4,Assumptions!$B$5))*$Q37-$R37)) | V37: =IF($A37="","",IF($O37="FAIL","REJECT",IF($J37="","NEEDS PRICE",IF(OR($K37="",$L37=""),"NEEDS VALUATION",IF($T37>=Assumptions!$B$13,"BUY",IF($T37>=1,"MARGINAL","PASS")))))) -> NEEDS PRICE | W37: Taken | X37: [T3] 'Desk' is real institutional finance vocabulary.
A38: fundingdesk.com | B38: =IF($A38="","",IF(ISERROR(FIND(".",$A38)),"",LOWER(MID($A38,FIND(CHAR(1),SUBSTITUTE($A38,".",CHAR(1),LEN($A38)-LEN(SUBSTITUTE($A38,".",""))))+1,LEN($A38))))) -> com | C38: =IF($B38="","",IFERROR(INDEX(Rubric!$B$14:$B$23,MATCH($B38,Rubric!$A$14:$A$23,0)),INDEX(Rubric!$B$14:$B$23,MATCH("other",Rubric!$A$14:$A$23,0)))) -> 5 | D38: 4 | E38: 3 | F38: 5 | G38: 5 | H38: N | I38: N | J38: 4900 | M38: =IF($B38="","",IFERROR(INDEX(Rubric!$C$14:$C$23,MATCH($B38,Rubric!$A$14:$A$23,0)),INDEX(Rubric!$C$14:$C$23,MATCH("other",Rubric!$A$14:$A$23,0)))) -> 11 | N38: =IF(OR($A38="",$C38=""),"",$C38*Rubric!$B$5+$D38*Rubric!$B$6+$E38*Rubric!$B$7+$F38*Rubric!$B$8+$G38*Rubric!$B$9) -> 4.26 | O38: =IF($A38="","",IF(OR(UPPER($H38)="Y",UPPER($I38)="Y"),"FAIL","PASS")) -> PASS | P38: =IF($N38="","",Assumptions!$B$6*MAX(0.05,($N38/Assumptions!$B$11)^Assumptions!$B$12)) -> 0.0142 | Q38: =IF($P38="","",1-(1-$P38)^Assumptions!$B$7) -> 0.06901203 | R38: =IF($M38="","",$M38*Assumptions!$B$7) -> 55 | S38: =IF(OR($J38="",$Q38="",$Q38=0),"",($J38+$R38)/($Q38*(1-Assumptions!$B$4))) -> 89748.845 | T38: =IF(OR($K38="",$S38="",$S38=0),"",$K38/$S38) | U38: =IF(OR($K38="",$Q38=""),"",MAX(0,($K38-MAX($K38*Assumptions!$B$4,Assumptions!$B$5))*$Q38-$R38)) | V38: =IF($A38="","",IF($O38="FAIL","REJECT",IF($J38="","NEEDS PRICE",IF(OR($K38="",$L38=""),"NEEDS VALUATION",IF($T38>=Assumptions!$B$13,"BUY",IF($T38>=1,"MARGINAL","PASS")))))) -> NEEDS VALUATION | W38: Available - premium | X38: [T3] Same.
A39: capitaldesk.com | B39: =IF($A39="","",IF(ISERROR(FIND(".",$A39)),"",LOWER(MID($A39,FIND(CHAR(1),SUBSTITUTE($A39,".",CHAR(1),LEN($A39)-LEN(SUBSTITUTE($A39,".",""))))+1,LEN($A39))))) -> com | C39: =IF($B39="","",IFERROR(INDEX(Rubric!$B$14:$B$23,MATCH($B39,Rubric!$A$14:$A$23,0)),INDEX(Rubric!$B$14:$B$23,MATCH("other",Rubric!$A$14:$A$23,0)))) -> 5 | D39: 4 | E39: 3 | F39: 5 | G39: 5 | H39: N | I39: N | M39: =IF($B39="","",IFERROR(INDEX(Rubric!$C$14:$C$23,MATCH($B39,Rubric!$A$14:$A$23,0)),INDEX(Rubric!$C$14:$C$23,MATCH("other",Rubric!$A$14:$A$23,0)))) -> 11 | N39: =IF(OR($A39="",$C39=""),"",$C39*Rubric!$B$5+$D39*Rubric!$B$6+$E39*Rubric!$B$7+$F39*Rubric!$B$8+$G39*Rubric!$B$9) -> 4.26 | O39: =IF($A39="","",IF(OR(UPPER($H39)="Y",UPPER($I39)="Y"),"FAIL","PASS")) -> PASS | P39: =IF($N39="","",Assumptions!$B$6*MAX(0.05,($N39/Assumptions!$B$11)^Assumptions!$B$12)) -> 0.0142 | Q39: =IF($P39="","",1-(1-$P39)^Assumptions!$B$7) -> 0.06901203 | R39: =IF($M39="","",$M39*Assumptions!$B$7) -> 55 | S39: =IF(OR($J39="",$Q39="",$Q39=0),"",($J39+$R39)/($Q39*(1-Assumptions!$B$4))) | T39: =IF(OR($K39="",$S39="",$S39=0),"",$K39/$S39) | U39: =IF(OR($K39="",$Q39=""),"",MAX(0,($K39-MAX($K39*Assumptions!$B$4,Assumptions!$B$5))*$Q39-$R39)) | V39: =IF($A39="","",IF($O39="FAIL","REJECT",IF($J39="","NEEDS PRICE",IF(OR($K39="",$L39=""),"NEEDS VALUATION",IF($T39>=Assumptions!$B$13,"BUY",IF($T39>=1,"MARGINAL","PASS")))))) -> NEEDS PRICE | W39: Taken | X39: [T3] Same.
A40: creditdesk.com | B40: =IF($A40="","",IF(ISERROR(FIND(".",$A40)),"",LOWER(MID($A40,FIND(CHAR(1),SUBSTITUTE($A40,".",CHAR(1),LEN($A40)-LEN(SUBSTITUTE($A40,".",""))))+1,LEN($A40))))) -> com | C40: =IF($B40="","",IFERROR(INDEX(Rubric!$B$14:$B$23,MATCH($B40,Rubric!$A$14:$A$23,0)),INDEX(Rubric!$B$14:$B$23,MATCH("other",Rubric!$A$14:$A$23,0)))) -> 5 | D40: 4 | E40: 3 | F40: 5 | G40: 5 | H40: N | I40: N | J40: 500000 | M40: =IF($B40="","",IFERROR(INDEX(Rubric!$C$14:$C$23,MATCH($B40,Rubric!$A$14:$A$23,0)),INDEX(Rubric!$C$14:$C$23,MATCH("other",Rubric!$A$14:$A$23,0)))) -> 11 | N40: =IF(OR($A40="",$C40=""),"",$C40*Rubric!$B$5+$D40*Rubric!$B$6+$E40*Rubric!$B$7+$F40*Rubric!$B$8+$G40*Rubric!$B$9) -> 4.26 | O40: =IF($A40="","",IF(OR(UPPER($H40)="Y",UPPER($I40)="Y"),"FAIL","PASS")) -> PASS | P40: =IF($N40="","",Assumptions!$B$6*MAX(0.05,($N40/Assumptions!$B$11)^Assumptions!$B$12)) -> 0.0142 | Q40: =IF($P40="","",1-(1-$P40)^Assumptions!$B$7) -> 0.06901203 | R40: =IF($M40="","",$M40*Assumptions!$B$7) -> 55 | S40: =IF(OR($J40="",$Q40="",$Q40=0),"",($J40+$R40)/($Q40*(1-Assumptions!$B$4))) -> 9057388.2 | T40: =IF(OR($K40="",$S40="",$S40=0),"",$K40/$S40) | U40: =IF(OR($K40="",$Q40=""),"",MAX(0,($K40-MAX($K40*Assumptions!$B$4,Assumptions!$B$5))*$Q40-$R40)) | V40: =IF($A40="","",IF($O40="FAIL","REJECT",IF($J40="","NEEDS PRICE",IF(OR($K40="",$L40=""),"NEEDS VALUATION",IF($T40>=Assumptions!$B$13,"BUY",IF($T40>=1,"MARGINAL","PASS")))))) -> NEEDS VALUATION | W40: Available - premium | X40: [T3] Same.
A41: termsheet.com | B41: =IF($A41="","",IF(ISERROR(FIND(".",$A41)),"",LOWER(MID($A41,FIND(CHAR(1),SUBSTITUTE($A41,".",CHAR(1),LEN($A41)-LEN(SUBSTITUTE($A41,".",""))))+1,LEN($A41))))) -> com | C41: =IF($B41="","",IFERROR(INDEX(Rubric!$B$14:$B$23,MATCH($B41,Rubric!$A$14:$A$23,0)),INDEX(Rubric!$B$14:$B$23,MATCH("other",Rubric!$A$14:$A$23,0)))) -> 5 | D41: 4 | E41: 3 | F41: 5 | G41: 5 | H41: N | I41: N | M41: =IF($B41="","",IFERROR(INDEX(Rubric!$C$14:$C$23,MATCH($B41,Rubric!$A$14:$A$23,0)),INDEX(Rubric!$C$14:$C$23,MATCH("other",Rubric!$A$14:$A$23,0)))) -> 11 | N41: =IF(OR($A41="",$C41=""),"",$C41*Rubric!$B$5+$D41*Rubric!$B$6+$E41*Rubric!$B$7+$F41*Rubric!$B$8+$G41*Rubric!$B$9) -> 4.26 | O41: =IF($A41="","",IF(OR(UPPER($H41)="Y",UPPER($I41)="Y"),"FAIL","PASS")) -> PASS | P41: =IF($N41="","",Assumptions!$B$6*MAX(0.05,($N41/Assumptions!$B$11)^Assumptions!$B$12)) -> 0.0142 | Q41: =IF($P41="","",1-(1-$P41)^Assumptions!$B$7) -> 0.06901203 | R41: =IF($M41="","",$M41*Assumptions!$B$7) -> 55 | S41: =IF(OR($J41="",$Q41="",$Q41=0),"",($J41+$R41)/($Q41*(1-Assumptions!$B$4))) | T41: =IF(OR($K41="",$S41="",$S41=0),"",$K41/$S41) | U41: =IF(OR($K41="",$Q41=""),"",MAX(0,($K41-MAX($K41*Assumptions!$B$4,Assumptions!$B$5))*$Q41-$R41)) | V41: =IF($A41="","",IF($O41="FAIL","REJECT",IF($J41="","NEEDS PRICE",IF(OR($K41="",$L41=""),"NEEDS VALUATION",IF($T41>=Assumptions!$B$13,"BUY",IF($T41>=1,"MARGINAL","PASS")))))) -> NEEDS PRICE | W41: Taken | X41: [T3] One word, real industry term. Almost certainly registered.
A42: underwrite.com | B42: =IF($A42="","",IF(ISERROR(FIND(".",$A42)),"",LOWER(MID($A42,FIND(CHAR(1),SUBSTITUTE($A42,".",CHAR(1),LEN($A42)-LEN(SUBSTITUTE($A42,".",""))))+1,LEN($A42))))) -> com | C42: =IF($B42="","",IFERROR(INDEX(Rubric!$B$14:$B$23,MATCH($B42,Rubric!$A$14:$A$23,0)),INDEX(Rubric!$B$14:$B$23,MATCH("other",Rubric!$A$14:$A$23,0)))) -> 5 | D42: 4 | E42: 3 | F42: 5 | G42: 5 | H42: N | I42: N | M42: =IF($B42="","",IFERROR(INDEX(Rubric!$C$14:$C$23,MATCH($B42,Rubric!$A$14:$A$23,0)),INDEX(Rubric!$C$14:$C$23,MATCH("other",Rubric!$A$14:$A$23,0)))) -> 11 | N42: =IF(OR($A42="",$C42=""),"",$C42*Rubric!$B$5+$D42*Rubric!$B$6+$E42*Rubric!$B$7+$F42*Rubric!$B$8+$G42*Rubric!$B$9) -> 4.26 | O42: =IF($A42="","",IF(OR(UPPER($H42)="Y",UPPER($I42)="Y"),"FAIL","PASS")) -> PASS | P42: =IF($N42="","",Assumptions!$B$6*MAX(0.05,($N42/Assumptions!$B$11)^Assumptions!$B$12)) -> 0.0142 | Q42: =IF($P42="","",1-(1-$P42)^Assumptions!$B$7) -> 0.06901203 | R42: =IF($M42="","",$M42*Assumptions!$B$7) -> 55 | S42: =IF(OR($J42="",$Q42="",$Q42=0),"",($J42+$R42)/($Q42*(1-Assumptions!$B$4))) | T42: =IF(OR($K42="",$S42="",$S42=0),"",$K42/$S42) | U42: =IF(OR($K42="",$Q42=""),"",MAX(0,($K42-MAX($K42*Assumptions!$B$4,Assumptions!$B$5))*$Q42-$R42)) | V42: =IF($A42="","",IF($O42="FAIL","REJECT",IF($J42="","NEEDS PRICE",IF(OR($K42="",$L42=""),"NEEDS VALUATION",IF($T42>=Assumptions!$B$13,"BUY",IF($T42>=1,"MARGINAL","PASS")))))) -> NEEDS PRICE | W42: Taken | X42: [T3] Single dictionary verb, core to lending. Likely registered.
A43: sba504.com | B43: =IF($A43="","",IF(ISERROR(FIND(".",$A43)),"",LOWER(MID($A43,FIND(CHAR(1),SUBSTITUTE($A43,".",CHAR(1),LEN($A43)-LEN(SUBSTITUTE($A43,".",""))))+1,LEN($A43))))) -> com | C43: =IF($B43="","",IFERROR(INDEX(Rubric!$B$14:$B$23,MATCH($B43,Rubric!$A$14:$A$23,0)),INDEX(Rubric!$B$14:$B$23,MATCH("other",Rubric!$A$14:$A$23,0)))) -> 5 | D43: 4 | E43: 2 | F43: 5 | G43: 3 | H43: N | I43: Y | J43: 2795 | M43: =IF($B43="","",IFERROR(INDEX(Rubric!$C$14:$C$23,MATCH($B43,Rubric!$A$14:$A$23,0)),INDEX(Rubric!$C$14:$C$23,MATCH("other",Rubric!$A$14:$A$23,0)))) -> 11 | N43: =IF(OR($A43="",$C43=""),"",$C43*Rubric!$B$5+$D43*Rubric!$B$6+$E43*Rubric!$B$7+$F43*Rubric!$B$8+$G43*Rubric!$B$9) -> 3.84 | O43: =IF($A43="","",IF(OR(UPPER($H43)="Y",UPPER($I43)="Y"),"FAIL","PASS")) -> FAIL | P43: =IF($N43="","",Assumptions!$B$6*MAX(0.05,($N43/Assumptions!$B$11)^Assumptions!$B$12)) -> 0.0128 | Q43: =IF($P43="","",1-(1-$P43)^Assumptions!$B$7) -> 0.062382438 | R43: =IF($M43="","",$M43*Assumptions!$B$7) -> 55 | S43: =IF(OR($J43="",$Q43="",$Q43=0),"",($J43+$R43)/($Q43*(1-Assumptions!$B$4))) -> 57107.419 | T43: =IF(OR($K43="",$S43="",$S43=0),"",$K43/$S43) | U43: =IF(OR($K43="",$Q43=""),"",MAX(0,($K43-MAX($K43*Assumptions!$B$4,Assumptions!$B$5))*$Q43-$R43)) | V43: =IF($A43="","",IF($O43="FAIL","REJECT",IF($J43="","NEEDS PRICE",IF(OR($K43="",$L43=""),"NEEDS VALUATION",IF($T43>=Assumptions!$B$13,"BUY",IF($T43>=1,"MARGINAL","PASS")))))) -> REJECT | W43: Available - premium | X43: [T3] HARD FILTER DEMO — contains digits. Auto-rejects.
A44: section179financing.com | B44: =IF($A44="","",IF(ISERROR(FIND(".",$A44)),"",LOWER(MID($A44,FIND(CHAR(1),SUBSTITUTE($A44,".",CHAR(1),LEN($A44)-LEN(SUBSTITUTE($A44,".",""))))+1,LEN($A44))))) -> com | C44: =IF($B44="","",IFERROR(INDEX(Rubric!$B$14:$B$23,MATCH($B44,Rubric!$A$14:$A$23,0)),INDEX(Rubric!$B$14:$B$23,MATCH("other",Rubric!$A$14:$A$23,0)))) -> 5 | D44: 4 | E44: 2 | F44: 2 | G44: 4 | H44: N | I44: Y | J44: 22.99 | M44: =IF($B44="","",IFERROR(INDEX(Rubric!$C$14:$C$23,MATCH($B44,Rubric!$A$14:$A$23,0)),INDEX(Rubric!$C$14:$C$23,MATCH("other",Rubric!$A$14:$A$23,0)))) -> 11 | N44: =IF(OR($A44="",$C44=""),"",$C44*Rubric!$B$5+$D44*Rubric!$B$6+$E44*Rubric!$B$7+$F44*Rubric!$B$8+$G44*Rubric!$B$9) -> 3.46 | O44: =IF($A44="","",IF(OR(UPPER($H44)="Y",UPPER($I44)="Y"),"FAIL","PASS")) -> FAIL | P44: =IF($N44="","",Assumptions!$B$6*MAX(0.05,($N44/Assumptions!$B$11)^Assumptions!$B$12)) -> 0.011533333 | Q44: =IF($P44="","",1-(1-$P44)^Assumptions!$B$7) -> 0.056351742 | R44: =IF($M44="","",$M44*Assumptions!$B$7) -> 55 | S44: =IF(OR($J44="",$Q44="",$Q44=0),"",($J44+$R44)/($Q44*(1-Assumptions!$B$4))) -> 1729.982 | T44: =IF(OR($K44="",$S44="",$S44=0),"",$K44/$S44) | U44: =IF(OR($K44="",$Q44=""),"",MAX(0,($K44-MAX($K44*Assumptions!$B$4,Assumptions!$B$5))*$Q44-$R44)) | V44: =IF($A44="","",IF($O44="FAIL","REJECT",IF($J44="","NEEDS PRICE",IF(OR($K44="",$L44=""),"NEEDS VALUATION",IF($T44>=Assumptions!$B$13,"BUY",IF($T44>=1,"MARGINAL","PASS")))))) -> REJECT | W44: Available - reg | X44: [T3] HARD FILTER DEMO — digits. Also a tax-code term; verify before use.
A45: commercial-lending.com | B45: =IF($A45="","",IF(ISERROR(FIND(".",$A45)),"",LOWER(MID($A45,FIND(CHAR(1),SUBSTITUTE($A45,".",CHAR(1),LEN($A45)-LEN(SUBSTITUTE($A45,".",""))))+1,LEN($A45))))) -> com | C45: =IF($B45="","",IFERROR(INDEX(Rubric!$B$14:$B$23,MATCH($B45,Rubric!$A$14:$A$23,0)),INDEX(Rubric!$B$14:$B$23,MATCH("other",Rubric!$A$14:$A$23,0)))) -> 5 | D45: 4 | E45: 2 | F45: 3 | G45: 4 | H45: N | I45: Y | J45: 3595 | M45: =IF($B45="","",IFERROR(INDEX(Rubric!$C$14:$C$23,MATCH($B45,Rubric!$A$14:$A$23,0)),INDEX(Rubric!$C$14:$C$23,MATCH("other",Rubric!$A$14:$A$23,0)))) -> 11 | N45: =IF(OR($A45="",$C45=""),"",$C45*Rubric!$B$5+$D45*Rubric!$B$6+$E45*Rubric!$B$7+$F45*Rubric!$B$8+$G45*Rubric!$B$9) -> 3.62 | O45: =IF($A45="","",IF(OR(UPPER($H45)="Y",UPPER($I45)="Y"),"FAIL","PASS")) -> FAIL | P45: =IF($N45="","",Assumptions!$B$6*MAX(0.05,($N45/Assumptions!$B$11)^Assumptions!$B$12)) -> 0.012066667 | Q45: =IF($P45="","",1-(1-$P45)^Assumptions!$B$7) -> 0.058894753 | R45: =IF($M45="","",$M45*Assumptions!$B$7) -> 55 | S45: =IF(OR($J45="",$Q45="",$Q45=0),"",($J45+$R45)/($Q45*(1-Assumptions!$B$4))) -> 77468.701 | T45: =IF(OR($K45="",$S45="",$S45=0),"",$K45/$S45) | U45: =IF(OR($K45="",$Q45=""),"",MAX(0,($K45-MAX($K45*Assumptions!$B$4,Assumptions!$B$5))*$Q45-$R45)) | V45: =IF($A45="","",IF($O45="FAIL","REJECT",IF($J45="","NEEDS PRICE",IF(OR($K45="",$L45=""),"NEEDS VALUATION",IF($T45>=Assumptions!$B$13,"BUY",IF($T45>=1,"MARGINAL","PASS")))))) -> REJECT | W45: Available - premium | X45: [T3] HARD FILTER DEMO — hyphen. Auto-rejects.
A46: anvilcapital.com | B46: =IF($A46="","",IF(ISERROR(FIND(".",$A46)),"",LOWER(MID($A46,FIND(CHAR(1),SUBSTITUTE($A46,".",CHAR(1),LEN($A46)-LEN(SUBSTITUTE($A46,".",""))))+1,LEN($A46))))) -> com | C46: =IF($B46="","",IFERROR(INDEX(Rubric!$B$14:$B$23,MATCH($B46,Rubric!$A$14:$A$23,0)),INDEX(Rubric!$B$14:$B$23,MATCH("other",Rubric!$A$14:$A$23,0)))) -> 5 | D46: 4 | E46: 3 | F46: 4 | G46: 5 | H46: N | I46: N | J46: 19000 | M46: =IF($B46="","",IFERROR(INDEX(Rubric!$C$14:$C$23,MATCH($B46,Rubric!$A$14:$A$23,0)),INDEX(Rubric!$C$14:$C$23,MATCH("other",Rubric!$A$14:$A$23,0)))) -> 11 | N46: =IF(OR($A46="",$C46=""),"",$C46*Rubric!$B$5+$D46*Rubric!$B$6+$E46*Rubric!$B$7+$F46*Rubric!$B$8+$G46*Rubric!$B$9) -> 4.1 | O46: =IF($A46="","",IF(OR(UPPER($H46)="Y",UPPER($I46)="Y"),"FAIL","PASS")) -> PASS | P46: =IF($N46="","",Assumptions!$B$6*MAX(0.05,($N46/Assumptions!$B$11)^Assumptions!$B$12)) -> 0.013666667 | Q46: =IF($P46="","",1-(1-$P46)^Assumptions!$B$7) -> 0.066490908 | R46: =IF($M46="","",$M46*Assumptions!$B$7) -> 55 | S46: =IF(OR($J46="",$Q46="",$Q46=0),"",($J46+$R46)/($Q46*(1-Assumptions!$B$4))) -> 358225.67 | T46: =IF(OR($K46="",$S46="",$S46=0),"",$K46/$S46) | U46: =IF(OR($K46="",$Q46=""),"",MAX(0,($K46-MAX($K46*Assumptions!$B$4,Assumptions!$B$5))*$Q46-$R46)) | V46: =IF($A46="","",IF($O46="FAIL","REJECT",IF($J46="","NEEDS PRICE",IF(OR($K46="",$L46=""),"NEEDS VALUATION",IF($T46>=Assumptions!$B$13,"BUY",IF($T46>=1,"MARGINAL","PASS")))))) -> NEEDS VALUATION | W46: Available - premium | X46: [T4] Industrial metaphor, fits equipment finance. Verify TM.
A47: keelcapital.com | B47: =IF($A47="","",IF(ISERROR(FIND(".",$A47)),"",LOWER(MID($A47,FIND(CHAR(1),SUBSTITUTE($A47,".",CHAR(1),LEN($A47)-LEN(SUBSTITUTE($A47,".",""))))+1,LEN($A47))))) -> com | C47: =IF($B47="","",IFERROR(INDEX(Rubric!$B$14:$B$23,MATCH($B47,Rubric!$A$14:$A$23,0)),INDEX(Rubric!$B$14:$B$23,MATCH("other",Rubric!$A$14:$A$23,0)))) -> 5 | D47: 4 | E47: 3 | F47: 4 | G47: 4 | H47: N | I47: N | M47: =IF($B47="","",IFERROR(INDEX(Rubric!$C$14:$C$23,MATCH($B47,Rubric!$A$14:$A$23,0)),INDEX(Rubric!$C$14:$C$23,MATCH("other",Rubric!$A$14:$A$23,0)))) -> 11 | N47: =IF(OR($A47="",$C47=""),"",$C47*Rubric!$B$5+$D47*Rubric!$B$6+$E47*Rubric!$B$7+$F47*Rubric!$B$8+$G47*Rubric!$B$9) -> 4 | O47: =IF($A47="","",IF(OR(UPPER($H47)="Y",UPPER($I47)="Y"),"FAIL","PASS")) -> PASS | P47: =IF($N47="","",Assumptions!$B$6*MAX(0.05,($N47/Assumptions!$B$11)^Assumptions!$B$12)) -> 0.013333333 | Q47: =IF($P47="","",1-(1-$P47)^Assumptions!$B$7) -> 0.064912435 | R47: =IF($M47="","",$M47*Assumptions!$B$7) -> 55 | S47: =IF(OR($J47="",$Q47="",$Q47=0),"",($J47+$R47)/($Q47*(1-Assumptions!$B$4))) | T47: =IF(OR($K47="",$S47="",$S47=0),"",$K47/$S47) | U47: =IF(OR($K47="",$Q47=""),"",MAX(0,($K47-MAX($K47*Assumptions!$B$4,Assumptions!$B$5))*$Q47-$R47)) | V47: =IF($A47="","",IF($O47="FAIL","REJECT",IF($J47="","NEEDS PRICE",IF(OR($K47="",$L47=""),"NEEDS VALUATION",IF($T47>=Assumptions!$B$13,"BUY",IF($T47>=1,"MARGINAL","PASS")))))) -> NEEDS PRICE | W47: Taken | X47: [T4] Stability metaphor. Verify TM.
A48: forgelending.com | B48: =IF($A48="","",IF(ISERROR(FIND(".",$A48)),"",LOWER(MID($A48,FIND(CHAR(1),SUBSTITUTE($A48,".",CHAR(1),LEN($A48)-LEN(SUBSTITUTE($A48,".",""))))+1,LEN($A48))))) -> com | C48: =IF($B48="","",IFERROR(INDEX(Rubric!$B$14:$B$23,MATCH($B48,Rubric!$A$14:$A$23,0)),INDEX(Rubric!$B$14:$B$23,MATCH("other",Rubric!$A$14:$A$23,0)))) -> 5 | D48: 4 | E48: 3 | F48: 4 | G48: 5 | H48: N | I48: N | J48: 8995 | M48: =IF($B48="","",IFERROR(INDEX(Rubric!$C$14:$C$23,MATCH($B48,Rubric!$A$14:$A$23,0)),INDEX(Rubric!$C$14:$C$23,MATCH("other",Rubric!$A$14:$A$23,0)))) -> 11 | N48: =IF(OR($A48="",$C48=""),"",$C48*Rubric!$B$5+$D48*Rubric!$B$6+$E48*Rubric!$B$7+$F48*Rubric!$B$8+$G48*Rubric!$B$9) -> 4.1 | O48: =IF($A48="","",IF(OR(UPPER($H48)="Y",UPPER($I48)="Y"),"FAIL","PASS")) -> PASS | P48: =IF($N48="","",Assumptions!$B$6*MAX(0.05,($N48/Assumptions!$B$11)^Assumptions!$B$12)) -> 0.013666667 | Q48: =IF($P48="","",1-(1-$P48)^Assumptions!$B$7) -> 0.066490908 | R48: =IF($M48="","",$M48*Assumptions!$B$7) -> 55 | S48: =IF(OR($J48="",$Q48="",$Q48=0),"",($J48+$R48)/($Q48*(1-Assumptions!$B$4))) -> 170136.04 | T48: =IF(OR($K48="",$S48="",$S48=0),"",$K48/$S48) | U48: =IF(OR($K48="",$Q48=""),"",MAX(0,($K48-MAX($K48*Assumptions!$B$4,Assumptions!$B$5))*$Q48-$R48)) | V48: =IF($A48="","",IF($O48="FAIL","REJECT",IF($J48="","NEEDS PRICE",IF(OR($K48="",$L48=""),"NEEDS VALUATION",IF($T48>=Assumptions!$B$13,"BUY",IF($T48>=1,"MARGINAL","PASS")))))) -> NEEDS VALUATION | W48: Available - premium | X48: [T4] Industrial, credible for a lender.
A49: quarrycapital.com | B49: =IF($A49="","",IF(ISERROR(FIND(".",$A49)),"",LOWER(MID($A49,FIND(CHAR(1),SUBSTITUTE($A49,".",CHAR(1),LEN($A49)-LEN(SUBSTITUTE($A49,".",""))))+1,LEN($A49))))) -> com | C49: =IF($B49="","",IFERROR(INDEX(Rubric!$B$14:$B$23,MATCH($B49,Rubric!$A$14:$A$23,0)),INDEX(Rubric!$B$14:$B$23,MATCH("other",Rubric!$A$14:$A$23,0)))) -> 5 | D49: 3 | E49: 2 | F49: 4 | G49: 4 | H49: N | I49: N | M49: =IF($B49="","",IFERROR(INDEX(Rubric!$C$14:$C$23,MATCH($B49,Rubric!$A$14:$A$23,0)),INDEX(Rubric!$C$14:$C$23,MATCH("other",Rubric!$A$14:$A$23,0)))) -> 11 | N49: =IF(OR($A49="",$C49=""),"",$C49*Rubric!$B$5+$D49*Rubric!$B$6+$E49*Rubric!$B$7+$F49*Rubric!$B$8+$G49*Rubric!$B$9) -> 3.48 | O49: =IF($A49="","",IF(OR(UPPER($H49)="Y",UPPER($I49)="Y"),"FAIL","PASS")) -> PASS | P49: =IF($N49="","",Assumptions!$B$6*MAX(0.05,($N49/Assumptions!$B$11)^Assumptions!$B$12)) -> 0.0116 | Q49: =IF($P49="","",1-(1-$P49)^Assumptions!$B$7) -> 0.056669919 | R49: =IF($M49="","",$M49*Assumptions!$B$7) -> 55 | S49: =IF(OR($J49="",$Q49="",$Q49=0),"",($J49+$R49)/($Q49*(1-Assumptions!$B$4))) | T49: =IF(OR($K49="",$S49="",$S49=0),"",$K49/$S49) | U49: =IF(OR($K49="",$Q49=""),"",MAX(0,($K49-MAX($K49*Assumptions!$B$4,Assumptions!$B$5))*$Q49-$R49)) | V49: =IF($A49="","",IF($O49="FAIL","REJECT",IF($J49="","NEEDS PRICE",IF(OR($K49="",$L49=""),"NEEDS VALUATION",IF($T49>=Assumptions!$B$13,"BUY",IF($T49>=1,"MARGINAL","PASS")))))) -> NEEDS PRICE | W49: Taken | X49: [T4] Extraction/heavy-industry feel.
A50: millcapital.com | B50: =IF($A50="","",IF(ISERROR(FIND(".",$A50)),"",LOWER(MID($A50,FIND(CHAR(1),SUBSTITUTE($A50,".",CHAR(1),LEN($A50)-LEN(SUBSTITUTE($A50,".",""))))+1,LEN($A50))))) -> com | C50: =IF($B50="","",IFERROR(INDEX(Rubric!$B$14:$B$23,MATCH($B50,Rubric!$A$14:$A$23,0)),INDEX(Rubric!$B$14:$B$23,MATCH("other",Rubric!$A$14:$A$23,0)))) -> 5 | D50: 3 | E50: 2 | F50: 5 | G50: 4 | H50: N | I50: N | M50: =IF($B50="","",IFERROR(INDEX(Rubric!$C$14:$C$23,MATCH($B50,Rubric!$A$14:$A$23,0)),INDEX(Rubric!$C$14:$C$23,MATCH("other",Rubric!$A$14:$A$23,0)))) -> 11 | N50: =IF(OR($A50="",$C50=""),"",$C50*Rubric!$B$5+$D50*Rubric!$B$6+$E50*Rubric!$B$7+$F50*Rubric!$B$8+$G50*Rubric!$B$9) -> 3.64 | O50: =IF($A50="","",IF(OR(UPPER($H50)="Y",UPPER($I50)="Y"),"FAIL","PASS")) -> PASS | P50: =IF($N50="","",Assumptions!$B$6*MAX(0.05,($N50/Assumptions!$B$11)^Assumptions!$B$12)) -> 0.012133333 | Q50: =IF($P50="","",1-(1-$P50)^Assumptions!$B$7) -> 0.059212243 | R50: =IF($M50="","",$M50*Assumptions!$B$7) -> 55 | S50: =IF(OR($J50="",$Q50="",$Q50=0),"",($J50+$R50)/($Q50*(1-Assumptions!$B$4))) | T50: =IF(OR($K50="",$S50="",$S50=0),"",$K50/$S50) | U50: =IF(OR($K50="",$Q50=""),"",MAX(0,($K50-MAX($K50*Assumptions!$B$4,Assumptions!$B$5))*$Q50-$R50)) | V50: =IF($A50="","",IF($O50="FAIL","REJECT",IF($J50="","NEEDS PRICE",IF(OR($K50="",$L50=""),"NEEDS VALUATION",IF($T50>=Assumptions!$B$13,"BUY",IF($T50>=1,"MARGINAL","PASS")))))) -> NEEDS PRICE | W50: Taken | X50: [T4] Short, industrial.
A51: girdercapital.com | B51: =IF($A51="","",IF(ISERROR(FIND(".",$A51)),"",LOWER(MID($A51,FIND(CHAR(1),SUBSTITUTE($A51,".",CHAR(1),LEN($A51)-LEN(SUBSTITUTE($A51,".",""))))+1,LEN($A51))))) -> com | C51: =IF($B51="","",IFERROR(INDEX(Rubric!$B$14:$B$23,MATCH($B51,Rubric!$A$14:$A$23,0)),INDEX(Rubric!$B$14:$B$23,MATCH("other",Rubric!$A$14:$A$23,0)))) -> 5 | D51: 3 | E51: 2 | F51: 4 | G51: 4 | H51: N | I51: N | M51: =IF($B51="","",IFERROR(INDEX(Rubric!$C$14:$C$23,MATCH($B51,Rubric!$A$14:$A$23,0)),INDEX(Rubric!$C$14:$C$23,MATCH("other",Rubric!$A$14:$A$23,0)))) -> 11 | N51: =IF(OR($A51="",$C51=""),"",$C51*Rubric!$B$5+$D51*Rubric!$B$6+$E51*Rubric!$B$7+$F51*Rubric!$B$8+$G51*Rubric!$B$9) -> 3.48 | O51: =IF($A51="","",IF(OR(UPPER($H51)="Y",UPPER($I51)="Y"),"FAIL","PASS")) -> PASS | P51: =IF($N51="","",Assumptions!$B$6*MAX(0.05,($N51/Assumptions!$B$11)^Assumptions!$B$12)) -> 0.0116 | Q51: =IF($P51="","",1-(1-$P51)^Assumptions!$B$7) -> 0.056669919 | R51: =IF($M51="","",$M51*Assumptions!$B$7) -> 55 | S51: =IF(OR($J51="",$Q51="",$Q51=0),"",($J51+$R51)/($Q51*(1-Assumptions!$B$4))) | T51: =IF(OR($K51="",$S51="",$S51=0),"",$K51/$S51) | U51: =IF(OR($K51="",$Q51=""),"",MAX(0,($K51-MAX($K51*Assumptions!$B$4,Assumptions!$B$5))*$Q51-$R51)) | V51: =IF($A51="","",IF($O51="FAIL","REJECT",IF($J51="","NEEDS PRICE",IF(OR($K51="",$L51=""),"NEEDS VALUATION",IF($T51>=Assumptions!$B$13,"BUY",IF($T51>=1,"MARGINAL","PASS")))))) -> NEEDS PRICE | W51: Taken | X51: [T4] Construction metaphor, slightly obscure.
A52: axlecapital.com | B52: =IF($A52="","",IF(ISERROR(FIND(".",$A52)),"",LOWER(MID($A52,FIND(CHAR(1),SUBSTITUTE($A52,".",CHAR(1),LEN($A52)-LEN(SUBSTITUTE($A52,".",""))))+1,LEN($A52))))) -> com | C52: =IF($B52="","",IFERROR(INDEX(Rubric!$B$14:$B$23,MATCH($B52,Rubric!$A$14:$A$23,0)),INDEX(Rubric!$B$14:$B$23,MATCH("other",Rubric!$A$14:$A$23,0)))) -> 5 | D52: 3 | E52: 2 | F52: 4 | G52: 4 | H52: N | I52: N | M52: =IF($B52="","",IFERROR(INDEX(Rubric!$C$14:$C$23,MATCH($B52,Rubric!$A$14:$A$23,0)),INDEX(Rubric!$C$14:$C$23,MATCH("other",Rubric!$A$14:$A$23,0)))) -> 11 | N52: =IF(OR($A52="",$C52=""),"",$C52*Rubric!$B$5+$D52*Rubric!$B$6+$E52*Rubric!$B$7+$F52*Rubric!$B$8+$G52*Rubric!$B$9) -> 3.48 | O52: =IF($A52="","",IF(OR(UPPER($H52)="Y",UPPER($I52)="Y"),"FAIL","PASS")) -> PASS | P52: =IF($N52="","",Assumptions!$B$6*MAX(0.05,($N52/Assumptions!$B$11)^Assumptions!$B$12)) -> 0.0116 | Q52: =IF($P52="","",1-(1-$P52)^Assumptions!$B$7) -> 0.056669919 | R52: =IF($M52="","",$M52*Assumptions!$B$7) -> 55 | S52: =IF(OR($J52="",$Q52="",$Q52=0),"",($J52+$R52)/($Q52*(1-Assumptions!$B$4))) | T52: =IF(OR($K52="",$S52="",$S52=0),"",$K52/$S52) | U52: =IF(OR($K52="",$Q52=""),"",MAX(0,($K52-MAX($K52*Assumptions!$B$4,Assumptions!$B$5))*$Q52-$R52)) | V52: =IF($A52="","",IF($O52="FAIL","REJECT",IF($J52="","NEEDS PRICE",IF(OR($K52="",$L52=""),"NEEDS VALUATION",IF($T52>=Assumptions!$B$13,"BUY",IF($T52>=1,"MARGINAL","PASS")))))) -> NEEDS PRICE | W52: Taken | X52: [T4] Fleet/trucking flavour.
A53: torquelending.com | B53: =IF($A53="","",IF(ISERROR(FIND(".",$A53)),"",LOWER(MID($A53,FIND(CHAR(1),SUBSTITUTE($A53,".",CHAR(1),LEN($A53)-LEN(SUBSTITUTE($A53,".",""))))+1,LEN($A53))))) -> com | C53: =IF($B53="","",IFERROR(INDEX(Rubric!$B$14:$B$23,MATCH($B53,Rubric!$A$14:$A$23,0)),INDEX(Rubric!$B$14:$B$23,MATCH("other",Rubric!$A$14:$A$23,0)))) -> 5 | D53: 3 | E53: 2 | F53: 4 | G53: 4 | H53: N | I53: N | J53: 22.99 | M53: =IF($B53="","",IFERROR(INDEX(Rubric!$C$14:$C$23,MATCH($B53,Rubric!$A$14:$A$23,0)),INDEX(Rubric!$C$14:$C$23,MATCH("other",Rubric!$A$14:$A$23,0)))) -> 11 | N53: =IF(OR($A53="",$C53=""),"",$C53*Rubric!$B$5+$D53*Rubric!$B$6+$E53*Rubric!$B$7+$F53*Rubric!$B$8+$G53*Rubric!$B$9) -> 3.48 | O53: =IF($A53="","",IF(OR(UPPER($H53)="Y",UPPER($I53)="Y"),"FAIL","PASS")) -> PASS | P53: =IF($N53="","",Assumptions!$B$6*MAX(0.05,($N53/Assumptions!$B$11)^Assumptions!$B$12)) -> 0.0116 | Q53: =IF($P53="","",1-(1-$P53)^Assumptions!$B$7) -> 0.056669919 | R53: =IF($M53="","",$M53*Assumptions!$B$7) -> 55 | S53: =IF(OR($J53="",$Q53="",$Q53=0),"",($J53+$R53)/($Q53*(1-Assumptions!$B$4))) -> 1720.2689 | T53: =IF(OR($K53="",$S53="",$S53=0),"",$K53/$S53) | U53: =IF(OR($K53="",$Q53=""),"",MAX(0,($K53-MAX($K53*Assumptions!$B$4,Assumptions!$B$5))*$Q53-$R53)) | V53: =IF($A53="","",IF($O53="FAIL","REJECT",IF($J53="","NEEDS PRICE",IF(OR($K53="",$L53=""),"NEEDS VALUATION",IF($T53>=Assumptions!$B$13,"BUY",IF($T53>=1,"MARGINAL","PASS")))))) -> NEEDS VALUATION | W53: Available - reg | X53: [T4] Machinery flavour. Torque Capital Group exists — check TM.
A54: bedrocklending.com | B54: =IF($A54="","",IF(ISERROR(FIND(".",$A54)),"",LOWER(MID($A54,FIND(CHAR(1),SUBSTITUTE($A54,".",CHAR(1),LEN($A54)-LEN(SUBSTITUTE($A54,".",""))))+1,LEN($A54))))) -> com | C54: =IF($B54="","",IFERROR(INDEX(Rubric!$B$14:$B$23,MATCH($B54,Rubric!$A$14:$A$23,0)),INDEX(Rubric!$B$14:$B$23,MATCH("other",Rubric!$A$14:$A$23,0)))) -> 5 | D54: 3 | E54: 2 | F54: 4 | G54: 5 | H54: Y | I54: N | M54: =IF($B54="","",IFERROR(INDEX(Rubric!$C$14:$C$23,MATCH($B54,Rubric!$A$14:$A$23,0)),INDEX(Rubric!$C$14:$C$23,MATCH("other",Rubric!$A$14:$A$23,0)))) -> 11 | N54: =IF(OR($A54="",$C54=""),"",$C54*Rubric!$B$5+$D54*Rubric!$B$6+$E54*Rubric!$B$7+$F54*Rubric!$B$8+$G54*Rubric!$B$9) -> 3.58 | O54: =IF($A54="","",IF(OR(UPPER($H54)="Y",UPPER($I54)="Y"),"FAIL","PASS")) -> FAIL | P54: =IF($N54="","",Assumptions!$B$6*MAX(0.05,($N54/Assumptions!$B$11)^Assumptions!$B$12)) -> 0.011933333 | Q54: =IF($P54="","",1-(1-$P54)^Assumptions!$B$7) -> 0.058259515 | R54: =IF($M54="","",$M54*Assumptions!$B$7) -> 55 | S54: =IF(OR($J54="",$Q54="",$Q54=0),"",($J54+$R54)/($Q54*(1-Assumptions!$B$4))) | T54: =IF(OR($K54="",$S54="",$S54=0),"",$K54/$S54) | U54: =IF(OR($K54="",$Q54=""),"",MAX(0,($K54-MAX($K54*Assumptions!$B$4,Assumptions!$B$5))*$Q54-$R54)) | V54: =IF($A54="","",IF($O54="FAIL","REJECT",IF($J54="","NEEDS PRICE",IF(OR($K54="",$L54=""),"NEEDS VALUATION",IF($T54>=Assumptions!$B$13,"BUY",IF($T54>=1,"MARGINAL","PASS")))))) -> REJECT | W54: Taken | X54: [T4] TM FLAG — Bedrock Capital is an existing firm. Marked Y to show the filter working.
A55: lendcraft.com | B55: =IF($A55="","",IF(ISERROR(FIND(".",$A55)),"",LOWER(MID($A55,FIND(CHAR(1),SUBSTITUTE($A55,".",CHAR(1),LEN($A55)-LEN(SUBSTITUTE($A55,".",""))))+1,LEN($A55))))) -> com | C55: =IF($B55="","",IFERROR(INDEX(Rubric!$B$14:$B$23,MATCH($B55,Rubric!$A$14:$A$23,0)),INDEX(Rubric!$B$14:$B$23,MATCH("other",Rubric!$A$14:$A$23,0)))) -> 5 | D55: 4 | E55: 3 | F55: 5 | G55: 5 | H55: N | I55: N | M55: =IF($B55="","",IFERROR(INDEX(Rubric!$C$14:$C$23,MATCH($B55,Rubric!$A$14:$A$23,0)),INDEX(Rubric!$C$14:$C$23,MATCH("other",Rubric!$A$14:$A$23,0)))) -> 11 | N55: =IF(OR($A55="",$C55=""),"",$C55*Rubric!$B$5+$D55*Rubric!$B$6+$E55*Rubric!$B$7+$F55*Rubric!$B$8+$G55*Rubric!$B$9) -> 4.26 | O55: =IF($A55="","",IF(OR(UPPER($H55)="Y",UPPER($I55)="Y"),"FAIL","PASS")) -> PASS | P55: =IF($N55="","",Assumptions!$B$6*MAX(0.05,($N55/Assumptions!$B$11)^Assumptions!$B$12)) -> 0.0142 | Q55: =IF($P55="","",1-(1-$P55)^Assumptions!$B$7) -> 0.06901203 | R55: =IF($M55="","",$M55*Assumptions!$B$7) -> 55 | S55: =IF(OR($J55="",$Q55="",$Q55=0),"",($J55+$R55)/($Q55*(1-Assumptions!$B$4))) | T55: =IF(OR($K55="",$S55="",$S55=0),"",$K55/$S55) | U55: =IF(OR($K55="",$Q55=""),"",MAX(0,($K55-MAX($K55*Assumptions!$B$4,Assumptions!$B$5))*$Q55-$R55)) | V55: =IF($A55="","",IF($O55="FAIL","REJECT",IF($J55="","NEEDS PRICE",IF(OR($K55="",$L55=""),"NEEDS VALUATION",IF($T55>=Assumptions!$B$13,"BUY",IF($T55>=1,"MARGINAL","PASS")))))) -> NEEDS PRICE | W55: Taken | X55: [T4] Coined but obvious. Good radio test.
A56: capstack.com | B56: =IF($A56="","",IF(ISERROR(FIND(".",$A56)),"",LOWER(MID($A56,FIND(CHAR(1),SUBSTITUTE($A56,".",CHAR(1),LEN($A56)-LEN(SUBSTITUTE($A56,".",""))))+1,LEN($A56))))) -> com | C56: =IF($B56="","",IFERROR(INDEX(Rubric!$B$14:$B$23,MATCH($B56,Rubric!$A$14:$A$23,0)),INDEX(Rubric!$B$14:$B$23,MATCH("other",Rubric!$A$14:$A$23,0)))) -> 5 | D56: 4 | E56: 3 | F56: 5 | G56: 5 | H56: N | I56: N | M56: =IF($B56="","",IFERROR(INDEX(Rubric!$C$14:$C$23,MATCH($B56,Rubric!$A$14:$A$23,0)),INDEX(Rubric!$C$14:$C$23,MATCH("other",Rubric!$A$14:$A$23,0)))) -> 11 | N56: =IF(OR($A56="",$C56=""),"",$C56*Rubric!$B$5+$D56*Rubric!$B$6+$E56*Rubric!$B$7+$F56*Rubric!$B$8+$G56*Rubric!$B$9) -> 4.26 | O56: =IF($A56="","",IF(OR(UPPER($H56)="Y",UPPER($I56)="Y"),"FAIL","PASS")) -> PASS | P56: =IF($N56="","",Assumptions!$B$6*MAX(0.05,($N56/Assumptions!$B$11)^Assumptions!$B$12)) -> 0.0142 | Q56: =IF($P56="","",1-(1-$P56)^Assumptions!$B$7) -> 0.06901203 | R56: =IF($M56="","",$M56*Assumptions!$B$7) -> 55 | S56: =IF(OR($J56="",$Q56="",$Q56=0),"",($J56+$R56)/($Q56*(1-Assumptions!$B$4))) | T56: =IF(OR($K56="",$S56="",$S56=0),"",$K56/$S56) | U56: =IF(OR($K56="",$Q56=""),"",MAX(0,($K56-MAX($K56*Assumptions!$B$4,Assumptions!$B$5))*$Q56-$R56)) | V56: =IF($A56="","",IF($O56="FAIL","REJECT",IF($J56="","NEEDS PRICE",IF(OR($K56="",$L56=""),"NEEDS VALUATION",IF($T56>=Assumptions!$B$13,"BUY",IF($T56>=1,"MARGINAL","PASS")))))) -> NEEDS PRICE | W56: Taken | X56: [T4] 'Capital stack' is genuine finance vocabulary. Likely registered.
A57: leaseflow.com | B57: =IF($A57="","",IF(ISERROR(FIND(".",$A57)),"",LOWER(MID($A57,FIND(CHAR(1),SUBSTITUTE($A57,".",CHAR(1),LEN($A57)-LEN(SUBSTITUTE($A57,".",""))))+1,LEN($A57))))) -> com | C57: =IF($B57="","",IFERROR(INDEX(Rubric!$B$14:$B$23,MATCH($B57,Rubric!$A$14:$A$23,0)),INDEX(Rubric!$B$14:$B$23,MATCH("other",Rubric!$A$14:$A$23,0)))) -> 5 | D57: 4 | E57: 3 | F57: 5 | G57: 5 | H57: N | I57: N | J57: 70000 | M57: =IF($B57="","",IFERROR(INDEX(Rubric!$C$14:$C$23,MATCH($B57,Rubric!$A$14:$A$23,0)),INDEX(Rubric!$C$14:$C$23,MATCH("other",Rubric!$A$14:$A$23,0)))) -> 11 | N57: =IF(OR($A57="",$C57=""),"",$C57*Rubric!$B$5+$D57*Rubric!$B$6+$E57*Rubric!$B$7+$F57*Rubric!$B$8+$G57*Rubric!$B$9) -> 4.26 | O57: =IF($A57="","",IF(OR(UPPER($H57)="Y",UPPER($I57)="Y"),"FAIL","PASS")) -> PASS | P57: =IF($N57="","",Assumptions!$B$6*MAX(0.05,($N57/Assumptions!$B$11)^Assumptions!$B$12)) -> 0.0142 | Q57: =IF($P57="","",1-(1-$P57)^Assumptions!$B$7) -> 0.06901203 | R57: =IF($M57="","",$M57*Assumptions!$B$7) -> 55 | S57: =IF(OR($J57="",$Q57="",$Q57=0),"",($J57+$R57)/($Q57*(1-Assumptions!$B$4))) -> 1268891.1 | T57: =IF(OR($K57="",$S57="",$S57=0),"",$K57/$S57) | U57: =IF(OR($K57="",$Q57=""),"",MAX(0,($K57-MAX($K57*Assumptions!$B$4,Assumptions!$B$5))*$Q57-$R57)) | V57: =IF($A57="","",IF($O57="FAIL","REJECT",IF($J57="","NEEDS PRICE",IF(OR($K57="",$L57=""),"NEEDS VALUATION",IF($T57>=Assumptions!$B$13,"BUY",IF($T57>=1,"MARGINAL","PASS")))))) -> NEEDS VALUATION | W57: Available - premium | X57: [T4] SaaS-ish; could suit a lessor or a software buyer.
A58: fundrig.com | B58: =IF($A58="","",IF(ISERROR(FIND(".",$A58)),"",LOWER(MID($A58,FIND(CHAR(1),SUBSTITUTE($A58,".",CHAR(1),LEN($A58)-LEN(SUBSTITUTE($A58,".",""))))+1,LEN($A58))))) -> com | C58: =IF($B58="","",IFERROR(INDEX(Rubric!$B$14:$B$23,MATCH($B58,Rubric!$A$14:$A$23,0)),INDEX(Rubric!$B$14:$B$23,MATCH("other",Rubric!$A$14:$A$23,0)))) -> 5 | D58: 3 | E58: 2 | F58: 5 | G58: 4 | H58: N | I58: N | J58: 2995 | M58: =IF($B58="","",IFERROR(INDEX(Rubric!$C$14:$C$23,MATCH($B58,Rubric!$A$14:$A$23,0)),INDEX(Rubric!$C$14:$C$23,MATCH("other",Rubric!$A$14:$A$23,0)))) -> 11 | N58: =IF(OR($A58="",$C58=""),"",$C58*Rubric!$B$5+$D58*Rubric!$B$6+$E58*Rubric!$B$7+$F58*Rubric!$B$8+$G58*Rubric!$B$9) -> 3.64 | O58: =IF($A58="","",IF(OR(UPPER($H58)="Y",UPPER($I58)="Y"),"FAIL","PASS")) -> PASS | P58: =IF($N58="","",Assumptions!$B$6*MAX(0.05,($N58/Assumptions!$B$11)^Assumptions!$B$12)) -> 0.012133333 | Q58: =IF($P58="","",1-(1-$P58)^Assumptions!$B$7) -> 0.059212243 | R58: =IF($M58="","",$M58*Assumptions!$B$7) -> 55 | S58: =IF(OR($J58="",$Q58="",$Q58=0),"",($J58+$R58)/($Q58*(1-Assumptions!$B$4))) -> 64387.022 | T58: =IF(OR($K58="",$S58="",$S58=0),"",$K58/$S58) | U58: =IF(OR($K58="",$Q58=""),"",MAX(0,($K58-MAX($K58*Assumptions!$B$4,Assumptions!$B$5))*$Q58-$R58)) | V58: =IF($A58="","",IF($O58="FAIL","REJECT",IF($J58="","NEEDS PRICE",IF(OR($K58="",$L58=""),"NEEDS VALUATION",IF($T58>=Assumptions!$B$13,"BUY",IF($T58>=1,"MARGINAL","PASS")))))) -> NEEDS VALUATION | W58: Available - premium | X58: [T4] Short, oilfield/equipment flavour. Slightly odd.
A59: assetly.com | B59: =IF($A59="","",IF(ISERROR(FIND(".",$A59)),"",LOWER(MID($A59,FIND(CHAR(1),SUBSTITUTE($A59,".",CHAR(1),LEN($A59)-LEN(SUBSTITUTE($A59,".",""))))+1,LEN($A59))))) -> com | C59: =IF($B59="","",IFERROR(INDEX(Rubric!$B$14:$B$23,MATCH($B59,Rubric!$A$14:$A$23,0)),INDEX(Rubric!$B$14:$B$23,MATCH("other",Rubric!$A$14:$A$23,0)))) -> 5 | D59: 3 | E59: 2 | F59: 5 | G59: 4 | H59: N | I59: N | M59: =IF($B59="","",IFERROR(INDEX(Rubric!$C$14:$C$23,MATCH($B59,Rubric!$A$14:$A$23,0)),INDEX(Rubric!$C$14:$C$23,MATCH("other",Rubric!$A$14:$A$23,0)))) -> 11 | N59: =IF(OR($A59="",$C59=""),"",$C59*Rubric!$B$5+$D59*Rubric!$B$6+$E59*Rubric!$B$7+$F59*Rubric!$B$8+$G59*Rubric!$B$9) -> 3.64 | O59: =IF($A59="","",IF(OR(UPPER($H59)="Y",UPPER($I59)="Y"),"FAIL","PASS")) -> PASS | P59: =IF($N59="","",Assumptions!$B$6*MAX(0.05,($N59/Assumptions!$B$11)^Assumptions!$B$12)) -> 0.012133333 | Q59: =IF($P59="","",1-(1-$P59)^Assumptions!$B$7) -> 0.059212243 | R59: =IF($M59="","",$M59*Assumptions!$B$7) -> 55 | S59: =IF(OR($J59="",$Q59="",$Q59=0),"",($J59+$R59)/($Q59*(1-Assumptions!$B$4))) | T59: =IF(OR($K59="",$S59="",$S59=0),"",$K59/$S59) | U59: =IF(OR($K59="",$Q59=""),"",MAX(0,($K59-MAX($K59*Assumptions!$B$4,Assumptions!$B$5))*$Q59-$R59)) | V59: =IF($A59="","",IF($O59="FAIL","REJECT",IF($J59="","NEEDS PRICE",IF(OR($K59="",$L59=""),"NEEDS VALUATION",IF($T59>=Assumptions!$B$13,"BUY",IF($T59>=1,"MARGINAL","PASS")))))) -> NEEDS PRICE | W59: Taken | X59: [T4] -ly brandable. Generic, crowded pattern.
A60: ledgerlend.com | B60: =IF($A60="","",IF(ISERROR(FIND(".",$A60)),"",LOWER(MID($A60,FIND(CHAR(1),SUBSTITUTE($A60,".",CHAR(1),LEN($A60)-LEN(SUBSTITUTE($A60,".",""))))+1,LEN($A60))))) -> com | C60: =IF($B60="","",IFERROR(INDEX(Rubric!$B$14:$B$23,MATCH($B60,Rubric!$A$14:$A$23,0)),INDEX(Rubric!$B$14:$B$23,MATCH("other",Rubric!$A$14:$A$23,0)))) -> 5 | D60: 3 | E60: 2 | F60: 4 | G60: 4 | H60: N | I60: N | M60: =IF($B60="","",IFERROR(INDEX(Rubric!$C$14:$C$23,MATCH($B60,Rubric!$A$14:$A$23,0)),INDEX(Rubric!$C$14:$C$23,MATCH("other",Rubric!$A$14:$A$23,0)))) -> 11 | N60: =IF(OR($A60="",$C60=""),"",$C60*Rubric!$B$5+$D60*Rubric!$B$6+$E60*Rubric!$B$7+$F60*Rubric!$B$8+$G60*Rubric!$B$9) -> 3.48 | O60: =IF($A60="","",IF(OR(UPPER($H60)="Y",UPPER($I60)="Y"),"FAIL","PASS")) -> PASS | P60: =IF($N60="","",Assumptions!$B$6*MAX(0.05,($N60/Assumptions!$B$11)^Assumptions!$B$12)) -> 0.0116 | Q60: =IF($P60="","",1-(1-$P60)^Assumptions!$B$7) -> 0.056669919 | R60: =IF($M60="","",$M60*Assumptions!$B$7) -> 55 | S60: =IF(OR($J60="",$Q60="",$Q60=0),"",($J60+$R60)/($Q60*(1-Assumptions!$B$4))) | T60: =IF(OR($K60="",$S60="",$S60=0),"",$K60/$S60) | U60: =IF(OR($K60="",$Q60=""),"",MAX(0,($K60-MAX($K60*Assumptions!$B$4,Assumptions!$B$5))*$Q60-$R60)) | V60: =IF($A60="","",IF($O60="FAIL","REJECT",IF($J60="","NEEDS PRICE",IF(OR($K60="",$L60=""),"NEEDS VALUATION",IF($T60>=Assumptions!$B$13,"BUY",IF($T60>=1,"MARGINAL","PASS")))))) -> NEEDS PRICE | W60: Taken | X60: [T4] Alliterative, a little clunky.
A61: creditbox.com | B61: =IF($A61="","",IF(ISERROR(FIND(".",$A61)),"",LOWER(MID($A61,FIND(CHAR(1),SUBSTITUTE($A61,".",CHAR(1),LEN($A61)-LEN(SUBSTITUTE($A61,".",""))))+1,LEN($A61))))) -> com | C61: =IF($B61="","",IFERROR(INDEX(Rubric!$B$14:$B$23,MATCH($B61,Rubric!$A$14:$A$23,0)),INDEX(Rubric!$B$14:$B$23,MATCH("other",Rubric!$A$14:$A$23,0)))) -> 5 | D61: 4 | E61: 2 | F61: 5 | G61: 5 | H61: N | I61: N | M61: =IF($B61="","",IFERROR(INDEX(Rubric!$C$14:$C$23,MATCH($B61,Rubric!$A$14:$A$23,0)),INDEX(Rubric!$C$14:$C$23,MATCH("other",Rubric!$A$14:$A$23,0)))) -> 11 | N61: =IF(OR($A61="",$C61=""),"",$C61*Rubric!$B$5+$D61*Rubric!$B$6+$E61*Rubric!$B$7+$F61*Rubric!$B$8+$G61*Rubric!$B$9) -> 4.04 | O61: =IF($A61="","",IF(OR(UPPER($H61)="Y",UPPER($I61)="Y"),"FAIL","PASS")) -> PASS | P61: =IF($N61="","",Assumptions!$B$6*MAX(0.05,($N61/Assumptions!$B$11)^Assumptions!$B$12)) -> 0.013466667 | Q61: =IF($P61="","",1-(1-$P61)^Assumptions!$B$7) -> 0.06554408 | R61: =IF($M61="","",$M61*Assumptions!$B$7) -> 55 | S61: =IF(OR($J61="",$Q61="",$Q61=0),"",($J61+$R61)/($Q61*(1-Assumptions!$B$4))) | T61: =IF(OR($K61="",$S61="",$S61=0),"",$K61/$S61) | U61: =IF(OR($K61="",$Q61=""),"",MAX(0,($K61-MAX($K61*Assumptions!$B$4,Assumptions!$B$5))*$Q61-$R61)) | V61: =IF($A61="","",IF($O61="FAIL","REJECT",IF($J61="","NEEDS PRICE",IF(OR($K61="",$L61=""),"NEEDS VALUATION",IF($T61>=Assumptions!$B$13,"BUY",IF($T61>=1,"MARGINAL","PASS")))))) -> NEEDS PRICE | W61: Taken | X61: [B2/Jargon] 'Inside the credit box' is everyday underwriting speech. Not a consumer search term, so less likely mined.
A62: residualvalue.com | B62: =IF($A62="","",IF(ISERROR(FIND(".",$A62)),"",LOWER(MID($A62,FIND(CHAR(1),SUBSTITUTE($A62,".",CHAR(1),LEN($A62)-LEN(SUBSTITUTE($A62,".",""))))+1,LEN($A62))))) -> com | C62: =IF($B62="","",IFERROR(INDEX(Rubric!$B$14:$B$23,MATCH($B62,Rubric!$A$14:$A$23,0)),INDEX(Rubric!$B$14:$B$23,MATCH("other",Rubric!$A$14:$A$23,0)))) -> 5 | D62: 4 | E62: 2 | F62: 3 | G62: 5 | H62: N | I62: N | J62: 14499 | M62: =IF($B62="","",IFERROR(INDEX(Rubric!$C$14:$C$23,MATCH($B62,Rubric!$A$14:$A$23,0)),INDEX(Rubric!$C$14:$C$23,MATCH("other",Rubric!$A$14:$A$23,0)))) -> 11 | N62: =IF(OR($A62="",$C62=""),"",$C62*Rubric!$B$5+$D62*Rubric!$B$6+$E62*Rubric!$B$7+$F62*Rubric!$B$8+$G62*Rubric!$B$9) -> 3.72 | O62: =IF($A62="","",IF(OR(UPPER($H62)="Y",UPPER($I62)="Y"),"FAIL","PASS")) -> PASS | P62: =IF($N62="","",Assumptions!$B$6*MAX(0.05,($N62/Assumptions!$B$11)^Assumptions!$B$12)) -> 0.0124 | Q62: =IF($P62="","",1-(1-$P62)^Assumptions!$B$7) -> 0.060481348 | R62: =IF($M62="","",$M62*Assumptions!$B$7) -> 55 | S62: =IF(OR($J62="",$Q62="",$Q62=0),"",($J62+$R62)/($Q62*(1-Assumptions!$B$4))) -> 300795.21 | T62: =IF(OR($K62="",$S62="",$S62=0),"",$K62/$S62) | U62: =IF(OR($K62="",$Q62=""),"",MAX(0,($K62-MAX($K62*Assumptions!$B$4,Assumptions!$B$5))*$Q62-$R62)) | V62: =IF($A62="","",IF($O62="FAIL","REJECT",IF($J62="","NEEDS PRICE",IF(OR($K62="",$L62=""),"NEEDS VALUATION",IF($T62>=Assumptions!$B$13,"BUY",IF($T62>=1,"MARGINAL","PASS")))))) -> NEEDS VALUATION | W62: Available - premium | X62: [B2/Jargon] Core equipment-lease concept — the whole economics of an FMV lease.
A63: buyrate.com | B63: =IF($A63="","",IF(ISERROR(FIND(".",$A63)),"",LOWER(MID($A63,FIND(CHAR(1),SUBSTITUTE($A63,".",CHAR(1),LEN($A63)-LEN(SUBSTITUTE($A63,".",""))))+1,LEN($A63))))) -> com | C63: =IF($B63="","",IFERROR(INDEX(Rubric!$B$14:$B$23,MATCH($B63,Rubric!$A$14:$A$23,0)),INDEX(Rubric!$B$14:$B$23,MATCH("other",Rubric!$A$14:$A$23,0)))) -> 5 | D63: 4 | E63: 2 | F63: 5 | G63: 5 | H63: N | I63: N | M63: =IF($B63="","",IFERROR(INDEX(Rubric!$C$14:$C$23,MATCH($B63,Rubric!$A$14:$A$23,0)),INDEX(Rubric!$C$14:$C$23,MATCH("other",Rubric!$A$14:$A$23,0)))) -> 11 | N63: =IF(OR($A63="",$C63=""),"",$C63*Rubric!$B$5+$D63*Rubric!$B$6+$E63*Rubric!$B$7+$F63*Rubric!$B$8+$G63*Rubric!$B$9) -> 4.04 | O63: =IF($A63="","",IF(OR(UPPER($H63)="Y",UPPER($I63)="Y"),"FAIL","PASS")) -> PASS | P63: =IF($N63="","",Assumptions!$B$6*MAX(0.05,($N63/Assumptions!$B$11)^Assumptions!$B$12)) -> 0.013466667 | Q63: =IF($P63="","",1-(1-$P63)^Assumptions!$B$7) -> 0.06554408 | R63: =IF($M63="","",$M63*Assumptions!$B$7) -> 55 | S63: =IF(OR($J63="",$Q63="",$Q63=0),"",($J63+$R63)/($Q63*(1-Assumptions!$B$4))) | T63: =IF(OR($K63="",$S63="",$S63=0),"",$K63/$S63) | U63: =IF(OR($K63="",$Q63=""),"",MAX(0,($K63-MAX($K63*Assumptions!$B$4,Assumptions!$B$5))*$Q63-$R63)) | V63: =IF($A63="","",IF($O63="FAIL","REJECT",IF($J63="","NEEDS PRICE",IF(OR($K63="",$L63=""),"NEEDS VALUATION",IF($T63>=Assumptions!$B$13,"BUY",IF($T63>=1,"MARGINAL","PASS")))))) -> NEEDS PRICE | W63: Taken | X63: [B2/Jargon] The rate a funder quotes a broker. Pure industry vocabulary.
A64: ticketsize.com | B64: =IF($A64="","",IF(ISERROR(FIND(".",$A64)),"",LOWER(MID($A64,FIND(CHAR(1),SUBSTITUTE($A64,".",CHAR(1),LEN($A64)-LEN(SUBSTITUTE($A64,".",""))))+1,LEN($A64))))) -> com | C64: =IF($B64="","",IFERROR(INDEX(Rubric!$B$14:$B$23,MATCH($B64,Rubric!$A$14:$A$23,0)),INDEX(Rubric!$B$14:$B$23,MATCH("other",Rubric!$A$14:$A$23,0)))) -> 5 | D64: 3 | E64: 2 | F64: 4 | G64: 5 | H64: N | I64: N | J64: 2395 | M64: =IF($B64="","",IFERROR(INDEX(Rubric!$C$14:$C$23,MATCH($B64,Rubric!$A$14:$A$23,0)),INDEX(Rubric!$C$14:$C$23,MATCH("other",Rubric!$A$14:$A$23,0)))) -> 11 | N64: =IF(OR($A64="",$C64=""),"",$C64*Rubric!$B$5+$D64*Rubric!$B$6+$E64*Rubric!$B$7+$F64*Rubric!$B$8+$G64*Rubric!$B$9) -> 3.58 | O64: =IF($A64="","",IF(OR(UPPER($H64)="Y",UPPER($I64)="Y"),"FAIL","PASS")) -> PASS | P64: =IF($N64="","",Assumptions!$B$6*MAX(0.05,($N64/Assumptions!$B$11)^Assumptions!$B$12)) -> 0.011933333 | Q64: =IF($P64="","",1-(1-$P64)^Assumptions!$B$7) -> 0.058259515 | R64: =IF($M64="","",$M64*Assumptions!$B$7) -> 55 | S64: =IF(OR($J64="",$Q64="",$Q64=0),"",($J64+$R64)/($Q64*(1-Assumptions!$B$4))) -> 52566.521 | T64: =IF(OR($K64="",$S64="",$S64=0),"",$K64/$S64) | U64: =IF(OR($K64="",$Q64=""),"",MAX(0,($K64-MAX($K64*Assumptions!$B$4,Assumptions!$B$5))*$Q64-$R64)) | V64: =IF($A64="","",IF($O64="FAIL","REJECT",IF($J64="","NEEDS PRICE",IF(OR($K64="",$L64=""),"NEEDS VALUATION",IF($T64>=Assumptions!$B$13,"BUY",IF($T64>=1,"MARGINAL","PASS")))))) -> NEEDS VALUATION | W64: Available - premium | X64: [B2/Jargon] How the industry segments deals. Narrow but real.
A65: capitalcall.com | B65: =IF($A65="","",IF(ISERROR(FIND(".",$A65)),"",LOWER(MID($A65,FIND(CHAR(1),SUBSTITUTE($A65,".",CHAR(1),LEN($A65)-LEN(SUBSTITUTE($A65,".",""))))+1,LEN($A65))))) -> com | C65: =IF($B65="","",IFERROR(INDEX(Rubric!$B$14:$B$23,MATCH($B65,Rubric!$A$14:$A$23,0)),INDEX(Rubric!$B$14:$B$23,MATCH("other",Rubric!$A$14:$A$23,0)))) -> 5 | D65: 4 | E65: 3 | F65: 4 | G65: 5 | H65: N | I65: N | M65: =IF($B65="","",IFERROR(INDEX(Rubric!$C$14:$C$23,MATCH($B65,Rubric!$A$14:$A$23,0)),INDEX(Rubric!$C$14:$C$23,MATCH("other",Rubric!$A$14:$A$23,0)))) -> 11 | N65: =IF(OR($A65="",$C65=""),"",$C65*Rubric!$B$5+$D65*Rubric!$B$6+$E65*Rubric!$B$7+$F65*Rubric!$B$8+$G65*Rubric!$B$9) -> 4.1 | O65: =IF($A65="","",IF(OR(UPPER($H65)="Y",UPPER($I65)="Y"),"FAIL","PASS")) -> PASS | P65: =IF($N65="","",Assumptions!$B$6*MAX(0.05,($N65/Assumptions!$B$11)^Assumptions!$B$12)) -> 0.013666667 | Q65: =IF($P65="","",1-(1-$P65)^Assumptions!$B$7) -> 0.066490908 | R65: =IF($M65="","",$M65*Assumptions!$B$7) -> 55 | S65: =IF(OR($J65="",$Q65="",$Q65=0),"",($J65+$R65)/($Q65*(1-Assumptions!$B$4))) | T65: =IF(OR($K65="",$S65="",$S65=0),"",$K65/$S65) | U65: =IF(OR($K65="",$Q65=""),"",MAX(0,($K65-MAX($K65*Assumptions!$B$4,Assumptions!$B$5))*$Q65-$R65)) | V65: =IF($A65="","",IF($O65="FAIL","REJECT",IF($J65="","NEEDS PRICE",IF(OR($K65="",$L65=""),"NEEDS VALUATION",IF($T65>=Assumptions!$B$13,"BUY",IF($T65>=1,"MARGINAL","PASS")))))) -> NEEDS PRICE | W65: Taken | X65: [B2/Jargon] Fund-finance term with a wider PE buyer pool than equipment alone.
A66: nonrecourse.com | B66: =IF($A66="","",IF(ISERROR(FIND(".",$A66)),"",LOWER(MID($A66,FIND(CHAR(1),SUBSTITUTE($A66,".",CHAR(1),LEN($A66)-LEN(SUBSTITUTE($A66,".",""))))+1,LEN($A66))))) -> com | C66: =IF($B66="","",IFERROR(INDEX(Rubric!$B$14:$B$23,MATCH($B66,Rubric!$A$14:$A$23,0)),INDEX(Rubric!$B$14:$B$23,MATCH("other",Rubric!$A$14:$A$23,0)))) -> 5 | D66: 4 | E66: 2 | F66: 4 | G66: 4 | H66: N | I66: N | M66: =IF($B66="","",IFERROR(INDEX(Rubric!$C$14:$C$23,MATCH($B66,Rubric!$A$14:$A$23,0)),INDEX(Rubric!$C$14:$C$23,MATCH("other",Rubric!$A$14:$A$23,0)))) -> 11 | N66: =IF(OR($A66="",$C66=""),"",$C66*Rubric!$B$5+$D66*Rubric!$B$6+$E66*Rubric!$B$7+$F66*Rubric!$B$8+$G66*Rubric!$B$9) -> 3.78 | O66: =IF($A66="","",IF(OR(UPPER($H66)="Y",UPPER($I66)="Y"),"FAIL","PASS")) -> PASS | P66: =IF($N66="","",Assumptions!$B$6*MAX(0.05,($N66/Assumptions!$B$11)^Assumptions!$B$12)) -> 0.0126 | Q66: =IF($P66="","",1-(1-$P66)^Assumptions!$B$7) -> 0.061432278 | R66: =IF($M66="","",$M66*Assumptions!$B$7) -> 55 | S66: =IF(OR($J66="",$Q66="",$Q66=0),"",($J66+$R66)/($Q66*(1-Assumptions!$B$4))) | T66: =IF(OR($K66="",$S66="",$S66=0),"",$K66/$S66) | U66: =IF(OR($K66="",$Q66=""),"",MAX(0,($K66-MAX($K66*Assumptions!$B$4,Assumptions!$B$5))*$Q66-$R66)) | V66: =IF($A66="","",IF($O66="FAIL","REJECT",IF($J66="","NEEDS PRICE",IF(OR($K66="",$L66=""),"NEEDS VALUATION",IF($T66>=Assumptions!$B$13,"BUY",IF($T66>=1,"MARGINAL","PASS")))))) -> NEEDS PRICE | W66: Taken | X66: [B2/Jargon] Financing structure term. Single compound word.
A67: termloan.com | B67: =IF($A67="","",IF(ISERROR(FIND(".",$A67)),"",LOWER(MID($A67,FIND(CHAR(1),SUBSTITUTE($A67,".",CHAR(1),LEN($A67)-LEN(SUBSTITUTE($A67,".",""))))+1,LEN($A67))))) -> com | C67: =IF($B67="","",IFERROR(INDEX(Rubric!$B$14:$B$23,MATCH($B67,Rubric!$A$14:$A$23,0)),INDEX(Rubric!$B$14:$B$23,MATCH("other",Rubric!$A$14:$A$23,0)))) -> 5 | D67: 4 | E67: 3 | F67: 5 | G67: 5 | H67: N | I67: N | M67: =IF($B67="","",IFERROR(INDEX(Rubric!$C$14:$C$23,MATCH($B67,Rubric!$A$14:$A$23,0)),INDEX(Rubric!$C$14:$C$23,MATCH("other",Rubric!$A$14:$A$23,0)))) -> 11 | N67: =IF(OR($A67="",$C67=""),"",$C67*Rubric!$B$5+$D67*Rubric!$B$6+$E67*Rubric!$B$7+$F67*Rubric!$B$8+$G67*Rubric!$B$9) -> 4.26 | O67: =IF($A67="","",IF(OR(UPPER($H67)="Y",UPPER($I67)="Y"),"FAIL","PASS")) -> PASS | P67: =IF($N67="","",Assumptions!$B$6*MAX(0.05,($N67/Assumptions!$B$11)^Assumptions!$B$12)) -> 0.0142 | Q67: =IF($P67="","",1-(1-$P67)^Assumptions!$B$7) -> 0.06901203 | R67: =IF($M67="","",$M67*Assumptions!$B$7) -> 55 | S67: =IF(OR($J67="",$Q67="",$Q67=0),"",($J67+$R67)/($Q67*(1-Assumptions!$B$4))) | T67: =IF(OR($K67="",$S67="",$S67=0),"",$K67/$S67) | U67: =IF(OR($K67="",$Q67=""),"",MAX(0,($K67-MAX($K67*Assumptions!$B$4,Assumptions!$B$5))*$Q67-$R67)) | V67: =IF($A67="","",IF($O67="FAIL","REJECT",IF($J67="","NEEDS PRICE",IF(OR($K67="",$L67=""),"NEEDS VALUATION",IF($T67>=Assumptions!$B$13,"BUY",IF($T67>=1,"MARGINAL","PASS")))))) -> NEEDS PRICE | W67: Taken | X67: [B2/Jargon] Clean product term, two short syllables.
A68: creditline.com | B68: =IF($A68="","",IF(ISERROR(FIND(".",$A68)),"",LOWER(MID($A68,FIND(CHAR(1),SUBSTITUTE($A68,".",CHAR(1),LEN($A68)-LEN(SUBSTITUTE($A68,".",""))))+1,LEN($A68))))) -> com | C68: =IF($B68="","",IFERROR(INDEX(Rubric!$B$14:$B$23,MATCH($B68,Rubric!$A$14:$A$23,0)),INDEX(Rubric!$B$14:$B$23,MATCH("other",Rubric!$A$14:$A$23,0)))) -> 5 | D68: 5 | E68: 3 | F68: 5 | G68: 5 | H68: N | I68: N | M68: =IF($B68="","",IFERROR(INDEX(Rubric!$C$14:$C$23,MATCH($B68,Rubric!$A$14:$A$23,0)),INDEX(Rubric!$C$14:$C$23,MATCH("other",Rubric!$A$14:$A$23,0)))) -> 11 | N68: =IF(OR($A68="",$C68=""),"",$C68*Rubric!$B$5+$D68*Rubric!$B$6+$E68*Rubric!$B$7+$F68*Rubric!$B$8+$G68*Rubric!$B$9) -> 4.56 | O68: =IF($A68="","",IF(OR(UPPER($H68)="Y",UPPER($I68)="Y"),"FAIL","PASS")) -> PASS | P68: =IF($N68="","",Assumptions!$B$6*MAX(0.05,($N68/Assumptions!$B$11)^Assumptions!$B$12)) -> 0.0152 | Q68: =IF($P68="","",1-(1-$P68)^Assumptions!$B$7) -> 0.073724452 | R68: =IF($M68="","",$M68*Assumptions!$B$7) -> 55 | S68: =IF(OR($J68="",$Q68="",$Q68=0),"",($J68+$R68)/($Q68*(1-Assumptions!$B$4))) | T68: =IF(OR($K68="",$S68="",$S68=0),"",$K68/$S68) | U68: =IF(OR($K68="",$Q68=""),"",MAX(0,($K68-MAX($K68*Assumptions!$B$4,Assumptions!$B$5))*$Q68-$R68)) | V68: =IF($A68="","",IF($O68="FAIL","REJECT",IF($J68="","NEEDS PRICE",IF(OR($K68="",$L68=""),"NEEDS VALUATION",IF($T68>=Assumptions!$B$13,"BUY",IF($T68>=1,"MARGINAL","PASS")))))) -> NEEDS PRICE | W68: Taken | X68: [B2/Jargon] Very high commercial intent. Expect taken.
A69: originations.com | B69: =IF($A69="","",IF(ISERROR(FIND(".",$A69)),"",LOWER(MID($A69,FIND(CHAR(1),SUBSTITUTE($A69,".",CHAR(1),LEN($A69)-LEN(SUBSTITUTE($A69,".",""))))+1,LEN($A69))))) -> com | C69: =IF($B69="","",IFERROR(INDEX(Rubric!$B$14:$B$23,MATCH($B69,Rubric!$A$14:$A$23,0)),INDEX(Rubric!$B$14:$B$23,MATCH("other",Rubric!$A$14:$A$23,0)))) -> 5 | D69: 4 | E69: 3 | F69: 4 | G69: 4 | H69: N | I69: N | J69: 55000 | M69: =IF($B69="","",IFERROR(INDEX(Rubric!$C$14:$C$23,MATCH($B69,Rubric!$A$14:$A$23,0)),INDEX(Rubric!$C$14:$C$23,MATCH("other",Rubric!$A$14:$A$23,0)))) -> 11 | N69: =IF(OR($A69="",$C69=""),"",$C69*Rubric!$B$5+$D69*Rubric!$B$6+$E69*Rubric!$B$7+$F69*Rubric!$B$8+$G69*Rubric!$B$9) -> 4 | O69: =IF($A69="","",IF(OR(UPPER($H69)="Y",UPPER($I69)="Y"),"FAIL","PASS")) -> PASS | P69: =IF($N69="","",Assumptions!$B$6*MAX(0.05,($N69/Assumptions!$B$11)^Assumptions!$B$12)) -> 0.013333333 | Q69: =IF($P69="","",1-(1-$P69)^Assumptions!$B$7) -> 0.064912435 | R69: =IF($M69="","",$M69*Assumptions!$B$7) -> 55 | S69: =IF(OR($J69="",$Q69="",$Q69=0),"",($J69+$R69)/($Q69*(1-Assumptions!$B$4))) -> 1060178.2 | T69: =IF(OR($K69="",$S69="",$S69=0),"",$K69/$S69) | U69: =IF(OR($K69="",$Q69=""),"",MAX(0,($K69-MAX($K69*Assumptions!$B$4,Assumptions!$B$5))*$Q69-$R69)) | V69: =IF($A69="","",IF($O69="FAIL","REJECT",IF($J69="","NEEDS PRICE",IF(OR($K69="",$L69=""),"NEEDS VALUATION",IF($T69>=Assumptions!$B$13,"BUY",IF($T69>=1,"MARGINAL","PASS")))))) -> NEEDS VALUATION | W69: Available - premium | X69: [B2/Jargon] How lenders describe new business volume.
A70: syndications.com | B70: =IF($A70="","",IF(ISERROR(FIND(".",$A70)),"",LOWER(MID($A70,FIND(CHAR(1),SUBSTITUTE($A70,".",CHAR(1),LEN($A70)-LEN(SUBSTITUTE($A70,".",""))))+1,LEN($A70))))) -> com | C70: =IF($B70="","",IFERROR(INDEX(Rubric!$B$14:$B$23,MATCH($B70,Rubric!$A$14:$A$23,0)),INDEX(Rubric!$B$14:$B$23,MATCH("other",Rubric!$A$14:$A$23,0)))) -> 5 | D70: 3 | E70: 2 | F70: 3 | G70: 4 | H70: N | I70: N | M70: =IF($B70="","",IFERROR(INDEX(Rubric!$C$14:$C$23,MATCH($B70,Rubric!$A$14:$A$23,0)),INDEX(Rubric!$C$14:$C$23,MATCH("other",Rubric!$A$14:$A$23,0)))) -> 11 | N70: =IF(OR($A70="",$C70=""),"",$C70*Rubric!$B$5+$D70*Rubric!$B$6+$E70*Rubric!$B$7+$F70*Rubric!$B$8+$G70*Rubric!$B$9) -> 3.32 | O70: =IF($A70="","",IF(OR(UPPER($H70)="Y",UPPER($I70)="Y"),"FAIL","PASS")) -> PASS | P70: =IF($N70="","",Assumptions!$B$6*MAX(0.05,($N70/Assumptions!$B$11)^Assumptions!$B$12)) -> 0.011066667 | Q70: =IF($P70="","",1-(1-$P70)^Assumptions!$B$7) -> 0.054122101 | R70: =IF($M70="","",$M70*Assumptions!$B$7) -> 55 | S70: =IF(OR($J70="",$Q70="",$Q70=0),"",($J70+$R70)/($Q70*(1-Assumptions!$B$4))) | T70: =IF(OR($K70="",$S70="",$S70=0),"",$K70/$S70) | U70: =IF(OR($K70="",$Q70=""),"",MAX(0,($K70-MAX($K70*Assumptions!$B$4,Assumptions!$B$5))*$Q70-$R70)) | V70: =IF($A70="","",IF($O70="FAIL","REJECT",IF($J70="","NEEDS PRICE",IF(OR($K70="",$L70=""),"NEEDS VALUATION",IF($T70>=Assumptions!$B$13,"BUY",IF($T70>=1,"MARGINAL","PASS")))))) -> NEEDS PRICE | W70: Taken | X70: [B2/Jargon] Lender syndication desks. Narrow institutional pool.
A71: covenants.com | B71: =IF($A71="","",IF(ISERROR(FIND(".",$A71)),"",LOWER(MID($A71,FIND(CHAR(1),SUBSTITUTE($A71,".",CHAR(1),LEN($A71)-LEN(SUBSTITUTE($A71,".",""))))+1,LEN($A71))))) -> com | C71: =IF($B71="","",IFERROR(INDEX(Rubric!$B$14:$B$23,MATCH($B71,Rubric!$A$14:$A$23,0)),INDEX(Rubric!$B$14:$B$23,MATCH("other",Rubric!$A$14:$A$23,0)))) -> 5 | D71: 3 | E71: 2 | F71: 4 | G71: 4 | H71: N | I71: N | M71: =IF($B71="","",IFERROR(INDEX(Rubric!$C$14:$C$23,MATCH($B71,Rubric!$A$14:$A$23,0)),INDEX(Rubric!$C$14:$C$23,MATCH("other",Rubric!$A$14:$A$23,0)))) -> 11 | N71: =IF(OR($A71="",$C71=""),"",$C71*Rubric!$B$5+$D71*Rubric!$B$6+$E71*Rubric!$B$7+$F71*Rubric!$B$8+$G71*Rubric!$B$9) -> 3.48 | O71: =IF($A71="","",IF(OR(UPPER($H71)="Y",UPPER($I71)="Y"),"FAIL","PASS")) -> PASS | P71: =IF($N71="","",Assumptions!$B$6*MAX(0.05,($N71/Assumptions!$B$11)^Assumptions!$B$12)) -> 0.0116 | Q71: =IF($P71="","",1-(1-$P71)^Assumptions!$B$7) -> 0.056669919 | R71: =IF($M71="","",$M71*Assumptions!$B$7) -> 55 | S71: =IF(OR($J71="",$Q71="",$Q71=0),"",($J71+$R71)/($Q71*(1-Assumptions!$B$4))) | T71: =IF(OR($K71="",$S71="",$S71=0),"",$K71/$S71) | U71: =IF(OR($K71="",$Q71=""),"",MAX(0,($K71-MAX($K71*Assumptions!$B$4,Assumptions!$B$5))*$Q71-$R71)) | V71: =IF($A71="","",IF($O71="FAIL","REJECT",IF($J71="","NEEDS PRICE",IF(OR($K71="",$L71=""),"NEEDS VALUATION",IF($T71>=Assumptions!$B$13,"BUY",IF($T71>=1,"MARGINAL","PASS")))))) -> NEEDS PRICE | W71: Taken | X71: [B2/Jargon] Loan covenants. Also has a religious reading — muddies intent.
A72: stipsheet.com | B72: =IF($A72="","",IF(ISERROR(FIND(".",$A72)),"",LOWER(MID($A72,FIND(CHAR(1),SUBSTITUTE($A72,".",CHAR(1),LEN($A72)-LEN(SUBSTITUTE($A72,".",""))))+1,LEN($A72))))) -> com | C72: =IF($B72="","",IFERROR(INDEX(Rubric!$B$14:$B$23,MATCH($B72,Rubric!$A$14:$A$23,0)),INDEX(Rubric!$B$14:$B$23,MATCH("other",Rubric!$A$14:$A$23,0)))) -> 5 | D72: 2 | E72: 1 | F72: 4 | G72: 3 | H72: N | I72: N | J72: 22.99 | M72: =IF($B72="","",IFERROR(INDEX(Rubric!$C$14:$C$23,MATCH($B72,Rubric!$A$14:$A$23,0)),INDEX(Rubric!$C$14:$C$23,MATCH("other",Rubric!$A$14:$A$23,0)))) -> 11 | N72: =IF(OR($A72="",$C72=""),"",$C72*Rubric!$B$5+$D72*Rubric!$B$6+$E72*Rubric!$B$7+$F72*Rubric!$B$8+$G72*Rubric!$B$9) -> 2.86 | O72: =IF($A72="","",IF(OR(UPPER($H72)="Y",UPPER($I72)="Y"),"FAIL","PASS")) -> PASS | P72: =IF($N72="","",Assumptions!$B$6*MAX(0.05,($N72/Assumptions!$B$11)^Assumptions!$B$12)) -> 0.0095333333 | Q72: =IF($P72="","",1-(1-$P72)^Assumptions!$B$7) -> 0.046766445 | R72: =IF($M72="","",$M72*Assumptions!$B$7) -> 55 | S72: =IF(OR($J72="",$Q72="",$Q72=0),"",($J72+$R72)/($Q72*(1-Assumptions!$B$4))) -> 2084.5608 | T72: =IF(OR($K72="",$S72="",$S72=0),"",$K72/$S72) | U72: =IF(OR($K72="",$Q72=""),"",MAX(0,($K72-MAX($K72*Assumptions!$B$4,Assumptions!$B$5))*$Q72-$R72)) | V72: =IF($A72="","",IF($O72="FAIL","REJECT",IF($J72="","NEEDS PRICE",IF(OR($K72="",$L72=""),"NEEDS VALUATION",IF($T72>=Assumptions!$B$13,"BUY",IF($T72>=1,"MARGINAL","PASS")))))) -> NEEDS VALUATION | W72: Available - reg | X72: [B2/Jargon] 'Stips' is deep insider slang. Too obscure — included to test the floor.
A73: getfunded.com | B73: =IF($A73="","",IF(ISERROR(FIND(".",$A73)),"",LOWER(MID($A73,FIND(CHAR(1),SUBSTITUTE($A73,".",CHAR(1),LEN($A73)-LEN(SUBSTITUTE($A73,".",""))))+1,LEN($A73))))) -> com | C73: =IF($B73="","",IFERROR(INDEX(Rubric!$B$14:$B$23,MATCH($B73,Rubric!$A$14:$A$23,0)),INDEX(Rubric!$B$14:$B$23,MATCH("other",Rubric!$A$14:$A$23,0)))) -> 5 | D73: 5 | E73: 3 | F73: 5 | G73: 5 | H73: N | I73: N | M73: =IF($B73="","",IFERROR(INDEX(Rubric!$C$14:$C$23,MATCH($B73,Rubric!$A$14:$A$23,0)),INDEX(Rubric!$C$14:$C$23,MATCH("other",Rubric!$A$14:$A$23,0)))) -> 11 | N73: =IF(OR($A73="",$C73=""),"",$C73*Rubric!$B$5+$D73*Rubric!$B$6+$E73*Rubric!$B$7+$F73*Rubric!$B$8+$G73*Rubric!$B$9) -> 4.56 | O73: =IF($A73="","",IF(OR(UPPER($H73)="Y",UPPER($I73)="Y"),"FAIL","PASS")) -> PASS | P73: =IF($N73="","",Assumptions!$B$6*MAX(0.05,($N73/Assumptions!$B$11)^Assumptions!$B$12)) -> 0.0152 | Q73: =IF($P73="","",1-(1-$P73)^Assumptions!$B$7) -> 0.073724452 | R73: =IF($M73="","",$M73*Assumptions!$B$7) -> 55 | S73: =IF(OR($J73="",$Q73="",$Q73=0),"",($J73+$R73)/($Q73*(1-Assumptions!$B$4))) | T73: =IF(OR($K73="",$S73="",$S73=0),"",$K73/$S73) | U73: =IF(OR($K73="",$Q73=""),"",MAX(0,($K73-MAX($K73*Assumptions!$B$4,Assumptions!$B$5))*$Q73-$R73)) | V73: =IF($A73="","",IF($O73="FAIL","REJECT",IF($J73="","NEEDS PRICE",IF(OR($K73="",$L73=""),"NEEDS VALUATION",IF($T73>=Assumptions!$B$13,"BUY",IF($T73>=1,"MARGINAL","PASS")))))) -> NEEDS PRICE | W73: Taken | X73: [B2/Action] Direct call to action, exactly what a borrower types. Expect taken.
A74: getapproved.com | B74: =IF($A74="","",IF(ISERROR(FIND(".",$A74)),"",LOWER(MID($A74,FIND(CHAR(1),SUBSTITUTE($A74,".",CHAR(1),LEN($A74)-LEN(SUBSTITUTE($A74,".",""))))+1,LEN($A74))))) -> com | C74: =IF($B74="","",IFERROR(INDEX(Rubric!$B$14:$B$23,MATCH($B74,Rubric!$A$14:$A$23,0)),INDEX(Rubric!$B$14:$B$23,MATCH("other",Rubric!$A$14:$A$23,0)))) -> 5 | D74: 4 | E74: 3 | F74: 5 | G74: 5 | H74: N | I74: N | M74: =IF($B74="","",IFERROR(INDEX(Rubric!$C$14:$C$23,MATCH($B74,Rubric!$A$14:$A$23,0)),INDEX(Rubric!$C$14:$C$23,MATCH("other",Rubric!$A$14:$A$23,0)))) -> 11 | N74: =IF(OR($A74="",$C74=""),"",$C74*Rubric!$B$5+$D74*Rubric!$B$6+$E74*Rubric!$B$7+$F74*Rubric!$B$8+$G74*Rubric!$B$9) -> 4.26 | O74: =IF($A74="","",IF(OR(UPPER($H74)="Y",UPPER($I74)="Y"),"FAIL","PASS")) -> PASS | P74: =IF($N74="","",Assumptions!$B$6*MAX(0.05,($N74/Assumptions!$B$11)^Assumptions!$B$12)) -> 0.0142 | Q74: =IF($P74="","",1-(1-$P74)^Assumptions!$B$7) -> 0.06901203 | R74: =IF($M74="","",$M74*Assumptions!$B$7) -> 55 | S74: =IF(OR($J74="",$Q74="",$Q74=0),"",($J74+$R74)/($Q74*(1-Assumptions!$B$4))) | T74: =IF(OR($K74="",$S74="",$S74=0),"",$K74/$S74) | U74: =IF(OR($K74="",$Q74=""),"",MAX(0,($K74-MAX($K74*Assumptions!$B$4,Assumptions!$B$5))*$Q74-$R74)) | V74: =IF($A74="","",IF($O74="FAIL","REJECT",IF($J74="","NEEDS PRICE",IF(OR($K74="",$L74=""),"NEEDS VALUATION",IF($T74>=Assumptions!$B$13,"BUY",IF($T74>=1,"MARGINAL","PASS")))))) -> NEEDS PRICE | W74: Taken | X74: [B2/Action] Same pattern, slightly broader than lending.
A75: prequalify.com | B75: =IF($A75="","",IF(ISERROR(FIND(".",$A75)),"",LOWER(MID($A75,FIND(CHAR(1),SUBSTITUTE($A75,".",CHAR(1),LEN($A75)-LEN(SUBSTITUTE($A75,".",""))))+1,LEN($A75))))) -> com | C75: =IF($B75="","",IFERROR(INDEX(Rubric!$B$14:$B$23,MATCH($B75,Rubric!$A$14:$A$23,0)),INDEX(Rubric!$B$14:$B$23,MATCH("other",Rubric!$A$14:$A$23,0)))) -> 5 | D75: 5 | E75: 3 | F75: 4 | G75: 5 | H75: N | I75: N | M75: =IF($B75="","",IFERROR(INDEX(Rubric!$C$14:$C$23,MATCH($B75,Rubric!$A$14:$A$23,0)),INDEX(Rubric!$C$14:$C$23,MATCH("other",Rubric!$A$14:$A$23,0)))) -> 11 | N75: =IF(OR($A75="",$C75=""),"",$C75*Rubric!$B$5+$D75*Rubric!$B$6+$E75*Rubric!$B$7+$F75*Rubric!$B$8+$G75*Rubric!$B$9) -> 4.4 | O75: =IF($A75="","",IF(OR(UPPER($H75)="Y",UPPER($I75)="Y"),"FAIL","PASS")) -> PASS | P75: =IF($N75="","",Assumptions!$B$6*MAX(0.05,($N75/Assumptions!$B$11)^Assumptions!$B$12)) -> 0.014666667 | Q75: =IF($P75="","",1-(1-$P75)^Assumptions!$B$7) -> 0.071213541 | R75: =IF($M75="","",$M75*Assumptions!$B$7) -> 55 | S75: =IF(OR($J75="",$Q75="",$Q75=0),"",($J75+$R75)/($Q75*(1-Assumptions!$B$4))) | T75: =IF(OR($K75="",$S75="",$S75=0),"",$K75/$S75) | U75: =IF(OR($K75="",$Q75=""),"",MAX(0,($K75-MAX($K75*Assumptions!$B$4,Assumptions!$B$5))*$Q75-$R75)) | V75: =IF($A75="","",IF($O75="FAIL","REJECT",IF($J75="","NEEDS PRICE",IF(OR($K75="",$L75=""),"NEEDS VALUATION",IF($T75>=Assumptions!$B$13,"BUY",IF($T75>=1,"MARGINAL","PASS")))))) -> NEEDS PRICE | W75: Taken | X75: [B2/Action] Real lending-funnel term with very high intent. Expect taken.
A76: fundfast.com | B76: =IF($A76="","",IF(ISERROR(FIND(".",$A76)),"",LOWER(MID($A76,FIND(CHAR(1),SUBSTITUTE($A76,".",CHAR(1),LEN($A76)-LEN(SUBSTITUTE($A76,".",""))))+1,LEN($A76))))) -> com | C76: =IF($B76="","",IFERROR(INDEX(Rubric!$B$14:$B$23,MATCH($B76,Rubric!$A$14:$A$23,0)),INDEX(Rubric!$B$14:$B$23,MATCH("other",Rubric!$A$14:$A$23,0)))) -> 5 | D76: 4 | E76: 3 | F76: 5 | G76: 5 | H76: N | I76: N | M76: =IF($B76="","",IFERROR(INDEX(Rubric!$C$14:$C$23,MATCH($B76,Rubric!$A$14:$A$23,0)),INDEX(Rubric!$C$14:$C$23,MATCH("other",Rubric!$A$14:$A$23,0)))) -> 11 | N76: =IF(OR($A76="",$C76=""),"",$C76*Rubric!$B$5+$D76*Rubric!$B$6+$E76*Rubric!$B$7+$F76*Rubric!$B$8+$G76*Rubric!$B$9) -> 4.26 | O76: =IF($A76="","",IF(OR(UPPER($H76)="Y",UPPER($I76)="Y"),"FAIL","PASS")) -> PASS | P76: =IF($N76="","",Assumptions!$B$6*MAX(0.05,($N76/Assumptions!$B$11)^Assumptions!$B$12)) -> 0.0142 | Q76: =IF($P76="","",1-(1-$P76)^Assumptions!$B$7) -> 0.06901203 | R76: =IF($M76="","",$M76*Assumptions!$B$7) -> 55 | S76: =IF(OR($J76="",$Q76="",$Q76=0),"",($J76+$R76)/($Q76*(1-Assumptions!$B$4))) | T76: =IF(OR($K76="",$S76="",$S76=0),"",$K76/$S76) | U76: =IF(OR($K76="",$Q76=""),"",MAX(0,($K76-MAX($K76*Assumptions!$B$4,Assumptions!$B$5))*$Q76-$R76)) | V76: =IF($A76="","",IF($O76="FAIL","REJECT",IF($J76="","NEEDS PRICE",IF(OR($K76="",$L76=""),"NEEDS VALUATION",IF($T76>=Assumptions!$B$13,"BUY",IF($T76>=1,"MARGINAL","PASS")))))) -> NEEDS PRICE | W76: Taken | X76: [B2/Action] Speed is the actual selling point in commercial lending.
A77: approvefast.com | B77: =IF($A77="","",IF(ISERROR(FIND(".",$A77)),"",LOWER(MID($A77,FIND(CHAR(1),SUBSTITUTE($A77,".",CHAR(1),LEN($A77)-LEN(SUBSTITUTE($A77,".",""))))+1,LEN($A77))))) -> com | C77: =IF($B77="","",IFERROR(INDEX(Rubric!$B$14:$B$23,MATCH($B77,Rubric!$A$14:$A$23,0)),INDEX(Rubric!$B$14:$B$23,MATCH("other",Rubric!$A$14:$A$23,0)))) -> 5 | D77: 3 | E77: 2 | F77: 4 | G77: 5 | H77: N | I77: N | J77: 3495 | M77: =IF($B77="","",IFERROR(INDEX(Rubric!$C$14:$C$23,MATCH($B77,Rubric!$A$14:$A$23,0)),INDEX(Rubric!$C$14:$C$23,MATCH("other",Rubric!$A$14:$A$23,0)))) -> 11 | N77: =IF(OR($A77="",$C77=""),"",$C77*Rubric!$B$5+$D77*Rubric!$B$6+$E77*Rubric!$B$7+$F77*Rubric!$B$8+$G77*Rubric!$B$9) -> 3.58 | O77: =IF($A77="","",IF(OR(UPPER($H77)="Y",UPPER($I77)="Y"),"FAIL","PASS")) -> PASS | P77: =IF($N77="","",Assumptions!$B$6*MAX(0.05,($N77/Assumptions!$B$11)^Assumptions!$B$12)) -> 0.011933333 | Q77: =IF($P77="","",1-(1-$P77)^Assumptions!$B$7) -> 0.058259515 | R77: =IF($M77="","",$M77*Assumptions!$B$7) -> 55 | S77: =IF(OR($J77="",$Q77="",$Q77=0),"",($J77+$R77)/($Q77*(1-Assumptions!$B$4))) -> 76167.816 | T77: =IF(OR($K77="",$S77="",$S77=0),"",$K77/$S77) | U77: =IF(OR($K77="",$Q77=""),"",MAX(0,($K77-MAX($K77*Assumptions!$B$4,Assumptions!$B$5))*$Q77-$R77)) | V77: =IF($A77="","",IF($O77="FAIL","REJECT",IF($J77="","NEEDS PRICE",IF(OR($K77="",$L77=""),"NEEDS VALUATION",IF($T77>=Assumptions!$B$13,"BUY",IF($T77>=1,"MARGINAL","PASS")))))) -> NEEDS VALUATION | W77: Available - premium | X77: [B2/Action] Same idea, weaker word pairing.
A78: leaseit.com | B78: =IF($A78="","",IF(ISERROR(FIND(".",$A78)),"",LOWER(MID($A78,FIND(CHAR(1),SUBSTITUTE($A78,".",CHAR(1),LEN($A78)-LEN(SUBSTITUTE($A78,".",""))))+1,LEN($A78))))) -> com | C78: =IF($B78="","",IFERROR(INDEX(Rubric!$B$14:$B$23,MATCH($B78,Rubric!$A$14:$A$23,0)),INDEX(Rubric!$B$14:$B$23,MATCH("other",Rubric!$A$14:$A$23,0)))) -> 5 | D78: 4 | E78: 3 | F78: 5 | G78: 4 | H78: N | I78: N | M78: =IF($B78="","",IFERROR(INDEX(Rubric!$C$14:$C$23,MATCH($B78,Rubric!$A$14:$A$23,0)),INDEX(Rubric!$C$14:$C$23,MATCH("other",Rubric!$A$14:$A$23,0)))) -> 11 | N78: =IF(OR($A78="",$C78=""),"",$C78*Rubric!$B$5+$D78*Rubric!$B$6+$E78*Rubric!$B$7+$F78*Rubric!$B$8+$G78*Rubric!$B$9) -> 4.16 | O78: =IF($A78="","",IF(OR(UPPER($H78)="Y",UPPER($I78)="Y"),"FAIL","PASS")) -> PASS | P78: =IF($N78="","",Assumptions!$B$6*MAX(0.05,($N78/Assumptions!$B$11)^Assumptions!$B$12)) -> 0.013866667 | Q78: =IF($P78="","",1-(1-$P78)^Assumptions!$B$7) -> 0.067436968 | R78: =IF($M78="","",$M78*Assumptions!$B$7) -> 55 | S78: =IF(OR($J78="",$Q78="",$Q78=0),"",($J78+$R78)/($Q78*(1-Assumptions!$B$4))) | T78: =IF(OR($K78="",$S78="",$S78=0),"",$K78/$S78) | U78: =IF(OR($K78="",$Q78=""),"",MAX(0,($K78-MAX($K78*Assumptions!$B$4,Assumptions!$B$5))*$Q78-$R78)) | V78: =IF($A78="","",IF($O78="FAIL","REJECT",IF($J78="","NEEDS PRICE",IF(OR($K78="",$L78=""),"NEEDS VALUATION",IF($T78>=Assumptions!$B$13,"BUY",IF($T78>=1,"MARGINAL","PASS")))))) -> NEEDS PRICE | W78: Taken | X78: [B2/Action] Short and punchy. 'it' is slightly weak when spoken.
A79: borrowsmart.com | B79: =IF($A79="","",IF(ISERROR(FIND(".",$A79)),"",LOWER(MID($A79,FIND(CHAR(1),SUBSTITUTE($A79,".",CHAR(1),LEN($A79)-LEN(SUBSTITUTE($A79,".",""))))+1,LEN($A79))))) -> com | C79: =IF($B79="","",IFERROR(INDEX(Rubric!$B$14:$B$23,MATCH($B79,Rubric!$A$14:$A$23,0)),INDEX(Rubric!$B$14:$B$23,MATCH("other",Rubric!$A$14:$A$23,0)))) -> 5 | D79: 3 | E79: 2 | F79: 4 | G79: 5 | H79: N | I79: N | M79: =IF($B79="","",IFERROR(INDEX(Rubric!$C$14:$C$23,MATCH($B79,Rubric!$A$14:$A$23,0)),INDEX(Rubric!$C$14:$C$23,MATCH("other",Rubric!$A$14:$A$23,0)))) -> 11 | N79: =IF(OR($A79="",$C79=""),"",$C79*Rubric!$B$5+$D79*Rubric!$B$6+$E79*Rubric!$B$7+$F79*Rubric!$B$8+$G79*Rubric!$B$9) -> 3.58 | O79: =IF($A79="","",IF(OR(UPPER($H79)="Y",UPPER($I79)="Y"),"FAIL","PASS")) -> PASS | P79: =IF($N79="","",Assumptions!$B$6*MAX(0.05,($N79/Assumptions!$B$11)^Assumptions!$B$12)) -> 0.011933333 | Q79: =IF($P79="","",1-(1-$P79)^Assumptions!$B$7) -> 0.058259515 | R79: =IF($M79="","",$M79*Assumptions!$B$7) -> 55 | S79: =IF(OR($J79="",$Q79="",$Q79=0),"",($J79+$R79)/($Q79*(1-Assumptions!$B$4))) | T79: =IF(OR($K79="",$S79="",$S79=0),"",$K79/$S79) | U79: =IF(OR($K79="",$Q79=""),"",MAX(0,($K79-MAX($K79*Assumptions!$B$4,Assumptions!$B$5))*$Q79-$R79)) | V79: =IF($A79="","",IF($O79="FAIL","REJECT",IF($J79="","NEEDS PRICE",IF(OR($K79="",$L79=""),"NEEDS VALUATION",IF($T79>=Assumptions!$B$13,"BUY",IF($T79>=1,"MARGINAL","PASS")))))) -> NEEDS PRICE | W79: Taken | X79: [B2/Action] Generic advice framing rather than a product.
A80: fundmyfleet.com | B80: =IF($A80="","",IF(ISERROR(FIND(".",$A80)),"",LOWER(MID($A80,FIND(CHAR(1),SUBSTITUTE($A80,".",CHAR(1),LEN($A80)-LEN(SUBSTITUTE($A80,".",""))))+1,LEN($A80))))) -> com | C80: =IF($B80="","",IFERROR(INDEX(Rubric!$B$14:$B$23,MATCH($B80,Rubric!$A$14:$A$23,0)),INDEX(Rubric!$B$14:$B$23,MATCH("other",Rubric!$A$14:$A$23,0)))) -> 5 | D80: 3 | E80: 2 | F80: 3 | G80: 5 | H80: N | I80: N | M80: =IF($B80="","",IFERROR(INDEX(Rubric!$C$14:$C$23,MATCH($B80,Rubric!$A$14:$A$23,0)),INDEX(Rubric!$C$14:$C$23,MATCH("other",Rubric!$A$14:$A$23,0)))) -> 11 | N80: =IF(OR($A80="",$C80=""),"",$C80*Rubric!$B$5+$D80*Rubric!$B$6+$E80*Rubric!$B$7+$F80*Rubric!$B$8+$G80*Rubric!$B$9) -> 3.42 | O80: =IF($A80="","",IF(OR(UPPER($H80)="Y",UPPER($I80)="Y"),"FAIL","PASS")) -> PASS | P80: =IF($N80="","",Assumptions!$B$6*MAX(0.05,($N80/Assumptions!$B$11)^Assumptions!$B$12)) -> 0.0114 | Q80: =IF($P80="","",1-(1-$P80)^Assumptions!$B$7) -> 0.055715131 | R80: =IF($M80="","",$M80*Assumptions!$B$7) -> 55 | S80: =IF(OR($J80="",$Q80="",$Q80=0),"",($J80+$R80)/($Q80*(1-Assumptions!$B$4))) | T80: =IF(OR($K80="",$S80="",$S80=0),"",$K80/$S80) | U80: =IF(OR($K80="",$Q80=""),"",MAX(0,($K80-MAX($K80*Assumptions!$B$4,Assumptions!$B$5))*$Q80-$R80)) | V80: =IF($A80="","",IF($O80="FAIL","REJECT",IF($J80="","NEEDS PRICE",IF(OR($K80="",$L80=""),"NEEDS VALUATION",IF($T80>=Assumptions!$B$13,"BUY",IF($T80>=1,"MARGINAL","PASS")))))) -> NEEDS PRICE | W80: Taken | X80: [B2/Action] Three words, but alliterative and clear. Fleet is a real vertical.
A81: ballast.com | B81: =IF($A81="","",IF(ISERROR(FIND(".",$A81)),"",LOWER(MID($A81,FIND(CHAR(1),SUBSTITUTE($A81,".",CHAR(1),LEN($A81)-LEN(SUBSTITUTE($A81,".",""))))+1,LEN($A81))))) -> com | C81: =IF($B81="","",IFERROR(INDEX(Rubric!$B$14:$B$23,MATCH($B81,Rubric!$A$14:$A$23,0)),INDEX(Rubric!$B$14:$B$23,MATCH("other",Rubric!$A$14:$A$23,0)))) -> 5 | D81: 3 | E81: 3 | F81: 5 | G81: 5 | H81: N | I81: N | M81: =IF($B81="","",IFERROR(INDEX(Rubric!$C$14:$C$23,MATCH($B81,Rubric!$A$14:$A$23,0)),INDEX(Rubric!$C$14:$C$23,MATCH("other",Rubric!$A$14:$A$23,0)))) -> 11 | N81: =IF(OR($A81="",$C81=""),"",$C81*Rubric!$B$5+$D81*Rubric!$B$6+$E81*Rubric!$B$7+$F81*Rubric!$B$8+$G81*Rubric!$B$9) -> 3.96 | O81: =IF($A81="","",IF(OR(UPPER($H81)="Y",UPPER($I81)="Y"),"FAIL","PASS")) -> PASS | P81: =IF($N81="","",Assumptions!$B$6*MAX(0.05,($N81/Assumptions!$B$11)^Assumptions!$B$12)) -> 0.0132 | Q81: =IF($P81="","",1-(1-$P81)^Assumptions!$B$7) -> 0.064280448 | R81: =IF($M81="","",$M81*Assumptions!$B$7) -> 55 | S81: =IF(OR($J81="",$Q81="",$Q81=0),"",($J81+$R81)/($Q81*(1-Assumptions!$B$4))) | T81: =IF(OR($K81="",$S81="",$S81=0),"",$K81/$S81) | U81: =IF(OR($K81="",$Q81=""),"",MAX(0,($K81-MAX($K81*Assumptions!$B$4,Assumptions!$B$5))*$Q81-$R81)) | V81: =IF($A81="","",IF($O81="FAIL","REJECT",IF($J81="","NEEDS PRICE",IF(OR($K81="",$L81=""),"NEEDS VALUATION",IF($T81>=Assumptions!$B$13,"BUY",IF($T81>=1,"MARGINAL","PASS")))))) -> NEEDS PRICE | W81: Taken | X81: [B2/Metaphor] Stability metaphor, clean dictionary word. Expect taken or expensive.
A82: linchpin.com | B82: =IF($A82="","",IF(ISERROR(FIND(".",$A82)),"",LOWER(MID($A82,FIND(CHAR(1),SUBSTITUTE($A82,".",CHAR(1),LEN($A82)-LEN(SUBSTITUTE($A82,".",""))))+1,LEN($A82))))) -> com | C82: =IF($B82="","",IFERROR(INDEX(Rubric!$B$14:$B$23,MATCH($B82,Rubric!$A$14:$A$23,0)),INDEX(Rubric!$B$14:$B$23,MATCH("other",Rubric!$A$14:$A$23,0)))) -> 5 | D82: 3 | E82: 3 | F82: 5 | G82: 4 | H82: N | I82: N | M82: =IF($B82="","",IFERROR(INDEX(Rubric!$C$14:$C$23,MATCH($B82,Rubric!$A$14:$A$23,0)),INDEX(Rubric!$C$14:$C$23,MATCH("other",Rubric!$A$14:$A$23,0)))) -> 11 | N82: =IF(OR($A82="",$C82=""),"",$C82*Rubric!$B$5+$D82*Rubric!$B$6+$E82*Rubric!$B$7+$F82*Rubric!$B$8+$G82*Rubric!$B$9) -> 3.86 | O82: =IF($A82="","",IF(OR(UPPER($H82)="Y",UPPER($I82)="Y"),"FAIL","PASS")) -> PASS | P82: =IF($N82="","",Assumptions!$B$6*MAX(0.05,($N82/Assumptions!$B$11)^Assumptions!$B$12)) -> 0.012866667 | Q82: =IF($P82="","",1-(1-$P82)^Assumptions!$B$7) -> 0.062698986 | R82: =IF($M82="","",$M82*Assumptions!$B$7) -> 55 | S82: =IF(OR($J82="",$Q82="",$Q82=0),"",($J82+$R82)/($Q82*(1-Assumptions!$B$4))) | T82: =IF(OR($K82="",$S82="",$S82=0),"",$K82/$S82) | U82: =IF(OR($K82="",$Q82=""),"",MAX(0,($K82-MAX($K82*Assumptions!$B$4,Assumptions!$B$5))*$Q82-$R82)) | V82: =IF($A82="","",IF($O82="FAIL","REJECT",IF($J82="","NEEDS PRICE",IF(OR($K82="",$L82=""),"NEEDS VALUATION",IF($T82>=Assumptions!$B$13,"BUY",IF($T82>=1,"MARGINAL","PASS")))))) -> NEEDS PRICE | W82: Taken | X82: [B2/Metaphor] Strong business metaphor, broad appeal beyond lending.
A83: ratchet.com | B83: =IF($A83="","",IF(ISERROR(FIND(".",$A83)),"",LOWER(MID($A83,FIND(CHAR(1),SUBSTITUTE($A83,".",CHAR(1),LEN($A83)-LEN(SUBSTITUTE($A83,".",""))))+1,LEN($A83))))) -> com | C83: =IF($B83="","",IFERROR(INDEX(Rubric!$B$14:$B$23,MATCH($B83,Rubric!$A$14:$A$23,0)),INDEX(Rubric!$B$14:$B$23,MATCH("other",Rubric!$A$14:$A$23,0)))) -> 5 | D83: 3 | E83: 3 | F83: 5 | G83: 5 | H83: N | I83: N | M83: =IF($B83="","",IFERROR(INDEX(Rubric!$C$14:$C$23,MATCH($B83,Rubric!$A$14:$A$23,0)),INDEX(Rubric!$C$14:$C$23,MATCH("other",Rubric!$A$14:$A$23,0)))) -> 11 | N83: =IF(OR($A83="",$C83=""),"",$C83*Rubric!$B$5+$D83*Rubric!$B$6+$E83*Rubric!$B$7+$F83*Rubric!$B$8+$G83*Rubric!$B$9) -> 3.96 | O83: =IF($A83="","",IF(OR(UPPER($H83)="Y",UPPER($I83)="Y"),"FAIL","PASS")) -> PASS | P83: =IF($N83="","",Assumptions!$B$6*MAX(0.05,($N83/Assumptions!$B$11)^Assumptions!$B$12)) -> 0.0132 | Q83: =IF($P83="","",1-(1-$P83)^Assumptions!$B$7) -> 0.064280448 | R83: =IF($M83="","",$M83*Assumptions!$B$7) -> 55 | S83: =IF(OR($J83="",$Q83="",$Q83=0),"",($J83+$R83)/($Q83*(1-Assumptions!$B$4))) | T83: =IF(OR($K83="",$S83="",$S83=0),"",$K83/$S83) | U83: =IF(OR($K83="",$Q83=""),"",MAX(0,($K83-MAX($K83*Assumptions!$B$4,Assumptions!$B$5))*$Q83-$R83)) | V83: =IF($A83="","",IF($O83="FAIL","REJECT",IF($J83="","NEEDS PRICE",IF(OR($K83="",$L83=""),"NEEDS VALUATION",IF($T83>=Assumptions!$B$13,"BUY",IF($T83>=1,"MARGINAL","PASS")))))) -> NEEDS PRICE | W83: Taken | X83: [B2/Metaphor] Also a genuine PE structuring term. Dual meaning helps.
A84: trestle.com | B84: =IF($A84="","",IF(ISERROR(FIND(".",$A84)),"",LOWER(MID($A84,FIND(CHAR(1),SUBSTITUTE($A84,".",CHAR(1),LEN($A84)-LEN(SUBSTITUTE($A84,".",""))))+1,LEN($A84))))) -> com | C84: =IF($B84="","",IFERROR(INDEX(Rubric!$B$14:$B$23,MATCH($B84,Rubric!$A$14:$A$23,0)),INDEX(Rubric!$B$14:$B$23,MATCH("other",Rubric!$A$14:$A$23,0)))) -> 5 | D84: 3 | E84: 2 | F84: 5 | G84: 4 | H84: N | I84: N | M84: =IF($B84="","",IFERROR(INDEX(Rubric!$C$14:$C$23,MATCH($B84,Rubric!$A$14:$A$23,0)),INDEX(Rubric!$C$14:$C$23,MATCH("other",Rubric!$A$14:$A$23,0)))) -> 11 | N84: =IF(OR($A84="",$C84=""),"",$C84*Rubric!$B$5+$D84*Rubric!$B$6+$E84*Rubric!$B$7+$F84*Rubric!$B$8+$G84*Rubric!$B$9) -> 3.64 | O84: =IF($A84="","",IF(OR(UPPER($H84)="Y",UPPER($I84)="Y"),"FAIL","PASS")) -> PASS | P84: =IF($N84="","",Assumptions!$B$6*MAX(0.05,($N84/Assumptions!$B$11)^Assumptions!$B$12)) -> 0.012133333 | Q84: =IF($P84="","",1-(1-$P84)^Assumptions!$B$7) -> 0.059212243 | R84: =IF($M84="","",$M84*Assumptions!$B$7) -> 55 | S84: =IF(OR($J84="",$Q84="",$Q84=0),"",($J84+$R84)/($Q84*(1-Assumptions!$B$4))) | T84: =IF(OR($K84="",$S84="",$S84=0),"",$K84/$S84) | U84: =IF(OR($K84="",$Q84=""),"",MAX(0,($K84-MAX($K84*Assumptions!$B$4,Assumptions!$B$5))*$Q84-$R84)) | V84: =IF($A84="","",IF($O84="FAIL","REJECT",IF($J84="","NEEDS PRICE",IF(OR($K84="",$L84=""),"NEEDS VALUATION",IF($T84>=Assumptions!$B$13,"BUY",IF($T84>=1,"MARGINAL","PASS")))))) -> NEEDS PRICE | W84: Taken | X84: [B2/Metaphor] Bridge structure. Quietly industrial.
A85: gantry.com | B85: =IF($A85="","",IF(ISERROR(FIND(".",$A85)),"",LOWER(MID($A85,FIND(CHAR(1),SUBSTITUTE($A85,".",CHAR(1),LEN($A85)-LEN(SUBSTITUTE($A85,".",""))))+1,LEN($A85))))) -> com | C85: =IF($B85="","",IFERROR(INDEX(Rubric!$B$14:$B$23,MATCH($B85,Rubric!$A$14:$A$23,0)),INDEX(Rubric!$B$14:$B$23,MATCH("other",Rubric!$A$14:$A$23,0)))) -> 5 | D85: 3 | E85: 2 | F85: 5 | G85: 4 | H85: N | I85: N | M85: =IF($B85="","",IFERROR(INDEX(Rubric!$C$14:$C$23,MATCH($B85,Rubric!$A$14:$A$23,0)),INDEX(Rubric!$C$14:$C$23,MATCH("other",Rubric!$A$14:$A$23,0)))) -> 11 | N85: =IF(OR($A85="",$C85=""),"",$C85*Rubric!$B$5+$D85*Rubric!$B$6+$E85*Rubric!$B$7+$F85*Rubric!$B$8+$G85*Rubric!$B$9) -> 3.64 | O85: =IF($A85="","",IF(OR(UPPER($H85)="Y",UPPER($I85)="Y"),"FAIL","PASS")) -> PASS | P85: =IF($N85="","",Assumptions!$B$6*MAX(0.05,($N85/Assumptions!$B$11)^Assumptions!$B$12)) -> 0.012133333 | Q85: =IF($P85="","",1-(1-$P85)^Assumptions!$B$7) -> 0.059212243 | R85: =IF($M85="","",$M85*Assumptions!$B$7) -> 55 | S85: =IF(OR($J85="",$Q85="",$Q85=0),"",($J85+$R85)/($Q85*(1-Assumptions!$B$4))) | T85: =IF(OR($K85="",$S85="",$S85=0),"",$K85/$S85) | U85: =IF(OR($K85="",$Q85=""),"",MAX(0,($K85-MAX($K85*Assumptions!$B$4,Assumptions!$B$5))*$Q85-$R85)) | V85: =IF($A85="","",IF($O85="FAIL","REJECT",IF($J85="","NEEDS PRICE",IF(OR($K85="",$L85=""),"NEEDS VALUATION",IF($T85>=Assumptions!$B$13,"BUY",IF($T85>=1,"MARGINAL","PASS")))))) -> NEEDS PRICE | W85: Taken | X85: [B2/Metaphor] Crane gantry — directly evokes heavy equipment.
A86: capstan.com | B86: =IF($A86="","",IF(ISERROR(FIND(".",$A86)),"",LOWER(MID($A86,FIND(CHAR(1),SUBSTITUTE($A86,".",CHAR(1),LEN($A86)-LEN(SUBSTITUTE($A86,".",""))))+1,LEN($A86))))) -> com | C86: =IF($B86="","",IFERROR(INDEX(Rubric!$B$14:$B$23,MATCH($B86,Rubric!$A$14:$A$23,0)),INDEX(Rubric!$B$14:$B$23,MATCH("other",Rubric!$A$14:$A$23,0)))) -> 5 | D86: 3 | E86: 2 | F86: 5 | G86: 4 | H86: N | I86: N | M86: =IF($B86="","",IFERROR(INDEX(Rubric!$C$14:$C$23,MATCH($B86,Rubric!$A$14:$A$23,0)),INDEX(Rubric!$C$14:$C$23,MATCH("other",Rubric!$A$14:$A$23,0)))) -> 11 | N86: =IF(OR($A86="",$C86=""),"",$C86*Rubric!$B$5+$D86*Rubric!$B$6+$E86*Rubric!$B$7+$F86*Rubric!$B$8+$G86*Rubric!$B$9) -> 3.64 | O86: =IF($A86="","",IF(OR(UPPER($H86)="Y",UPPER($I86)="Y"),"FAIL","PASS")) -> PASS | P86: =IF($N86="","",Assumptions!$B$6*MAX(0.05,($N86/Assumptions!$B$11)^Assumptions!$B$12)) -> 0.012133333 | Q86: =IF($P86="","",1-(1-$P86)^Assumptions!$B$7) -> 0.059212243 | R86: =IF($M86="","",$M86*Assumptions!$B$7) -> 55 | S86: =IF(OR($J86="",$Q86="",$Q86=0),"",($J86+$R86)/($Q86*(1-Assumptions!$B$4))) | T86: =IF(OR($K86="",$S86="",$S86=0),"",$K86/$S86) | U86: =IF(OR($K86="",$Q86=""),"",MAX(0,($K86-MAX($K86*Assumptions!$B$4,Assumptions!$B$5))*$Q86-$R86)) | V86: =IF($A86="","",IF($O86="FAIL","REJECT",IF($J86="","NEEDS PRICE",IF(OR($K86="",$L86=""),"NEEDS VALUATION",IF($T86>=Assumptions!$B$13,"BUY",IF($T86>=1,"MARGINAL","PASS")))))) -> NEEDS PRICE | W86: Taken | X86: [B2/Metaphor] Winch drum. Obscure to outsiders, evocative to insiders.
A87: bollard.com | B87: =IF($A87="","",IF(ISERROR(FIND(".",$A87)),"",LOWER(MID($A87,FIND(CHAR(1),SUBSTITUTE($A87,".",CHAR(1),LEN($A87)-LEN(SUBSTITUTE($A87,".",""))))+1,LEN($A87))))) -> com | C87: =IF($B87="","",IFERROR(INDEX(Rubric!$B$14:$B$23,MATCH($B87,Rubric!$A$14:$A$23,0)),INDEX(Rubric!$B$14:$B$23,MATCH("other",Rubric!$A$14:$A$23,0)))) -> 5 | D87: 2 | E87: 2 | F87: 5 | G87: 4 | H87: N | I87: N | M87: =IF($B87="","",IFERROR(INDEX(Rubric!$C$14:$C$23,MATCH($B87,Rubric!$A$14:$A$23,0)),INDEX(Rubric!$C$14:$C$23,MATCH("other",Rubric!$A$14:$A$23,0)))) -> 11 | N87: =IF(OR($A87="",$C87=""),"",$C87*Rubric!$B$5+$D87*Rubric!$B$6+$E87*Rubric!$B$7+$F87*Rubric!$B$8+$G87*Rubric!$B$9) -> 3.34 | O87: =IF($A87="","",IF(OR(UPPER($H87)="Y",UPPER($I87)="Y"),"FAIL","PASS")) -> PASS | P87: =IF($N87="","",Assumptions!$B$6*MAX(0.05,($N87/Assumptions!$B$11)^Assumptions!$B$12)) -> 0.011133333 | Q87: =IF($P87="","",1-(1-$P87)^Assumptions!$B$7) -> 0.054440879 | R87: =IF($M87="","",$M87*Assumptions!$B$7) -> 55 | S87: =IF(OR($J87="",$Q87="",$Q87=0),"",($J87+$R87)/($Q87*(1-Assumptions!$B$4))) | T87: =IF(OR($K87="",$S87="",$S87=0),"",$K87/$S87) | U87: =IF(OR($K87="",$Q87=""),"",MAX(0,($K87-MAX($K87*Assumptions!$B$4,Assumptions!$B$5))*$Q87-$R87)) | V87: =IF($A87="","",IF($O87="FAIL","REJECT",IF($J87="","NEEDS PRICE",IF(OR($K87="",$L87=""),"NEEDS VALUATION",IF($T87>=Assumptions!$B$13,"BUY",IF($T87>=1,"MARGINAL","PASS")))))) -> NEEDS PRICE | W87: Taken | X87: [B2/Metaphor] Mooring post. Weak commercial connection.
A88: crosstie.com | B88: =IF($A88="","",IF(ISERROR(FIND(".",$A88)),"",LOWER(MID($A88,FIND(CHAR(1),SUBSTITUTE($A88,".",CHAR(1),LEN($A88)-LEN(SUBSTITUTE($A88,".",""))))+1,LEN($A88))))) -> com | C88: =IF($B88="","",IFERROR(INDEX(Rubric!$B$14:$B$23,MATCH($B88,Rubric!$A$14:$A$23,0)),INDEX(Rubric!$B$14:$B$23,MATCH("other",Rubric!$A$14:$A$23,0)))) -> 5 | D88: 2 | E88: 2 | F88: 4 | G88: 4 | H88: N | I88: N | M88: =IF($B88="","",IFERROR(INDEX(Rubric!$C$14:$C$23,MATCH($B88,Rubric!$A$14:$A$23,0)),INDEX(Rubric!$C$14:$C$23,MATCH("other",Rubric!$A$14:$A$23,0)))) -> 11 | N88: =IF(OR($A88="",$C88=""),"",$C88*Rubric!$B$5+$D88*Rubric!$B$6+$E88*Rubric!$B$7+$F88*Rubric!$B$8+$G88*Rubric!$B$9) -> 3.18 | O88: =IF($A88="","",IF(OR(UPPER($H88)="Y",UPPER($I88)="Y"),"FAIL","PASS")) -> PASS | P88: =IF($N88="","",Assumptions!$B$6*MAX(0.05,($N88/Assumptions!$B$11)^Assumptions!$B$12)) -> 0.0106 | Q88: =IF($P88="","",1-(1-$P88)^Assumptions!$B$7) -> 0.051888247 | R88: =IF($M88="","",$M88*Assumptions!$B$7) -> 55 | S88: =IF(OR($J88="",$Q88="",$Q88=0),"",($J88+$R88)/($Q88*(1-Assumptions!$B$4))) | T88: =IF(OR($K88="",$S88="",$S88=0),"",$K88/$S88) | U88: =IF(OR($K88="",$Q88=""),"",MAX(0,($K88-MAX($K88*Assumptions!$B$4,Assumptions!$B$5))*$Q88-$R88)) | V88: =IF($A88="","",IF($O88="FAIL","REJECT",IF($J88="","NEEDS PRICE",IF(OR($K88="",$L88=""),"NEEDS VALUATION",IF($T88>=Assumptions!$B$13,"BUY",IF($T88>=1,"MARGINAL","PASS")))))) -> NEEDS PRICE | W88: Taken | X88: [B2/Metaphor] Railroad tie. Obscure and hard to spell.
A89: flywheel.com | B89: =IF($A89="","",IF(ISERROR(FIND(".",$A89)),"",LOWER(MID($A89,FIND(CHAR(1),SUBSTITUTE($A89,".",CHAR(1),LEN($A89)-LEN(SUBSTITUTE($A89,".",""))))+1,LEN($A89))))) -> com | C89: =IF($B89="","",IFERROR(INDEX(Rubric!$B$14:$B$23,MATCH($B89,Rubric!$A$14:$A$23,0)),INDEX(Rubric!$B$14:$B$23,MATCH("other",Rubric!$A$14:$A$23,0)))) -> 5 | D89: 3 | E89: 3 | F89: 5 | G89: 5 | H89: Y | I89: N | M89: =IF($B89="","",IFERROR(INDEX(Rubric!$C$14:$C$23,MATCH($B89,Rubric!$A$14:$A$23,0)),INDEX(Rubric!$C$14:$C$23,MATCH("other",Rubric!$A$14:$A$23,0)))) -> 11 | N89: =IF(OR($A89="",$C89=""),"",$C89*Rubric!$B$5+$D89*Rubric!$B$6+$E89*Rubric!$B$7+$F89*Rubric!$B$8+$G89*Rubric!$B$9) -> 3.96 | O89: =IF($A89="","",IF(OR(UPPER($H89)="Y",UPPER($I89)="Y"),"FAIL","PASS")) -> FAIL | P89: =IF($N89="","",Assumptions!$B$6*MAX(0.05,($N89/Assumptions!$B$11)^Assumptions!$B$12)) -> 0.0132 | Q89: =IF($P89="","",1-(1-$P89)^Assumptions!$B$7) -> 0.064280448 | R89: =IF($M89="","",$M89*Assumptions!$B$7) -> 55 | S89: =IF(OR($J89="",$Q89="",$Q89=0),"",($J89+$R89)/($Q89*(1-Assumptions!$B$4))) | T89: =IF(OR($K89="",$S89="",$S89=0),"",$K89/$S89) | U89: =IF(OR($K89="",$Q89=""),"",MAX(0,($K89-MAX($K89*Assumptions!$B$4,Assumptions!$B$5))*$Q89-$R89)) | V89: =IF($A89="","",IF($O89="FAIL","REJECT",IF($J89="","NEEDS PRICE",IF(OR($K89="",$L89=""),"NEEDS VALUATION",IF($T89>=Assumptions!$B$13,"BUY",IF($T89>=1,"MARGINAL","PASS")))))) -> REJECT | W89: Taken | X89: [B2/Metaphor] TM FLAG — Flywheel is an established software brand.
... A95: fundwise.com | B95: =IF($A95="","",IF(ISERROR(FIND(".",$A95)),"",LOWER(MID($A95,FIND(CHAR(1),SUBSTITUTE($A95,".",CHAR(1),LEN($A95)-LEN(SUBSTITUTE($A95,".",""))))+1,LEN($A95))))) -> com | C95: =IF($B95="","",IFERROR(INDEX(Rubric!$B$14:$B$23,MATCH($B95,Rubric!$A$14:$A$23,0)),INDEX(Rubric!$B$14:$B$23,MATCH("other",Rubric!$A$14:$A$23,0)))) -> 5 | D95: 4 | E95: 3 | F95: 5 | G95: 5 | H95: N | I95: N | M95: =IF($B95="","",IFERROR(INDEX(Rubric!$C$14:$C$23,MATCH($B95,Rubric!$A$14:$A$23,0)),INDEX(Rubric!$C$14:$C$23,MATCH("other",Rubric!$A$14:$A$23,0)))) -> 11 | N95: =IF(OR($A95="",$C95=""),"",$C95*Rubric!$B$5+$D95*Rubric!$B$6+$E95*Rubric!$B$7+$F95*Rubric!$B$8+$G95*Rubric!$B$9) -> 4.26 | O95: =IF($A95="","",IF(OR(UPPER($H95)="Y",UPPER($I95)="Y"),"FAIL","PASS")) -> PASS | P95: =IF($N95="","",Assumptions!$B$6*MAX(0.05,($N95/Assumptions!$B$11)^Assumptions!$B$12)) -> 0.0142 | Q95: =IF($P95="","",1-(1-$P95)^Assumptions!$B$7) -> 0.06901203 | R95: =IF($M95="","",$M95*Assumptions!$B$7) -> 55 | S95: =IF(OR($J95="",$Q95="",$Q95=0),"",($J95+$R95)/($Q95*(1-Assumptions!$B$4))) | T95: =IF(OR($K95="",$S95="",$S95=0),"",$K95/$S95) | U95: =IF(OR($K95="",$Q95=""),"",MAX(0,($K95-MAX($K95*Assumptions!$B$4,Assumptions!$B$5))*$Q95-$R95)) | V95: =IF($A95="","",IF($O95="FAIL","REJECT",IF($J95="","NEEDS PRICE",IF(OR($K95="",$L95=""),"NEEDS VALUATION",IF($T95>=Assumptions!$B$13,"BUY",IF($T95>=1,"MARGINAL","PASS")))))) -> NEEDS PRICE | W95: Taken | X95: [B2/Coined] Reads credible and established. Likely taken.
A96: fundpilot.com | B96: =IF($A96="","",IF(ISERROR(FIND(".",$A96)),"",LOWER(MID($A96,FIND(CHAR(1),SUBSTITUTE($A96,".",CHAR(1),LEN($A96)-LEN(SUBSTITUTE($A96,".",""))))+1,LEN($A96))))) -> com | C96: =IF($B96="","",IFERROR(INDEX(Rubric!$B$14:$B$23,MATCH($B96,Rubric!$A$14:$A$23,0)),INDEX(Rubric!$B$14:$B$23,MATCH("other",Rubric!$A$14:$A$23,0)))) -> 5 | D96: 3 | E96: 2 | F96: 4 | G96: 5 | H96: N | I96: N | J96: 14999 | M96: =IF($B96="","",IFERROR(INDEX(Rubric!$C$14:$C$23,MATCH($B96,Rubric!$A$14:$A$23,0)),INDEX(Rubric!$C$14:$C$23,MATCH("other",Rubric!$A$14:$A$23,0)))) -> 11 | N96: =IF(OR($A96="",$C96=""),"",$C96*Rubric!$B$5+$D96*Rubric!$B$6+$E96*Rubric!$B$7+$F96*Rubric!$B$8+$G96*Rubric!$B$9) -> 3.58 | O96: =IF($A96="","",IF(OR(UPPER($H96)="Y",UPPER($I96)="Y"),"FAIL","PASS")) -> PASS | P96: =IF($N96="","",Assumptions!$B$6*MAX(0.05,($N96/Assumptions!$B$11)^Assumptions!$B$12)) -> 0.011933333 | Q96: =IF($P96="","",1-(1-$P96)^Assumptions!$B$7) -> 0.058259515 | R96: =IF($M96="","",$M96*Assumptions!$B$7) -> 55 | S96: =IF(OR($J96="",$Q96="",$Q96=0),"",($J96+$R96)/($Q96*(1-Assumptions!$B$4))) -> 322994.45 | T96: =IF(OR($K96="",$S96="",$S96=0),"",$K96/$S96) | U96: =IF(OR($K96="",$Q96=""),"",MAX(0,($K96-MAX($K96*Assumptions!$B$4,Assumptions!$B$5))*$Q96-$R96)) | V96: =IF($A96="","",IF($O96="FAIL","REJECT",IF($J96="","NEEDS PRICE",IF(OR($K96="",$L96=""),"NEEDS VALUATION",IF($T96>=Assumptions!$B$13,"BUY",IF($T96>=1,"MARGINAL","PASS")))))) -> NEEDS VALUATION | W96: Available - premium | X96: [B2/Coined] -pilot suffix suggests software as much as lending.
A97: creditpilot.com | B97: =IF($A97="","",IF(ISERROR(FIND(".",$A97)),"",LOWER(MID($A97,FIND(CHAR(1),SUBSTITUTE($A97,".",CHAR(1),LEN($A97)-LEN(SUBSTITUTE($A97,".",""))))+1,LEN($A97))))) -> com | C97: =IF($B97="","",IFERROR(INDEX(Rubric!$B$14:$B$23,MATCH($B97,Rubric!$A$14:$A$23,0)),INDEX(Rubric!$B$14:$B$23,MATCH("other",Rubric!$A$14:$A$23,0)))) -> 5 | D97: 3 | E97: 2 | F97: 4 | G97: 5 | H97: N | I97: N | M97: =IF($B97="","",IFERROR(INDEX(Rubric!$C$14:$C$23,MATCH($B97,Rubric!$A$14:$A$23,0)),INDEX(Rubric!$C$14:$C$23,MATCH("other",Rubric!$A$14:$A$23,0)))) -> 11 | N97: =IF(OR($A97="",$C97=""),"",$C97*Rubric!$B$5+$D97*Rubric!$B$6+$E97*Rubric!$B$7+$F97*Rubric!$B$8+$G97*Rubric!$B$9) -> 3.58 | O97: =IF($A97="","",IF(OR(UPPER($H97)="Y",UPPER($I97)="Y"),"FAIL","PASS")) -> PASS | P97: =IF($N97="","",Assumptions!$B$6*MAX(0.05,($N97/Assumptions!$B$11)^Assumptions!$B$12)) -> 0.011933333 | Q97: =IF($P97="","",1-(1-$P97)^Assumptions!$B$7) -> 0.058259515 | R97: =IF($M97="","",$M97*Assumptions!$B$7) -> 55 | S97: =IF(OR($J97="",$Q97="",$Q97=0),"",($J97+$R97)/($Q97*(1-Assumptions!$B$4))) | T97: =IF(OR($K97="",$S97="",$S97=0),"",$K97/$S97) | U97: =IF(OR($K97="",$Q97=""),"",MAX(0,($K97-MAX($K97*Assumptions!$B$4,Assumptions!$B$5))*$Q97-$R97)) | V97: =IF($A97="","",IF($O97="FAIL","REJECT",IF($J97="","NEEDS PRICE",IF(OR($K97="",$L97=""),"NEEDS VALUATION",IF($T97>=Assumptions!$B$13,"BUY",IF($T97>=1,"MARGINAL","PASS")))))) -> NEEDS PRICE | W97: Taken | X97: [B2/Coined] Same.
A98: lendable.com | B98: =IF($A98="","",IF(ISERROR(FIND(".",$A98)),"",LOWER(MID($A98,FIND(CHAR(1),SUBSTITUTE($A98,".",CHAR(1),LEN($A98)-LEN(SUBSTITUTE($A98,".",""))))+1,LEN($A98))))) -> com | C98: =IF($B98="","",IFERROR(INDEX(Rubric!$B$14:$B$23,MATCH($B98,Rubric!$A$14:$A$23,0)),INDEX(Rubric!$B$14:$B$23,MATCH("other",Rubric!$A$14:$A$23,0)))) -> 5 | D98: 4 | E98: 3 | F98: 5 | G98: 5 | H98: Y | I98: N | M98: =IF($B98="","",IFERROR(INDEX(Rubric!$C$14:$C$23,MATCH($B98,Rubric!$A$14:$A$23,0)),INDEX(Rubric!$C$14:$C$23,MATCH("other",Rubric!$A$14:$A$23,0)))) -> 11 | N98: =IF(OR($A98="",$C98=""),"",$C98*Rubric!$B$5+$D98*Rubric!$B$6+$E98*Rubric!$B$7+$F98*Rubric!$B$8+$G98*Rubric!$B$9) -> 4.26 | O98: =IF($A98="","",IF(OR(UPPER($H98)="Y",UPPER($I98)="Y"),"FAIL","PASS")) -> FAIL | P98: =IF($N98="","",Assumptions!$B$6*MAX(0.05,($N98/Assumptions!$B$11)^Assumptions!$B$12)) -> 0.0142 | Q98: =IF($P98="","",1-(1-$P98)^Assumptions!$B$7) -> 0.06901203 | R98: =IF($M98="","",$M98*Assumptions!$B$7) -> 55 | S98: =IF(OR($J98="",$Q98="",$Q98=0),"",($J98+$R98)/($Q98*(1-Assumptions!$B$4))) | T98: =IF(OR($K98="",$S98="",$S98=0),"",$K98/$S98) | U98: =IF(OR($K98="",$Q98=""),"",MAX(0,($K98-MAX($K98*Assumptions!$B$4,Assumptions!$B$5))*$Q98-$R98)) | V98: =IF($A98="","",IF($O98="FAIL","REJECT",IF($J98="","NEEDS PRICE",IF(OR($K98="",$L98=""),"NEEDS VALUATION",IF($T98>=Assumptions!$B$13,"BUY",IF($T98>=1,"MARGINAL","PASS")))))) -> REJECT | W98: Taken | X98: [B2/Coined] TM FLAG — Lendable is an operating lender.
A99: capitalize.com | B99: =IF($A99="","",IF(ISERROR(FIND(".",$A99)),"",LOWER(MID($A99,FIND(CHAR(1),SUBSTITUTE($A99,".",CHAR(1),LEN($A99)-LEN(SUBSTITUTE($A99,".",""))))+1,LEN($A99))))) -> com | C99: =IF($B99="","",IFERROR(INDEX(Rubric!$B$14:$B$23,MATCH($B99,Rubric!$A$14:$A$23,0)),INDEX(Rubric!$B$14:$B$23,MATCH("other",Rubric!$A$14:$A$23,0)))) -> 5 | D99: 4 | E99: 3 | F99: 5 | G99: 5 | H99: Y | I99: N | M99: =IF($B99="","",IFERROR(INDEX(Rubric!$C$14:$C$23,MATCH($B99,Rubric!$A$14:$A$23,0)),INDEX(Rubric!$C$14:$C$23,MATCH("other",Rubric!$A$14:$A$23,0)))) -> 11 | N99: =IF(OR($A99="",$C99=""),"",$C99*Rubric!$B$5+$D99*Rubric!$B$6+$E99*Rubric!$B$7+$F99*Rubric!$B$8+$G99*Rubric!$B$9) -> 4.26 | O99: =IF($A99="","",IF(OR(UPPER($H99)="Y",UPPER($I99)="Y"),"FAIL","PASS")) -> FAIL | P99: =IF($N99="","",Assumptions!$B$6*MAX(0.05,($N99/Assumptions!$B$11)^Assumptions!$B$12)) -> 0.0142 | Q99: =IF($P99="","",1-(1-$P99)^Assumptions!$B$7) -> 0.06901203 | R99: =IF($M99="","",$M99*Assumptions!$B$7) -> 55 | S99: =IF(OR($J99="",$Q99="",$Q99=0),"",($J99+$R99)/($Q99*(1-Assumptions!$B$4))) | T99: =IF(OR($K99="",$S99="",$S99=0),"",$K99/$S99) | U99: =IF(OR($K99="",$Q99=""),"",MAX(0,($K99-MAX($K99*Assumptions!$B$4,Assumptions!$B$5))*$Q99-$R99)) | V99: =IF($A99="","",IF($O99="FAIL","REJECT",IF($J99="","NEEDS PRICE",IF(OR($K99="",$L99=""),"NEEDS VALUATION",IF($T99>=Assumptions!$B$13,"BUY",IF($T99>=1,"MARGINAL","PASS")))))) -> REJECT | W99: Taken | X99: [B2/Coined] TM FLAG — Capitalize is an existing fintech.
A100: decisioning.com | B100: =IF($A100="","",IF(ISERROR(FIND(".",$A100)),"",LOWER(MID($A100,FIND(CHAR(1),SUBSTITUTE($A100,".",CHAR(1),LEN($A100)-LEN(SUBSTITUTE($A100,".",""))))+1,LEN($A100))))) -> com | C100: =IF($B100="","",IFERROR(INDEX(Rubric!$B$14:$B$23,MATCH($B100,Rubric!$A$14:$A$23,0)),INDEX(Rubric!$B$14:$B$23,MATCH("other",Rubric!$A$14:$A$23,0)))) -> 5 | D100: 4 | E100: 3 | F100: 4 | G100: 4 | H100: N | I100: N | M100: =IF($B100="","",IFERROR(INDEX(Rubric!$C$14:$C$23,MATCH($B100,Rubric!$A$14:$A$23,0)),INDEX(Rubric!$C$14:$C$23,MATCH("other",Rubric!$A$14:$A$23,0)))) -> 11 | N100: =IF(OR($A100="",$C100=""),"",$C100*Rubric!$B$5+$D100*Rubric!$B$6+$E100*Rubric!$B$7+$F100*Rubric!$B$8+$G100*Rubric!$B$9) -> 4 | O100: =IF($A100="","",IF(OR(UPPER($H100)="Y",UPPER($I100)="Y"),"FAIL","PASS")) -> PASS | P100: =IF($N100="","",Assumptions!$B$6*MAX(0.05,($N100/Assumptions!$B$11)^Assumptions!$B$12)) -> 0.013333333 | Q100: =IF($P100="","",1-(1-$P100)^Assumptions!$B$7) -> 0.064912435 | R100: =IF($M100="","",$M100*Assumptions!$B$7) -> 55 | S100: =IF(OR($J100="",$Q100="",$Q100=0),"",($J100+$R100)/($Q100*(1-Assumptions!$B$4))) | T100: =IF(OR($K100="",$S100="",$S100=0),"",$K100/$S100) | U100: =IF(OR($K100="",$Q100=""),"",MAX(0,($K100-MAX($K100*Assumptions!$B$4,Assumptions!$B$5))*$Q100-$R100)) | V100: =IF($A100="","",IF($O100="FAIL","REJECT",IF($J100="","NEEDS PRICE",IF(OR($K100="",$L100=""),"NEEDS VALUATION",IF($T100>=Assumptions!$B$13,"BUY",IF($T100>=1,"MARGINAL","PASS")))))) -> NEEDS PRICE | W100: Taken | X100: [B2/Fintech] Credit decisioning is the standard term for the software category.
A101: originate.com | B101: =IF($A101="","",IF(ISERROR(FIND(".",$A101)),"",LOWER(MID($A101,FIND(CHAR(1),SUBSTITUTE($A101,".",CHAR(1),LEN($A101)-LEN(SUBSTITUTE($A101,".",""))))+1,LEN($A101))))) -> com | C101: =IF($B101="","",IFERROR(INDEX(Rubric!$B$14:$B$23,MATCH($B101,Rubric!$A$14:$A$23,0)),INDEX(Rubric!$B$14:$B$23,MATCH("other",Rubric!$A$14:$A$23,0)))) -> 5 | D101: 4 | E101: 3 | F101: 5 | G101: 5 | H101: N | I101: N | M101: =IF($B101="","",IFERROR(INDEX(Rubric!$C$14:$C$23,MATCH($B101,Rubric!$A$14:$A$23,0)),INDEX(Rubric!$C$14:$C$23,MATCH("other",Rubric!$A$14:$A$23,0)))) -> 11 | N101: =IF(OR($A101="",$C101=""),"",$C101*Rubric!$B$5+$D101*Rubric!$B$6+$E101*Rubric!$B$7+$F101*Rubric!$B$8+$G101*Rubric!$B$9) -> 4.26 | O101: =IF($A101="","",IF(OR(UPPER($H101)="Y",UPPER($I101)="Y"),"FAIL","PASS")) -> PASS | P101: =IF($N101="","",Assumptions!$B$6*MAX(0.05,($N101/Assumptions!$B$11)^Assumptions!$B$12)) -> 0.0142 | Q101: =IF($P101="","",1-(1-$P101)^Assumptions!$B$7) -> 0.06901203 | R101: =IF($M101="","",$M101*Assumptions!$B$7) -> 55 | S101: =IF(OR($J101="",$Q101="",$Q101=0),"",($J101+$R101)/($Q101*(1-Assumptions!$B$4))) | T101: =IF(OR($K101="",$S101="",$S101=0),"",$K101/$S101) | U101: =IF(OR($K101="",$Q101=""),"",MAX(0,($K101-MAX($K101*Assumptions!$B$4,Assumptions!$B$5))*$Q101-$R101)) | V101: =IF($A101="","",IF($O101="FAIL","REJECT",IF($J101="","NEEDS PRICE",IF(OR($K101="",$L101=""),"NEEDS VALUATION",IF($T101>=Assumptions!$B$13,"BUY",IF($T101>=1,"MARGINAL","PASS")))))) -> NEEDS PRICE | W101: Taken | X101: [B2/Fintech] Single verb at the centre of lending. Expect taken.
A102: servicing.com | B102: =IF($A102="","",IF(ISERROR(FIND(".",$A102)),"",LOWER(MID($A102,FIND(CHAR(1),SUBSTITUTE($A102,".",CHAR(1),LEN($A102)-LEN(SUBSTITUTE($A102,".",""))))+1,LEN($A102))))) -> com | C102: =IF($B102="","",IFERROR(INDEX(Rubric!$B$14:$B$23,MATCH($B102,Rubric!$A$14:$A$23,0)),INDEX(Rubric!$B$14:$B$23,MATCH("other",Rubric!$A$14:$A$23,0)))) -> 5 | D102: 4 | E102: 3 | F102: 5 | G102: 5 | H102: N | I102: N | J102: 287500 | M102: =IF($B102="","",IFERROR(INDEX(Rubric!$C$14:$C$23,MATCH($B102,Rubric!$A$14:$A$23,0)),INDEX(Rubric!$C$14:$C$23,MATCH("other",Rubric!$A$14:$A$23,0)))) -> 11 | N102: =IF(OR($A102="",$C102=""),"",$C102*Rubric!$B$5+$D102*Rubric!$B$6+$E102*Rubric!$B$7+$F102*Rubric!$B$8+$G102*Rubric!$B$9) -> 4.26 | O102: =IF($A102="","",IF(OR(UPPER($H102)="Y",UPPER($I102)="Y"),"FAIL","PASS")) -> PASS | P102: =IF($N102="","",Assumptions!$B$6*MAX(0.05,($N102/Assumptions!$B$11)^Assumptions!$B$12)) -> 0.0142 | Q102: =IF($P102="","",1-(1-$P102)^Assumptions!$B$7) -> 0.06901203 | R102: =IF($M102="","",$M102*Assumptions!$B$7) -> 55 | S102: =IF(OR($J102="",$Q102="",$Q102=0),"",($J102+$R102)/($Q102*(1-Assumptions!$B$4))) -> 5208421.6 | T102: =IF(OR($K102="",$S102="",$S102=0),"",$K102/$S102) | U102: =IF(OR($K102="",$Q102=""),"",MAX(0,($K102-MAX($K102*Assumptions!$B$4,Assumptions!$B$5))*$Q102-$R102)) | V102: =IF($A102="","",IF($O102="FAIL","REJECT",IF($J102="","NEEDS PRICE",IF(OR($K102="",$L102=""),"NEEDS VALUATION",IF($T102>=Assumptions!$B$13,"BUY",IF($T102>=1,"MARGINAL","PASS")))))) -> NEEDS VALUATION | W102: Available - premium | X102: [B2/Fintech] Loan servicing — huge industry. Expect taken.
A103: adjudicate.com | B103: =IF($A103="","",IF(ISERROR(FIND(".",$A103)),"",LOWER(MID($A103,FIND(CHAR(1),SUBSTITUTE($A103,".",CHAR(1),LEN($A103)-LEN(SUBSTITUTE($A103,".",""))))+1,LEN($A103))))) -> com | C103: =IF($B103="","",IFERROR(INDEX(Rubric!$B$14:$B$23,MATCH($B103,Rubric!$A$14:$A$23,0)),INDEX(Rubric!$B$14:$B$23,MATCH("other",Rubric!$A$14:$A$23,0)))) -> 5 | D103: 3 | E103: 3 | F103: 4 | G103: 4 | H103: N | I103: N | M103: =IF($B103="","",IFERROR(INDEX(Rubric!$C$14:$C$23,MATCH($B103,Rubric!$A$14:$A$23,0)),INDEX(Rubric!$C$14:$C$23,MATCH("other",Rubric!$A$14:$A$23,0)))) -> 11 | N103: =IF(OR($A103="",$C103=""),"",$C103*Rubric!$B$5+$D103*Rubric!$B$6+$E103*Rubric!$B$7+$F103*Rubric!$B$8+$G103*Rubric!$B$9) -> 3.7 | O103: =IF($A103="","",IF(OR(UPPER($H103)="Y",UPPER($I103)="Y"),"FAIL","PASS")) -> PASS | P103: =IF($N103="","",Assumptions!$B$6*MAX(0.05,($N103/Assumptions!$B$11)^Assumptions!$B$12)) -> 0.012333333 | Q103: =IF($P103="","",1-(1-$P103)^Assumptions!$B$7) -> 0.060164201 | R103: =IF($M103="","",$M103*Assumptions!$B$7) -> 55 | S103: =IF(OR($J103="",$Q103="",$Q103=0),"",($J103+$R103)/($Q103*(1-Assumptions!$B$4))) | T103: =IF(OR($K103="",$S103="",$S103=0),"",$K103/$S103) | U103: =IF(OR($K103="",$Q103=""),"",MAX(0,($K103-MAX($K103*Assumptions!$B$4,Assumptions!$B$5))*$Q103-$R103)) | V103: =IF($A103="","",IF($O103="FAIL","REJECT",IF($J103="","NEEDS PRICE",IF(OR($K103="",$L103=""),"NEEDS VALUATION",IF($T103>=Assumptions!$B$13,"BUY",IF($T103>=1,"MARGINAL","PASS")))))) -> NEEDS PRICE | W103: Taken | X103: [B2/Fintech] Credit adjudication. Also legal — broader buyer pool.
A104: creditflow.com | B104: =IF($A104="","",IF(ISERROR(FIND(".",$A104)),"",LOWER(MID($A104,FIND(CHAR(1),SUBSTITUTE($A104,".",CHAR(1),LEN($A104)-LEN(SUBSTITUTE($A104,".",""))))+1,LEN($A104))))) -> com | C104: =IF($B104="","",IFERROR(INDEX(Rubric!$B$14:$B$23,MATCH($B104,Rubric!$A$14:$A$23,0)),INDEX(Rubric!$B$14:$B$23,MATCH("other",Rubric!$A$14:$A$23,0)))) -> 5 | D104: 4 | E104: 3 | F104: 5 | G104: 5 | H104: N | I104: N | M104: =IF($B104="","",IFERROR(INDEX(Rubric!$C$14:$C$23,MATCH($B104,Rubric!$A$14:$A$23,0)),INDEX(Rubric!$C$14:$C$23,MATCH("other",Rubric!$A$14:$A$23,0)))) -> 11 | N104: =IF(OR($A104="",$C104=""),"",$C104*Rubric!$B$5+$D104*Rubric!$B$6+$E104*Rubric!$B$7+$F104*Rubric!$B$8+$G104*Rubric!$B$9) -> 4.26 | O104: =IF($A104="","",IF(OR(UPPER($H104)="Y",UPPER($I104)="Y"),"FAIL","PASS")) -> PASS | P104: =IF($N104="","",Assumptions!$B$6*MAX(0.05,($N104/Assumptions!$B$11)^Assumptions!$B$12)) -> 0.0142 | Q104: =IF($P104="","",1-(1-$P104)^Assumptions!$B$7) -> 0.06901203 | R104: =IF($M104="","",$M104*Assumptions!$B$7) -> 55 | S104: =IF(OR($J104="",$Q104="",$Q104=0),"",($J104+$R104)/($Q104*(1-Assumptions!$B$4))) | T104: =IF(OR($K104="",$S104="",$S104=0),"",$K104/$S104) | U104: =IF(OR($K104="",$Q104=""),"",MAX(0,($K104-MAX($K104*Assumptions!$B$4,Assumptions!$B$5))*$Q104-$R104)) | V104: =IF($A104="","",IF($O104="FAIL","REJECT",IF($J104="","NEEDS PRICE",IF(OR($K104="",$L104=""),"NEEDS VALUATION",IF($T104>=Assumptions!$B$13,"BUY",IF($T104>=1,"MARGINAL","PASS")))))) -> NEEDS PRICE | W104: Taken | X104: [B2/Fintech] Clean, software-flavoured, says what it does.
A105: loanstack.com | B105: =IF($A105="","",IF(ISERROR(FIND(".",$A105)),"",LOWER(MID($A105,FIND(CHAR(1),SUBSTITUTE($A105,".",CHAR(1),LEN($A105)-LEN(SUBSTITUTE($A105,".",""))))+1,LEN($A105))))) -> com | C105: =IF($B105="","",IFERROR(INDEX(Rubric!$B$14:$B$23,MATCH($B105,Rubric!$A$14:$A$23,0)),INDEX(Rubric!$B$14:$B$23,MATCH("other",Rubric!$A$14:$A$23,0)))) -> 5 | D105: 4 | E105: 3 | F105: 5 | G105: 5 | H105: N | I105: N | M105: =IF($B105="","",IFERROR(INDEX(Rubric!$C$14:$C$23,MATCH($B105,Rubric!$A$14:$A$23,0)),INDEX(Rubric!$C$14:$C$23,MATCH("other",Rubric!$A$14:$A$23,0)))) -> 11 | N105: =IF(OR($A105="",$C105=""),"",$C105*Rubric!$B$5+$D105*Rubric!$B$6+$E105*Rubric!$B$7+$F105*Rubric!$B$8+$G105*Rubric!$B$9) -> 4.26 | O105: =IF($A105="","",IF(OR(UPPER($H105)="Y",UPPER($I105)="Y"),"FAIL","PASS")) -> PASS | P105: =IF($N105="","",Assumptions!$B$6*MAX(0.05,($N105/Assumptions!$B$11)^Assumptions!$B$12)) -> 0.0142 | Q105: =IF($P105="","",1-(1-$P105)^Assumptions!$B$7) -> 0.06901203 | R105: =IF($M105="","",$M105*Assumptions!$B$7) -> 55 | S105: =IF(OR($J105="",$Q105="",$Q105=0),"",($J105+$R105)/($Q105*(1-Assumptions!$B$4))) | T105: =IF(OR($K105="",$S105="",$S105=0),"",$K105/$S105) | U105: =IF(OR($K105="",$Q105=""),"",MAX(0,($K105-MAX($K105*Assumptions!$B$4,Assumptions!$B$5))*$Q105-$R105)) | V105: =IF($A105="","",IF($O105="FAIL","REJECT",IF($J105="","NEEDS PRICE",IF(OR($K105="",$L105=""),"NEEDS VALUATION",IF($T105>=Assumptions!$B$13,"BUY",IF($T105>=1,"MARGINAL","PASS")))))) -> NEEDS PRICE | W105: Taken | X105: [B2/Fintech] 'Stack' reads modern and technical.
A106: riskdesk.com | B106: =IF($A106="","",IF(ISERROR(FIND(".",$A106)),"",LOWER(MID($A106,FIND(CHAR(1),SUBSTITUTE($A106,".",CHAR(1),LEN($A106)-LEN(SUBSTITUTE($A106,".",""))))+1,LEN($A106))))) -> com | C106: =IF($B106="","",IFERROR(INDEX(Rubric!$B$14:$B$23,MATCH($B106,Rubric!$A$14:$A$23,0)),INDEX(Rubric!$B$14:$B$23,MATCH("other",Rubric!$A$14:$A$23,0)))) -> 5 | D106: 3 | E106: 2 | F106: 5 | G106: 5 | H106: N | I106: N | M106: =IF($B106="","",IFERROR(INDEX(Rubric!$C$14:$C$23,MATCH($B106,Rubric!$A$14:$A$23,0)),INDEX(Rubric!$C$14:$C$23,MATCH("other",Rubric!$A$14:$A$23,0)))) -> 11 | N106: =IF(OR($A106="",$C106=""),"",$C106*Rubric!$B$5+$D106*Rubric!$B$6+$E106*Rubric!$B$7+$F106*Rubric!$B$8+$G106*Rubric!$B$9) -> 3.74 | O106: =IF($A106="","",IF(OR(UPPER($H106)="Y",UPPER($I106)="Y"),"FAIL","PASS")) -> PASS | P106: =IF($N106="","",Assumptions!$B$6*MAX(0.05,($N106/Assumptions!$B$11)^Assumptions!$B$12)) -> 0.012466667 | Q106: =IF($P106="","",1-(1-$P106)^Assumptions!$B$7) -> 0.06079841 | R106: =IF($M106="","",$M106*Assumptions!$B$7) -> 55 | S106: =IF(OR($J106="",$Q106="",$Q106=0),"",($J106+$R106)/($Q106*(1-Assumptions!$B$4))) | T106: =IF(OR($K106="",$S106="",$S106=0),"",$K106/$S106) | U106: =IF(OR($K106="",$Q106=""),"",MAX(0,($K106-MAX($K106*Assumptions!$B$4,Assumptions!$B$5))*$Q106-$R106)) | V106: =IF($A106="","",IF($O106="FAIL","REJECT",IF($J106="","NEEDS PRICE",IF(OR($K106="",$L106=""),"NEEDS VALUATION",IF($T106>=Assumptions!$B$13,"BUY",IF($T106>=1,"MARGINAL","PASS")))))) -> NEEDS PRICE | W106: Taken | X106: [B2/Fintech] Desk pattern applied to risk rather than funding.
...

Sheet Closeout Screener
A1: Closeout Screener — expired names at $5-$11
A2: A closeout runs 5 days as a reverse auction: $11 on day 1, falling $1/day to $5, plus the renewal. Strong names get taken on day 1 — the Bid Guidance column tells you whether to grab it now or wait for the floor. Blue cells are yours; everything else is a formula.
A4: SCORING WEIGHTS — edit the blue cells; each block must total 100%
A5: NAME QUALITY
A6: Extension | B6: 0.25
A7: Commercial intent | B7: 0.4
A8: Length & memorability | B8: 0.2
A9: Radio test | B9: 0.15
A10: Total | B10: =SUM(B6:B9) -> 1 | C10: =IF(ABS(B10-1)<0.0001,"OK","ERROR - must total 100%") -> OK
A12: ASSET QUALITY
A13: Domain age | B13: 0.25
A14: Backlink quality | B14: 0.35
A15: Prior use | B15: 0.25
A16: Traffic | B16: 0.15
A17: Total | B17: =SUM(B13:B16) -> 1 | C17: =IF(ABS(B17-1)<0.0001,"OK","ERROR - must total 100%") -> OK
A19: Blend: weight on NAME quality | B19: 0.6 | C19: Asset quality takes the remainder. Raise this if you are reselling on the name alone; lower it if you are buying for SEO value.
A21: ASSET CRITERIA — what the scores mean
A22: Domain age | B22: Scored automatically from the Age (yrs) column: under 2 = 1, 2-4 = 2, 5-9 = 3, 10-14 = 4, 15+ = 5. Age is the single hardest thing to fake.
A23: Backlink quality | B23: 1 = none, or obvious spam/PBN links. 3 = a handful of ordinary links. 5 = genuine editorial links from real sites. Check in any backlink tool before bidding — this is where the resale value hides.
A24: Prior use | B24: 1 = parked, spam, or a link farm. 3 = a thin or abandoned site. 5 = a real business with a clean archive. Check the Wayback Machine.
A25: Traffic | B25: 1 = none measurable. 3 = modest residual type-in traffic. 5 = meaningful ongoing traffic. Leave at 1 if you cannot measure it — do not guess upward.
A27: HARD FILTERS — any one rejects the name at any price
A28: REJECT if: | B28: Spam or penalty history — the domain was used for spam, or shows signs of a manual penalty. You inherit the reputation along with the name.
A29: REJECT if: | B29: Adult or gambling history — poisons the buyer pool for a commercial resale even when the name itself is clean.
A30: REJECT if: | B30: Trademark risk — contains or mimics an existing brand.
A31: REJECT if: | B31: Contains a hyphen or a digit.
A34: PIPELINE SUMMARY
A35: Names screened | B35: =COUNTIF($A$44:$A$163,"<>") -> 1
A36: BUY — take on day 1 | B36: =COUNTIF($AF$44:$AF$163,"BUY") -> 0
A37: BUY CHEAPER / FLOOR ONLY | B37: =COUNTIF($AF$44:$AF$163,"BUY CHEAPER")+COUNTIF($AF$44:$AF$163,"FLOOR ONLY") -> 0
A38: REJECT / OVERPRICED / SKIP | B38: =COUNTIF($AF$44:$AF$163,"REJECT")+COUNTIF($AF$44:$AF$163,"OVERPRICED")+COUNTIF($AF$44:$AF$163,"SKIP") -> 1
A39: Needs valuation or price | B39: =COUNTIF($AF$44:$AF$163,"NEEDS VALUATION")+COUNTIF($AF$44:$AF$163,"NEEDS PRICE") -> 0
A40: Total all-in cost of BUY names | B40: =SUMIF($AF$44:$AF$163,"BUY",$F$44:$F$163) -> 0
A41: Total EV headroom of BUY names | B41: =SUMIF($AF$44:$AF$163,"BUY",$AE$44:$AE$163) -> 0
A43: Domain (full, e.g. name.com) | B43: Ext | C43: Ext Score | D43: Closeout Price | E43: Renewal | F43: All-in Cost | G43: Commercial Intent (1-5) | H43: Length & Memorability (1-5) | I43: Radio Test (1-5) | J43: Age (yrs) | K43: Age Score | L43: Backlink Quality (1-5) | M43: Prior Use (1-5) | N43: Traffic (1-5) | O43: Spam/Penalty? (Y/N) | P43: Adult/Gambling? (Y/N) | Q43: TM Risk? (Y/N) | R43: Hyphen/Digit? (Y/N) | S43: Hard Filter | T43: Name Score | U43: Asset Score | V43: Combined Score | W43: Est. Resale Value | X43: Valuation Source | Y43: Net After Commission | Z43: Effective STR /yr | AA43: P(sale) | AB43: BREAK-EVEN RESALE | AC43: Value Ratio | AD43: Max Rational Bid | AE43: Margin vs Cost | AF43: Verdict | AG43: Bid Guidance | AH43: Notes
A44: fleetlogistics.com | B44: =IF($A44="","",IF(ISERROR(FIND(".",$A44)),"",LOWER(MID($A44,FIND(CHAR(1),SUBSTITUTE($A44,".",CHAR(1),LEN($A44)-LEN(SUBSTITUTE($A44,".",""))))+1,LEN($A44))))) -> com | C44: =IF($B44="","",IFERROR(INDEX(Rubric!$B$14:$B$23,MATCH($B44,Rubric!$A$14:$A$23,0)),INDEX(Rubric!$B$14:$B$23,MATCH("other",Rubric!$A$14:$A$23,0)))) -> 5 | D44: 11 | E44: =IF($B44="","",IFERROR(INDEX(Rubric!$C$14:$C$23,MATCH($B44,Rubric!$A$14:$A$23,0)),INDEX(Rubric!$C$14:$C$23,MATCH("other",Rubric!$A$14:$A$23,0)))) -> 11 | F44: =IF(OR($A44="",$D44=""),"",$D44+$E44) -> 22 | G44: 4 | H44: 4 | I44: 5 | J44: 12 | K44: =IF($J44="","",IF($J44>=15,5,IF($J44>=10,4,IF($J44>=5,3,IF($J44>=2,2,1))))) -> 4 | L44: 4 | M44: 4 | N44: 2 | O44: N | P44: N | Q44: N | R44: N | S44: =IF($A44="","",IF(OR(UPPER($O44)="Y",UPPER($P44)="Y",UPPER($Q44)="Y",UPPER($R44)="Y"),"FAIL","PASS")) -> PASS | T44: =IF(OR($A44="",$C44=""),"",$C44*$B$6+$G44*$B$7+$H44*$B$8+$I44*$B$9) -> 4.4 | U44: =IF(OR($A44="",$K44=""),"",$K44*$B$13+$L44*$B$14+$M44*$B$15+$N44*$B$16) -> 3.7 | V44: =IF(OR($T44="",$U44=""),"",$T44*$B$19+$U44*(1-$B$19)) -> 4.12 | W44: 1200 | X44: HumbleWorth brokerage 2026-08-03 | Y44: =IF(OR($A44="",$W44=""),"",MAX(0,$W44-MAX($W44*Assumptions!$B$4,Assumptions!$B$5))) -> 960 | Z44: =IF($V44="","",Assumptions!$B$6*MAX(0.05,($V44/Assumptions!$B$11)^Assumptions!$B$12)) -> 0.013733333 | AA44: =IF($Z44="","",1-(1-$Z44)^Assumptions!$B$7) -> 0.066806347 | AB44: =IF(OR($F44="",$AA44="",$AA44=0),"",($F44+$E44*Assumptions!$B$7)/($AA44*(1-Assumptions!$B$4))) -> 1440.7314 | AC44: =IF(OR($W44="",$AB44="",$AB44=0),"",$W44/$AB44) -> 0.83291029 | AD44: =IF(OR($Y44="",$E44="",$AA44=""),"",MAX(0,$Y44*$AA44-$E44*Assumptions!$B$7)) -> 9.1340927 | AE44: =IF(OR($AD44="",$F44=""),"",$AD44-$F44) -> -12.865907 | AF44: =IF($A44="","",IF($S44="FAIL","REJECT",IF($D44="","NEEDS PRICE",IF(OR($W44="",$X44=""),"NEEDS VALUATION",IF($AC44<1,"OVERPRICED",IF(AND($AC44>=Assumptions!$B$13,$V44>=4),"BUY",IF($V44>=3.4,"BUY CHEAPER",IF($V44>=2.8,"FLOOR ONLY","SKIP")))))))) -> OVERPRICED | AG44: =IF($AF44="","",IF($AF44="REJECT","Do not buy at any price",IF($AF44="NEEDS PRICE","Enter the current closeout price",IF($AF44="NEEDS VALUATION","Enter a valuation AND its source before bidding",IF($AF44="OVERPRICED","Worth less than break-even - walk",IF($AF44="BUY","Take it on day 1 at $11 - will not reach the floor",IF($AF44="BUY CHEAPER","Wait to about $8 (day 3), walk if outbid",IF($AF44="FLOOR ONLY","Only at the $5 floor","Skip")))))))) -> Worth less than break-even - walk
B45: =IF($A45="","",IF(ISERROR(FIND(".",$A45)),"",LOWER(MID($A45,FIND(CHAR(1),SUBSTITUTE($A45,".",CHAR(1),LEN($A45)-LEN(SUBSTITUTE($A45,".",""))))+1,LEN($A45))))) | C45: =IF($B45="","",IFERROR(INDEX(Rubric!$B$14:$B$23,MATCH($B45,Rubric!$A$14:$A$23,0)),INDEX(Rubric!$B$14:$B$23,MATCH("other",Rubric!$A$14:$A$23,0)))) | E45: =IF($B45="","",IFERROR(INDEX(Rubric!$C$14:$C$23,MATCH($B45,Rubric!$A$14:$A$23,0)),INDEX(Rubric!$C$14:$C$23,MATCH("other",Rubric!$A$14:$A$23,0)))) | F45: =IF(OR($A45="",$D45=""),"",$D45+$E45) | K45: =IF($J45="","",IF($J45>=15,5,IF($J45>=10,4,IF($J45>=5,3,IF($J45>=2,2,1))))) | S45: =IF($A45="","",IF(OR(UPPER($O45)="Y",UPPER($P45)="Y",UPPER($Q45)="Y",UPPER($R45)="Y"),"FAIL","PASS")) | T45: =IF(OR($A45="",$C45=""),"",$C45*$B$6+$G45*$B$7+$H45*$B$8+$I45*$B$9) | U45: =IF(OR($A45="",$K45=""),"",$K45*$B$13+$L45*$B$14+$M45*$B$15+$N45*$B$16) | V45: =IF(OR($T45="",$U45=""),"",$T45*$B$19+$U45*(1-$B$19)) | Y45: =IF(OR($A45="",$W45=""),"",MAX(0,$W45-MAX($W45*Assumptions!$B$4,Assumptions!$B$5))) | Z45: =IF($V45="","",Assumptions!$B$6*MAX(0.05,($V45/Assumptions!$B$11)^Assumptions!$B$12)) | AA45: =IF($Z45="","",1-(1-$Z45)^Assumptions!$B$7) | AB45: =IF(OR($F45="",$AA45="",$AA45=0),"",($F45+$E45*Assumptions!$B$7)/($AA45*(1-Assumptions!$B$4))) | AC45: =IF(OR($W45="",$AB45="",$AB45=0),"",$W45/$AB45) | AD45: =IF(OR($Y45="",$E45="",$AA45=""),"",MAX(0,$Y45*$AA45-$E45*Assumptions!$B$7)) | AE45: =IF(OR($AD45="",$F45=""),"",$AD45-$F45) | AF45: =IF($A45="","",IF($S45="FAIL","REJECT",IF($D45="","NEEDS PRICE",IF(OR($W45="",$X45=""),"NEEDS VALUATION",IF($AC45<1,"OVERPRICED",IF(AND($AC45>=Assumptions!$B$13,$V45>=4),"BUY",IF($V45>=3.4,"BUY CHEAPER",IF($V45>=2.8,"FLOOR ONLY","SKIP")))))))) | AG45: =IF($AF45="","",IF($AF45="REJECT","Do not buy at any price",IF($AF45="NEEDS PRICE","Enter the current closeout price",IF($AF45="NEEDS VALUATION","Enter a valuation AND its source before bidding",IF($AF45="OVERPRICED","Worth less than break-even - walk",IF($AF45="BUY","Take it on day 1 at $11 - will not reach the floor",IF($AF45="BUY CHEAPER","Wait to about $8 (day 3), walk if outbid",IF($AF45="FLOOR ONLY","Only at the $5 floor","Skip"))))))))
B46: =IF($A46="","",IF(ISERROR(FIND(".",$A46)),"",LOWER(MID($A46,FIND(CHAR(1),SUBSTITUTE($A46,".",CHAR(1),LEN($A46)-LEN(SUBSTITUTE($A46,".",""))))+1,LEN($A46))))) | C46: =IF($B46="","",IFERROR(INDEX(Rubric!$B$14:$B$23,MATCH($B46,Rubric!$A$14:$A$23,0)),INDEX(Rubric!$B$14:$B$23,MATCH("other",Rubric!$A$14:$A$23,0)))) | E46: =IF($B46="","",IFERROR(INDEX(Rubric!$C$14:$C$23,MATCH($B46,Rubric!$A$14:$A$23,0)),INDEX(Rubric!$C$14:$C$23,MATCH("other",Rubric!$A$14:$A$23,0)))) | F46: =IF(OR($A46="",$D46=""),"",$D46+$E46) | K46: =IF($J46="","",IF($J46>=15,5,IF($J46>=10,4,IF($J46>=5,3,IF($J46>=2,2,1))))) | S46: =IF($A46="","",IF(OR(UPPER($O46)="Y",UPPER($P46)="Y",UPPER($Q46)="Y",UPPER($R46)="Y"),"FAIL","PASS")) | T46: =IF(OR($A46="",$C46=""),"",$C46*$B$6+$G46*$B$7+$H46*$B$8+$I46*$B$9) | U46: =IF(OR($A46="",$K46=""),"",$K46*$B$13+$L46*$B$14+$M46*$B$15+$N46*$B$16) | V46: =IF(OR($T46="",$U46=""),"",$T46*$B$19+$U46*(1-$B$19)) | Y46: =IF(OR($A46="",$W46=""),"",MAX(0,$W46-MAX($W46*Assumptions!$B$4,Assumptions!$B$5))) | Z46: =IF($V46="","",Assumptions!$B$6*MAX(0.05,($V46/Assumptions!$B$11)^Assumptions!$B$12)) | AA46: =IF($Z46="","",1-(1-$Z46)^Assumptions!$B$7) | AB46: =IF(OR($F46="",$AA46="",$AA46=0),"",($F46+$E46*Assumptions!$B$7)/($AA46*(1-Assumptions!$B$4))) | AC46: =IF(OR($W46="",$AB46="",$AB46=0),"",$W46/$AB46) | AD46: =IF(OR($Y46="",$E46="",$AA46=""),"",MAX(0,$Y46*$AA46-$E46*Assumptions!$B$7)) | AE46: =IF(OR($AD46="",$F46=""),"",$AD46-$F46) | AF46: =IF($A46="","",IF($S46="FAIL","REJECT",IF($D46="","NEEDS PRICE",IF(OR($W46="",$X46=""),"NEEDS VALUATION",IF($AC46<1,"OVERPRICED",IF(AND($AC46>=Assumptions!$B$13,$V46>=4),"BUY",IF($V46>=3.4,"BUY CHEAPER",IF($V46>=2.8,"FLOOR ONLY","SKIP")))))))) | AG46: =IF($AF46="","",IF($AF46="REJECT","Do not buy at any price",IF($AF46="NEEDS PRICE","Enter the current closeout price",IF($AF46="NEEDS VALUATION","Enter a valuation AND its source before bidding",IF($AF46="OVERPRICED","Worth less than break-even - walk",IF($AF46="BUY","Take it on day 1 at $11 - will not reach the floor",IF($AF46="BUY CHEAPER","Wait to about $8 (day 3), walk if outbid",IF($AF46="FLOOR ONLY","Only at the $5 floor","Skip"))))))))
B47: =IF($A47="","",IF(ISERROR(FIND(".",$A47)),"",LOWER(MID($A47,FIND(CHAR(1),SUBSTITUTE($A47,".",CHAR(1),LEN($A47)-LEN(SUBSTITUTE($A47,".",""))))+1,LEN($A47))))) | C47: =IF($B47="","",IFERROR(INDEX(Rubric!$B$14:$B$23,MATCH($B47,Rubric!$A$14:$A$23,0)),INDEX(Rubric!$B$14:$B$23,MATCH("other",Rubric!$A$14:$A$23,0)))) | E47: =IF($B47="","",IFERROR(INDEX(Rubric!$C$14:$C$23,MATCH($B47,Rubric!$A$14:$A$23,0)),INDEX(Rubric!$C$14:$C$23,MATCH("other",Rubric!$A$14:$A$23,0)))) | F47: =IF(OR($A47="",$D47=""),"",$D47+$E47) | K47: =IF($J47="","",IF($J47>=15,5,IF($J47>=10,4,IF($J47>=5,3,IF($J47>=2,2,1))))) | S47: =IF($A47="","",IF(OR(UPPER($O47)="Y",UPPER($P47)="Y",UPPER($Q47)="Y",UPPER($R47)="Y"),"FAIL","PASS")) | T47: =IF(OR($A47="",$C47=""),"",$C47*$B$6+$G47*$B$7+$H47*$B$8+$I47*$B$9) | U47: =IF(OR($A47="",$K47=""),"",$K47*$B$13+$L47*$B$14+$M47*$B$15+$N47*$B$16) | V47: =IF(OR($T47="",$U47=""),"",$T47*$B$19+$U47*(1-$B$19)) | Y47: =IF(OR($A47="",$W47=""),"",MAX(0,$W47-MAX($W47*Assumptions!$B$4,Assumptions!$B$5))) | Z47: =IF($V47="","",Assumptions!$B$6*MAX(0.05,($V47/Assumptions!$B$11)^Assumptions!$B$12)) | AA47: =IF($Z47="","",1-(1-$Z47)^Assumptions!$B$7) | AB47: =IF(OR($F47="",$AA47="",$AA47=0),"",($F47+$E47*Assumptions!$B$7)/($AA47*(1-Assumptions!$B$4))) | AC47: =IF(OR($W47="",$AB47="",$AB47=0),"",$W47/$AB47) | AD47: =IF(OR($Y47="",$E47="",$AA47=""),"",MAX(0,$Y47*$AA47-$E47*Assumptions!$B$7)) | AE47: =IF(OR($AD47="",$F47=""),"",$AD47-$F47) | AF47: =IF($A47="","",IF($S47="FAIL","REJECT",IF($D47="","NEEDS PRICE",IF(OR($W47="",$X47=""),"NEEDS VALUATION",IF($AC47<1,"OVERPRICED",IF(AND($AC47>=Assumptions!$B$13,$V47>=4),"BUY",IF($V47>=3.4,"BUY CHEAPER",IF($V47>=2.8,"FLOOR ONLY","SKIP")))))))) | AG47: =IF($AF47="","",IF($AF47="REJECT","Do not buy at any price",IF($AF47="NEEDS PRICE","Enter the current closeout price",IF($AF47="NEEDS VALUATION","Enter a valuation AND its source before bidding",IF($AF47="OVERPRICED","Worth less than break-even - walk",IF($AF47="BUY","Take it on day 1 at $11 - will not reach the floor",IF($AF47="BUY CHEAPER","Wait to about $8 (day 3), walk if outbid",IF($AF47="FLOOR ONLY","Only at the $5 floor","Skip"))))))))
B48: =IF($A48="","",IF(ISERROR(FIND(".",$A48)),"",LOWER(MID($A48,FIND(CHAR(1),SUBSTITUTE($A48,".",CHAR(1),LEN($A48)-LEN(SUBSTITUTE($A48,".",""))))+1,LEN($A48))))) | C48: =IF($B48="","",IFERROR(INDEX(Rubric!$B$14:$B$23,MATCH($B48,Rubric!$A$14:$A$23,0)),INDEX(Rubric!$B$14:$B$23,MATCH("other",Rubric!$A$14:$A$23,0)))) | E48: =IF($B48="","",IFERROR(INDEX(Rubric!$C$14:$C$23,MATCH($B48,Rubric!$A$14:$A$23,0)),INDEX(Rubric!$C$14:$C$23,MATCH("other",Rubric!$A$14:$A$23,0)))) | F48: =IF(OR($A48="",$D48=""),"",$D48+$E48) | K48: =IF($J48="","",IF($J48>=15,5,IF($J48>=10,4,IF($J48>=5,3,IF($J48>=2,2,1))))) | S48: =IF($A48="","",IF(OR(UPPER($O48)="Y",UPPER($P48)="Y",UPPER($Q48)="Y",UPPER($R48)="Y"),"FAIL","PASS")) | T48: =IF(OR($A48="",$C48=""),"",$C48*$B$6+$G48*$B$7+$H48*$B$8+$I48*$B$9) | U48: =IF(OR($A48="",$K48=""),"",$K48*$B$13+$L48*$B$14+$M48*$B$15+$N48*$B$16) | V48: =IF(OR($T48="",$U48=""),"",$T48*$B$19+$U48*(1-$B$19)) | Y48: =IF(OR($A48="",$W48=""),"",MAX(0,$W48-MAX($W48*Assumptions!$B$4,Assumptions!$B$5))) | Z48: =IF($V48="","",Assumptions!$B$6*MAX(0.05,($V48/Assumptions!$B$11)^Assumptions!$B$12)) | AA48: =IF($Z48="","",1-(1-$Z48)^Assumptions!$B$7) | AB48: =IF(OR($F48="",$AA48="",$AA48=0),"",($F48+$E48*Assumptions!$B$7)/($AA48*(1-Assumptions!$B$4))) | AC48: =IF(OR($W48="",$AB48="",$AB48=0),"",$W48/$AB48) | AD48: =IF(OR($Y48="",$E48="",$AA48=""),"",MAX(0,$Y48*$AA48-$E48*Assumptions!$B$7)) | AE48: =IF(OR($AD48="",$F48=""),"",$AD48-$F48) | AF48: =IF($A48="","",IF($S48="FAIL","REJECT",IF($D48="","NEEDS PRICE",IF(OR($W48="",$X48=""),"NEEDS VALUATION",IF($AC48<1,"OVERPRICED",IF(AND($AC48>=Assumptions!$B$13,$V48>=4),"BUY",IF($V48>=3.4,"BUY CHEAPER",IF($V48>=2.8,"FLOOR ONLY","SKIP")))))))) | AG48: =IF($AF48="","",IF($AF48="REJECT","Do not buy at any price",IF($AF48="NEEDS PRICE","Enter the current closeout price",IF($AF48="NEEDS VALUATION","Enter a valuation AND its source before bidding",IF($AF48="OVERPRICED","Worth less than break-even - walk",IF($AF48="BUY","Take it on day 1 at $11 - will not reach the floor",IF($AF48="BUY CHEAPER","Wait to about $8 (day 3), walk if outbid",IF($AF48="FLOOR ONLY","Only at the $5 floor","Skip"))))))))
B49: =IF($A49="","",IF(ISERROR(FIND(".",$A49)),"",LOWER(MID($A49,FIND(CHAR(1),SUBSTITUTE($A49,".",CHAR(1),LEN($A49)-LEN(SUBSTITUTE($A49,".",""))))+1,LEN($A49))))) | C49: =IF($B49="","",IFERROR(INDEX(Rubric!$B$14:$B$23,MATCH($B49,Rubric!$A$14:$A$23,0)),INDEX(Rubric!$B$14:$B$23,MATCH("other",Rubric!$A$14:$A$23,0)))) | E49: =IF($B49="","",IFERROR(INDEX(Rubric!$C$14:$C$23,MATCH($B49,Rubric!$A$14:$A$23,0)),INDEX(Rubric!$C$14:$C$23,MATCH("other",Rubric!$A$14:$A$23,0)))) | F49: =IF(OR($A49="",$D49=""),"",$D49+$E49) | K49: =IF($J49="","",IF($J49>=15,5,IF($J49>=10,4,IF($J49>=5,3,IF($J49>=2,2,1))))) | S49: =IF($A49="","",IF(OR(UPPER($O49)="Y",UPPER($P49)="Y",UPPER($Q49)="Y",UPPER($R49)="Y"),"FAIL","PASS")) | T49: =IF(OR($A49="",$C49=""),"",$C49*$B$6+$G49*$B$7+$H49*$B$8+$I49*$B$9) | U49: =IF(OR($A49="",$K49=""),"",$K49*$B$13+$L49*$B$14+$M49*$B$15+$N49*$B$16) | V49: =IF(OR($T49="",$U49=""),"",$T49*$B$19+$U49*(1-$B$19)) | Y49: =IF(OR($A49="",$W49=""),"",MAX(0,$W49-MAX($W49*Assumptions!$B$4,Assumptions!$B$5))) | Z49: =IF($V49="","",Assumptions!$B$6*MAX(0.05,($V49/Assumptions!$B$11)^Assumptions!$B$12)) | AA49: =IF($Z49="","",1-(1-$Z49)^Assumptions!$B$7) | AB49: =IF(OR($F49="",$AA49="",$AA49=0),"",($F49+$E49*Assumptions!$B$7)/($AA49*(1-Assumptions!$B$4))) | AC49: =IF(OR($W49="",$AB49="",$AB49=0),"",$W49/$AB49) | AD49: =IF(OR($Y49="",$E49="",$AA49=""),"",MAX(0,$Y49*$AA49-$E49*Assumptions!$B$7)) | AE49: =IF(OR($AD49="",$F49=""),"",$AD49-$F49) | AF49: =IF($A49="","",IF($S49="FAIL","REJECT",IF($D49="","NEEDS PRICE",IF(OR($W49="",$X49=""),"NEEDS VALUATION",IF($AC49<1,"OVERPRICED",IF(AND($AC49>=Assumptions!$B$13,$V49>=4),"BUY",IF($V49>=3.4,"BUY CHEAPER",IF($V49>=2.8,"FLOOR ONLY","SKIP")))))))) | AG49: =IF($AF49="","",IF($AF49="REJECT","Do not buy at any price",IF($AF49="NEEDS PRICE","Enter the current closeout price",IF($AF49="NEEDS VALUATION","Enter a valuation AND its source before bidding",IF($AF49="OVERPRICED","Worth less than break-even - walk",IF($AF49="BUY","Take it on day 1 at $11 - will not reach the floor",IF($AF49="BUY CHEAPER","Wait to about $8 (day 3), walk if outbid",IF($AF49="FLOOR ONLY","Only at the $5 floor","Skip"))))))))
B50: =IF($A50="","",IF(ISERROR(FIND(".",$A50)),"",LOWER(MID($A50,FIND(CHAR(1),SUBSTITUTE($A50,".",CHAR(1),LEN($A50)-LEN(SUBSTITUTE($A50,".",""))))+1,LEN($A50))))) | C50: =IF($B50="","",IFERROR(INDEX(Rubric!$B$14:$B$23,MATCH($B50,Rubric!$A$14:$A$23,0)),INDEX(Rubric!$B$14:$B$23,MATCH("other",Rubric!$A$14:$A$23,0)))) | E50: =IF($B50="","",IFERROR(INDEX(Rubric!$C$14:$C$23,MATCH($B50,Rubric!$A$14:$A$23,0)),INDEX(Rubric!$C$14:$C$23,MATCH("other",Rubric!$A$14:$A$23,0)))) | F50: =IF(OR($A50="",$D50=""),"",$D50+$E50) | K50: =IF($J50="","",IF($J50>=15,5,IF($J50>=10,4,IF($J50>=5,3,IF($J50>=2,2,1))))) | S50: =IF($A50="","",IF(OR(UPPER($O50)="Y",UPPER($P50)="Y",UPPER($Q50)="Y",UPPER($R50)="Y"),"FAIL","PASS")) | T50: =IF(OR($A50="",$C50=""),"",$C50*$B$6+$G50*$B$7+$H50*$B$8+$I50*$B$9) | U50: =IF(OR($A50="",$K50=""),"",$K50*$B$13+$L50*$B$14+$M50*$B$15+$N50*$B$16) | V50: =IF(OR($T50="",$U50=""),"",$T50*$B$19+$U50*(1-$B$19)) | Y50: =IF(OR($A50="",$W50=""),"",MAX(0,$W50-MAX($W50*Assumptions!$B$4,Assumptions!$B$5))) | Z50: =IF($V50="","",Assumptions!$B$6*MAX(0.05,($V50/Assumptions!$B$11)^Assumptions!$B$12)) | AA50: =IF($Z50="","",1-(1-$Z50)^Assumptions!$B$7) | AB50: =IF(OR($F50="",$AA50="",$AA50=0),"",($F50+$E50*Assumptions!$B$7)/($AA50*(1-Assumptions!$B$4))) | AC50: =IF(OR($W50="",$AB50="",$AB50=0),"",$W50/$AB50) | AD50: =IF(OR($Y50="",$E50="",$AA50=""),"",MAX(0,$Y50*$AA50-$E50*Assumptions!$B$7)) | AE50: =IF(OR($AD50="",$F50=""),"",$AD50-$F50) | AF50: =IF($A50="","",IF($S50="FAIL","REJECT",IF($D50="","NEEDS PRICE",IF(OR($W50="",$X50=""),"NEEDS VALUATION",IF($AC50<1,"OVERPRICED",IF(AND($AC50>=Assumptions!$B$13,$V50>=4),"BUY",IF($V50>=3.4,"BUY CHEAPER",IF($V50>=2.8,"FLOOR ONLY","SKIP")))))))) | AG50: =IF($AF50="","",IF($AF50="REJECT","Do not buy at any price",IF($AF50="NEEDS PRICE","Enter the current closeout price",IF($AF50="NEEDS VALUATION","Enter a valuation AND its source before bidding",IF($AF50="OVERPRICED","Worth less than break-even - walk",IF($AF50="BUY","Take it on day 1 at $11 - will not reach the floor",IF($AF50="BUY CHEAPER","Wait to about $8 (day 3), walk if outbid",IF($AF50="FLOOR ONLY","Only at the $5 floor","Skip"))))))))
B51: =IF($A51="","",IF(ISERROR(FIND(".",$A51)),"",LOWER(MID($A51,FIND(CHAR(1),SUBSTITUTE($A51,".",CHAR(1),LEN($A51)-LEN(SUBSTITUTE($A51,".",""))))+1,LEN($A51))))) | C51: =IF($B51="","",IFERROR(INDEX(Rubric!$B$14:$B$23,MATCH($B51,Rubric!$A$14:$A$23,0)),INDEX(Rubric!$B$14:$B$23,MATCH("other",Rubric!$A$14:$A$23,0)))) | E51: =IF($B51="","",IFERROR(INDEX(Rubric!$C$14:$C$23,MATCH($B51,Rubric!$A$14:$A$23,0)),INDEX(Rubric!$C$14:$C$23,MATCH("other",Rubric!$A$14:$A$23,0)))) | F51: =IF(OR($A51="",$D51=""),"",$D51+$E51) | K51: =IF($J51="","",IF($J51>=15,5,IF($J51>=10,4,IF($J51>=5,3,IF($J51>=2,2,1))))) | S51: =IF($A51="","",IF(OR(UPPER($O51)="Y",UPPER($P51)="Y",UPPER($Q51)="Y",UPPER($R51)="Y"),"FAIL","PASS")) | T51: =IF(OR($A51="",$C51=""),"",$C51*$B$6+$G51*$B$7+$H51*$B$8+$I51*$B$9) | U51: =IF(OR($A51="",$K51=""),"",$K51*$B$13+$L51*$B$14+$M51*$B$15+$N51*$B$16) | V51: =IF(OR($T51="",$U51=""),"",$T51*$B$19+$U51*(1-$B$19)) | Y51: =IF(OR($A51="",$W51=""),"",MAX(0,$W51-MAX($W51*Assumptions!$B$4,Assumptions!$B$5))) | Z51: =IF($V51="","",Assumptions!$B$6*MAX(0.05,($V51/Assumptions!$B$11)^Assumptions!$B$12)) | AA51: =IF($Z51="","",1-(1-$Z51)^Assumptions!$B$7) | AB51: =IF(OR($F51="",$AA51="",$AA51=0),"",($F51+$E51*Assumptions!$B$7)/($AA51*(1-Assumptions!$B$4))) | AC51: =IF(OR($W51="",$AB51="",$AB51=0),"",$W51/$AB51) | AD51: =IF(OR($Y51="",$E51="",$AA51=""),"",MAX(0,$Y51*$AA51-$E51*Assumptions!$B$7)) | AE51: =IF(OR($AD51="",$F51=""),"",$AD51-$F51) | AF51: =IF($A51="","",IF($S51="FAIL","REJECT",IF($D51="","NEEDS PRICE",IF(OR($W51="",$X51=""),"NEEDS VALUATION",IF($AC51<1,"OVERPRICED",IF(AND($AC51>=Assumptions!$B$13,$V51>=4),"BUY",IF($V51>=3.4,"BUY CHEAPER",IF($V51>=2.8,"FLOOR ONLY","SKIP")))))))) | AG51: =IF($AF51="","",IF($AF51="REJECT","Do not buy at any price",IF($AF51="NEEDS PRICE","Enter the current closeout price",IF($AF51="NEEDS VALUATION","Enter a valuation AND its source before bidding",IF($AF51="OVERPRICED","Worth less than break-even - walk",IF($AF51="BUY","Take it on day 1 at $11 - will not reach the floor",IF($AF51="BUY CHEAPER","Wait to about $8 (day 3), walk if outbid",IF($AF51="FLOOR ONLY","Only at the $5 floor","Skip"))))))))
B52: =IF($A52="","",IF(ISERROR(FIND(".",$A52)),"",LOWER(MID($A52,FIND(CHAR(1),SUBSTITUTE($A52,".",CHAR(1),LEN($A52)-LEN(SUBSTITUTE($A52,".",""))))+1,LEN($A52))))) | C52: =IF($B52="","",IFERROR(INDEX(Rubric!$B$14:$B$23,MATCH($B52,Rubric!$A$14:$A$23,0)),INDEX(Rubric!$B$14:$B$23,MATCH("other",Rubric!$A$14:$A$23,0)))) | E52: =IF($B52="","",IFERROR(INDEX(Rubric!$C$14:$C$23,MATCH($B52,Rubric!$A$14:$A$23,0)),INDEX(Rubric!$C$14:$C$23,MATCH("other",Rubric!$A$14:$A$23,0)))) | F52: =IF(OR($A52="",$D52=""),"",$D52+$E52) | K52: =IF($J52="","",IF($J52>=15,5,IF($J52>=10,4,IF($J52>=5,3,IF($J52>=2,2,1))))) | S52: =IF($A52="","",IF(OR(UPPER($O52)="Y",UPPER($P52)="Y",UPPER($Q52)="Y",UPPER($R52)="Y"),"FAIL","PASS")) | T52: =IF(OR($A52="",$C52=""),"",$C52*$B$6+$G52*$B$7+$H52*$B$8+$I52*$B$9) | U52: =IF(OR($A52="",$K52=""),"",$K52*$B$13+$L52*$B$14+$M52*$B$15+$N52*$B$16) | V52: =IF(OR($T52="",$U52=""),"",$T52*$B$19+$U52*(1-$B$19)) | Y52: =IF(OR($A52="",$W52=""),"",MAX(0,$W52-MAX($W52*Assumptions!$B$4,Assumptions!$B$5))) | Z52: =IF($V52="","",Assumptions!$B$6*MAX(0.05,($V52/Assumptions!$B$11)^Assumptions!$B$12)) | AA52: =IF($Z52="","",1-(1-$Z52)^Assumptions!$B$7) | AB52: =IF(OR($F52="",$AA52="",$AA52=0),"",($F52+$E52*Assumptions!$B$7)/($AA52*(1-Assumptions!$B$4))) | AC52: =IF(OR($W52="",$AB52="",$AB52=0),"",$W52/$AB52) | AD52: =IF(OR($Y52="",$E52="",$AA52=""),"",MAX(0,$Y52*$AA52-$E52*Assumptions!$B$7)) | AE52: =IF(OR($AD52="",$F52=""),"",$AD52-$F52) | AF52: =IF($A52="","",IF($S52="FAIL","REJECT",IF($D52="","NEEDS PRICE",IF(OR($W52="",$X52=""),"NEEDS VALUATION",IF($AC52<1,"OVERPRICED",IF(AND($AC52>=Assumptions!$B$13,$V52>=4),"BUY",IF($V52>=3.4,"BUY CHEAPER",IF($V52>=2.8,"FLOOR ONLY","SKIP")))))))) | AG52: =IF($AF52="","",IF($AF52="REJECT","Do not buy at any price",IF($AF52="NEEDS PRICE","Enter the current closeout price",IF($AF52="NEEDS VALUATION","Enter a valuation AND its source before bidding",IF($AF52="OVERPRICED","Worth less than break-even - walk",IF($AF52="BUY","Take it on day 1 at $11 - will not reach the floor",IF($AF52="BUY CHEAPER","Wait to about $8 (day 3), walk if outbid",IF($AF52="FLOOR ONLY","Only at the $5 floor","Skip"))))))))
B53: =IF($A53="","",IF(ISERROR(FIND(".",$A53)),"",LOWER(MID($A53,FIND(CHAR(1),SUBSTITUTE($A53,".",CHAR(1),LEN($A53)-LEN(SUBSTITUTE($A53,".",""))))+1,LEN($A53))))) | C53: =IF($B53="","",IFERROR(INDEX(Rubric!$B$14:$B$23,MATCH($B53,Rubric!$A$14:$A$23,0)),INDEX(Rubric!$B$14:$B$23,MATCH("other",Rubric!$A$14:$A$23,0)))) | E53: =IF($B53="","",IFERROR(INDEX(Rubric!$C$14:$C$23,MATCH($B53,Rubric!$A$14:$A$23,0)),INDEX(Rubric!$C$14:$C$23,MATCH("other",Rubric!$A$14:$A$23,0)))) | F53: =IF(OR($A53="",$D53=""),"",$D53+$E53) | K53: =IF($J53="","",IF($J53>=15,5,IF($J53>=10,4,IF($J53>=5,3,IF($J53>=2,2,1))))) | S53: =IF($A53="","",IF(OR(UPPER($O53)="Y",UPPER($P53)="Y",UPPER($Q53)="Y",UPPER($R53)="Y"),"FAIL","PASS")) | T53: =IF(OR($A53="",$C53=""),"",$C53*$B$6+$G53*$B$7+$H53*$B$8+$I53*$B$9) | U53: =IF(OR($A53="",$K53=""),"",$K53*$B$13+$L53*$B$14+$M53*$B$15+$N53*$B$16) | V53: =IF(OR($T53="",$U53=""),"",$T53*$B$19+$U53*(1-$B$19)) | Y53: =IF(OR($A53="",$W53=""),"",MAX(0,$W53-MAX($W53*Assumptions!$B$4,Assumptions!$B$5))) | Z53: =IF($V53="","",Assumptions!$B$6*MAX(0.05,($V53/Assumptions!$B$11)^Assumptions!$B$12)) | AA53: =IF($Z53="","",1-(1-$Z53)^Assumptions!$B$7) | AB53: =IF(OR($F53="",$AA53="",$AA53=0),"",($F53+$E53*Assumptions!$B$7)/($AA53*(1-Assumptions!$B$4))) | AC53: =IF(OR($W53="",$AB53="",$AB53=0),"",$W53/$AB53) | AD53: =IF(OR($Y53="",$E53="",$AA53=""),"",MAX(0,$Y53*$AA53-$E53*Assumptions!$B$7)) | AE53: =IF(OR($AD53="",$F53=""),"",$AD53-$F53) | AF53: =IF($A53="","",IF($S53="FAIL","REJECT",IF($D53="","NEEDS PRICE",IF(OR($W53="",$X53=""),"NEEDS VALUATION",IF($AC53<1,"OVERPRICED",IF(AND($AC53>=Assumptions!$B$13,$V53>=4),"BUY",IF($V53>=3.4,"BUY CHEAPER",IF($V53>=2.8,"FLOOR ONLY","SKIP")))))))) | AG53: =IF($AF53="","",IF($AF53="REJECT","Do not buy at any price",IF($AF53="NEEDS PRICE","Enter the current closeout price",IF($AF53="NEEDS VALUATION","Enter a valuation AND its source before bidding",IF($AF53="OVERPRICED","Worth less than break-even - walk",IF($AF53="BUY","Take it on day 1 at $11 - will not reach the floor",IF($AF53="BUY CHEAPER","Wait to about $8 (day 3), walk if outbid",IF($AF53="FLOOR ONLY","Only at the $5 floor","Skip"))))))))
B54: =IF($A54="","",IF(ISERROR(FIND(".",$A54)),"",LOWER(MID($A54,FIND(CHAR(1),SUBSTITUTE($A54,".",CHAR(1),LEN($A54)-LEN(SUBSTITUTE($A54,".",""))))+1,LEN($A54))))) | C54: =IF($B54="","",IFERROR(INDEX(Rubric!$B$14:$B$23,MATCH($B54,Rubric!$A$14:$A$23,0)),INDEX(Rubric!$B$14:$B$23,MATCH("other",Rubric!$A$14:$A$23,0)))) | E54: =IF($B54="","",IFERROR(INDEX(Rubric!$C$14:$C$23,MATCH($B54,Rubric!$A$14:$A$23,0)),INDEX(Rubric!$C$14:$C$23,MATCH("other",Rubric!$A$14:$A$23,0)))) | F54: =IF(OR($A54="",$D54=""),"",$D54+$E54) | K54: =IF($J54="","",IF($J54>=15,5,IF($J54>=10,4,IF($J54>=5,3,IF($J54>=2,2,1))))) | S54: =IF($A54="","",IF(OR(UPPER($O54)="Y",UPPER($P54)="Y",UPPER($Q54)="Y",UPPER($R54)="Y"),"FAIL","PASS")) | T54: =IF(OR($A54="",$C54=""),"",$C54*$B$6+$G54*$B$7+$H54*$B$8+$I54*$B$9) | U54: =IF(OR($A54="",$K54=""),"",$K54*$B$13+$L54*$B$14+$M54*$B$15+$N54*$B$16) | V54: =IF(OR($T54="",$U54=""),"",$T54*$B$19+$U54*(1-$B$19)) | Y54: =IF(OR($A54="",$W54=""),"",MAX(0,$W54-MAX($W54*Assumptions!$B$4,Assumptions!$B$5))) | Z54: =IF($V54="","",Assumptions!$B$6*MAX(0.05,($V54/Assumptions!$B$11)^Assumptions!$B$12)) | AA54: =IF($Z54="","",1-(1-$Z54)^Assumptions!$B$7) | AB54: =IF(OR($F54="",$AA54="",$AA54=0),"",($F54+$E54*Assumptions!$B$7)/($AA54*(1-Assumptions!$B$4))) | AC54: =IF(OR($W54="",$AB54="",$AB54=0),"",$W54/$AB54) | AD54: =IF(OR($Y54="",$E54="",$AA54=""),"",MAX(0,$Y54*$AA54-$E54*Assumptions!$B$7)) | AE54: =IF(OR($AD54="",$F54=""),"",$AD54-$F54) | AF54: =IF($A54="","",IF($S54="FAIL","REJECT",IF($D54="","NEEDS PRICE",IF(OR($W54="",$X54=""),"NEEDS VALUATION",IF($AC54<1,"OVERPRICED",IF(AND($AC54>=Assumptions!$B$13,$V54>=4),"BUY",IF($V54>=3.4,"BUY CHEAPER",IF($V54>=2.8,"FLOOR ONLY","SKIP")))))))) | AG54: =IF($AF54="","",IF($AF54="REJECT","Do not buy at any price",IF($AF54="NEEDS PRICE","Enter the current closeout price",IF($AF54="NEEDS VALUATION","Enter a valuation AND its source before bidding",IF($AF54="OVERPRICED","Worth less than break-even - walk",IF($AF54="BUY","Take it on day 1 at $11 - will not reach the floor",IF($AF54="BUY CHEAPER","Wait to about $8 (day 3), walk if outbid",IF($AF54="FLOOR ONLY","Only at the $5 floor","Skip"))))))))
B55: =IF($A55="","",IF(ISERROR(FIND(".",$A55)),"",LOWER(MID($A55,FIND(CHAR(1),SUBSTITUTE($A55,".",CHAR(1),LEN($A55)-LEN(SUBSTITUTE($A55,".",""))))+1,LEN($A55))))) | C55: =IF($B55="","",IFERROR(INDEX(Rubric!$B$14:$B$23,MATCH($B55,Rubric!$A$14:$A$23,0)),INDEX(Rubric!$B$14:$B$23,MATCH("other",Rubric!$A$14:$A$23,0)))) | E55: =IF($B55="","",IFERROR(INDEX(Rubric!$C$14:$C$23,MATCH($B55,Rubric!$A$14:$A$23,0)),INDEX(Rubric!$C$14:$C$23,MATCH("other",Rubric!$A$14:$A$23,0)))) | F55: =IF(OR($A55="",$D55=""),"",$D55+$E55) | K55: =IF($J55="","",IF($J55>=15,5,IF($J55>=10,4,IF($J55>=5,3,IF($J55>=2,2,1))))) | S55: =IF($A55="","",IF(OR(UPPER($O55)="Y",UPPER($P55)="Y",UPPER($Q55)="Y",UPPER($R55)="Y"),"FAIL","PASS")) | T55: =IF(OR($A55="",$C55=""),"",$C55*$B$6+$G55*$B$7+$H55*$B$8+$I55*$B$9) | U55: =IF(OR($A55="",$K55=""),"",$K55*$B$13+$L55*$B$14+$M55*$B$15+$N55*$B$16) | V55: =IF(OR($T55="",$U55=""),"",$T55*$B$19+$U55*(1-$B$19)) | Y55: =IF(OR($A55="",$W55=""),"",MAX(0,$W55-MAX($W55*Assumptions!$B$4,Assumptions!$B$5))) | Z55: =IF($V55="","",Assumptions!$B$6*MAX(0.05,($V55/Assumptions!$B$11)^Assumptions!$B$12)) | AA55: =IF($Z55="","",1-(1-$Z55)^Assumptions!$B$7) | AB55: =IF(OR($F55="",$AA55="",$AA55=0),"",($F55+$E55*Assumptions!$B$7)/($AA55*(1-Assumptions!$B$4))) | AC55: =IF(OR($W55="",$AB55="",$AB55=0),"",$W55/$AB55) | AD55: =IF(OR($Y55="",$E55="",$AA55=""),"",MAX(0,$Y55*$AA55-$E55*Assumptions!$B$7)) | AE55: =IF(OR($AD55="",$F55=""),"",$AD55-$F55) | AF55: =IF($A55="","",IF($S55="FAIL","REJECT",IF($D55="","NEEDS PRICE",IF(OR($W55="",$X55=""),"NEEDS VALUATION",IF($AC55<1,"OVERPRICED",IF(AND($AC55>=Assumptions!$B$13,$V55>=4),"BUY",IF($V55>=3.4,"BUY CHEAPER",IF($V55>=2.8,"FLOOR ONLY","SKIP")))))))) | AG55: =IF($AF55="","",IF($AF55="REJECT","Do not buy at any price",IF($AF55="NEEDS PRICE","Enter the current closeout price",IF($AF55="NEEDS VALUATION","Enter a valuation AND its source before bidding",IF($AF55="OVERPRICED","Worth less than break-even - walk",IF($AF55="BUY","Take it on day 1 at $11 - will not reach the floor",IF($AF55="BUY CHEAPER","Wait to about $8 (day 3), walk if outbid",IF($AF55="FLOOR ONLY","Only at the $5 floor","Skip"))))))))
B56: =IF($A56="","",IF(ISERROR(FIND(".",$A56)),"",LOWER(MID($A56,FIND(CHAR(1),SUBSTITUTE($A56,".",CHAR(1),LEN($A56)-LEN(SUBSTITUTE($A56,".",""))))+1,LEN($A56))))) | C56: =IF($B56="","",IFERROR(INDEX(Rubric!$B$14:$B$23,MATCH($B56,Rubric!$A$14:$A$23,0)),INDEX(Rubric!$B$14:$B$23,MATCH("other",Rubric!$A$14:$A$23,0)))) | E56: =IF($B56="","",IFERROR(INDEX(Rubric!$C$14:$C$23,MATCH($B56,Rubric!$A$14:$A$23,0)),INDEX(Rubric!$C$14:$C$23,MATCH("other",Rubric!$A$14:$A$23,0)))) | F56: =IF(OR($A56="",$D56=""),"",$D56+$E56) | K56: =IF($J56="","",IF($J56>=15,5,IF($J56>=10,4,IF($J56>=5,3,IF($J56>=2,2,1))))) | S56: =IF($A56="","",IF(OR(UPPER($O56)="Y",UPPER($P56)="Y",UPPER($Q56)="Y",UPPER($R56)="Y"),"FAIL","PASS")) | T56: =IF(OR($A56="",$C56=""),"",$C56*$B$6+$G56*$B$7+$H56*$B$8+$I56*$B$9) | U56: =IF(OR($A56="",$K56=""),"",$K56*$B$13+$L56*$B$14+$M56*$B$15+$N56*$B$16) | V56: =IF(OR($T56="",$U56=""),"",$T56*$B$19+$U56*(1-$B$19)) | Y56: =IF(OR($A56="",$W56=""),"",MAX(0,$W56-MAX($W56*Assumptions!$B$4,Assumptions!$B$5))) | Z56: =IF($V56="","",Assumptions!$B$6*MAX(0.05,($V56/Assumptions!$B$11)^Assumptions!$B$12)) | AA56: =IF($Z56="","",1-(1-$Z56)^Assumptions!$B$7) | AB56: =IF(OR($F56="",$AA56="",$AA56=0),"",($F56+$E56*Assumptions!$B$7)/($AA56*(1-Assumptions!$B$4))) | AC56: =IF(OR($W56="",$AB56="",$AB56=0),"",$W56/$AB56) | AD56: =IF(OR($Y56="",$E56="",$AA56=""),"",MAX(0,$Y56*$AA56-$E56*Assumptions!$B$7)) | AE56: =IF(OR($AD56="",$F56=""),"",$AD56-$F56) | AF56: =IF($A56="","",IF($S56="FAIL","REJECT",IF($D56="","NEEDS PRICE",IF(OR($W56="",$X56=""),"NEEDS VALUATION",IF($AC56<1,"OVERPRICED",IF(AND($AC56>=Assumptions!$B$13,$V56>=4),"BUY",IF($V56>=3.4,"BUY CHEAPER",IF($V56>=2.8,"FLOOR ONLY","SKIP")))))))) | AG56: =IF($AF56="","",IF($AF56="REJECT","Do not buy at any price",IF($AF56="NEEDS PRICE","Enter the current closeout price",IF($AF56="NEEDS VALUATION","Enter a valuation AND its source before bidding",IF($AF56="OVERPRICED","Worth less than break-even - walk",IF($AF56="BUY","Take it on day 1 at $11 - will not reach the floor",IF($AF56="BUY CHEAPER","Wait to about $8 (day 3), walk if outbid",IF($AF56="FLOOR ONLY","Only at the $5 floor","Skip"))))))))
... B163: =IF($A163="","",IF(ISERROR(FIND(".",$A163)),"",LOWER(MID($A163,FIND(CHAR(1),SUBSTITUTE($A163,".",CHAR(1),LEN($A163)-LEN(SUBSTITUTE($A163,".",""))))+1,LEN($A163))))) | C163: =IF($B163="","",IFERROR(INDEX(Rubric!$B$14:$B$23,MATCH($B163,Rubric!$A$14:$A$23,0)),INDEX(Rubric!$B$14:$B$23,MATCH("other",Rubric!$A$14:$A$23,0)))) | E163: =IF($B163="","",IFERROR(INDEX(Rubric!$C$14:$C$23,MATCH($B163,Rubric!$A$14:$A$23,0)),INDEX(Rubric!$C$14:$C$23,MATCH("other",Rubric!$A$14:$A$23,0)))) | F163: =IF(OR($A163="",$D163=""),"",$D163+$E163) | K163: =IF($J163="","",IF($J163>=15,5,IF($J163>=10,4,IF($J163>=5,3,IF($J163>=2,2,1))))) | S163: =IF($A163="","",IF(OR(UPPER($O163)="Y",UPPER($P163)="Y",UPPER($Q163)="Y",UPPER($R163)="Y"),"FAIL","PASS")) | T163: =IF(OR($A163="",$C163=""),"",$C163*$B$6+$G163*$B$7+$H163*$B$8+$I163*$B$9) | U163: =IF(OR($A163="",$K163=""),"",$K163*$B$13+$L163*$B$14+$M163*$B$15+$N163*$B$16) | V163: =IF(OR($T163="",$U163=""),"",$T163*$B$19+$U163*(1-$B$19)) | Y163: =IF(OR($A163="",$W163=""),"",MAX(0,$W163-MAX($W163*Assumptions!$B$4,Assumptions!$B$5))) | Z163: =IF($V163="","",Assumptions!$B$6*MAX(0.05,($V163/Assumptions!$B$11)^Assumptions!$B$12)) | AA163: =IF($Z163="","",1-(1-$Z163)^Assumptions!$B$7) | AB163: =IF(OR($F163="",$AA163="",$AA163=0),"",($F163+$E163*Assumptions!$B$7)/($AA163*(1-Assumptions!$B$4))) | AC163: =IF(OR($W163="",$AB163="",$AB163=0),"",$W163/$AB163) | AD163: =IF(OR($Y163="",$E163="",$AA163=""),"",MAX(0,$Y163*$AA163-$E163*Assumptions!$B$7)) | AE163: =IF(OR($AD163="",$F163=""),"",$AD163-$F163) | AF163: =IF($A163="","",IF($S163="FAIL","REJECT",IF($D163="","NEEDS PRICE",IF(OR($W163="",$X163=""),"NEEDS VALUATION",IF($AC163<1,"OVERPRICED",IF(AND($AC163>=Assumptions!$B$13,$V163>=4),"BUY",IF($V163>=3.4,"BUY CHEAPER",IF($V163>=2.8,"FLOOR ONLY","SKIP")))))))) | AG163: =IF($AF163="","",IF($AF163="REJECT","Do not buy at any price",IF($AF163="NEEDS PRICE","Enter the current closeout price",IF($AF163="NEEDS VALUATION","Enter a valuation AND its source before bidding",IF($AF163="OVERPRICED","Worth less than break-even - walk",IF($AF163="BUY","Take it on day 1 at $11 - will not reach the floor",IF($AF163="BUY CHEAPER","Wait to about $8 (day 3), walk if outbid",IF($AF163="FLOOR ONLY","Only at the $5 floor","Skip"))))))))

Sheet Portfolio
A1: Portfolio — names you actually own
A2: Enter the FULL domain in column A (name.com) — Ext derives itself. Blue columns are yours; carry, cost basis and break-even are formulas that update with today's date. Row 5 is an example — delete it.
A4: Domain (full, e.g. name.com) | B4: Ext | C4: Status | D4: Acquired | E4: Acquisition Cost | F4: Annual Renewal | G4: Years Held | H4: Renewals Paid | I4: Cumulative Carry | J4: Total Cost Basis | K4: Break-Even List Price | L4: Target List Price | M4: Currently Listed At | N4: Notes
A5: equipmentfinancing.com | B5: =IF($A5="","",IF(ISERROR(FIND(".",$A5)),"",LOWER(MID($A5,FIND(CHAR(1),SUBSTITUTE($A5,".",CHAR(1),LEN($A5)-LEN(SUBSTITUTE($A5,".",""))))+1,LEN($A5))))) -> com | C5: Active | D5: 45363 | E5: 2400 | F5: =IF($B5="","",IFERROR(INDEX(Rubric!$C$14:$C$23,MATCH(LOWER($B5),Rubric!$A$14:$A$23,0)),INDEX(Rubric!$C$14:$C$23,MATCH("other",Rubric!$A$14:$A$23,0)))) -> 11 | G5: =IF(OR($A5="",$D5=""),"",YEARFRAC($D5,TODAY())) -> 2.4 | H5: =IF($G5="","",MAX(0,INT($G5))) -> 2 | I5: =IF(OR($F5="",$H5=""),"",$F5*$H5) -> 22 | J5: =IF(OR($A5="",$E5=""),"",$E5+IF($I5="",0,$I5)) -> 2422 | K5: =IF(OR($J5="",$J5=0),"",$J5/(1-Assumptions!$B$4)) -> 3027.5 | L5: =IF($K5="","",MAX($K5,$E5*Assumptions!$B$10)) -> 24000 | M5: 12000 | N5: EXAMPLE ROW — delete.
B6: =IF($A6="","",IF(ISERROR(FIND(".",$A6)),"",LOWER(MID($A6,FIND(CHAR(1),SUBSTITUTE($A6,".",CHAR(1),LEN($A6)-LEN(SUBSTITUTE($A6,".",""))))+1,LEN($A6))))) | F6: =IF($B6="","",IFERROR(INDEX(Rubric!$C$14:$C$23,MATCH(LOWER($B6),Rubric!$A$14:$A$23,0)),INDEX(Rubric!$C$14:$C$23,MATCH("other",Rubric!$A$14:$A$23,0)))) | G6: =IF(OR($A6="",$D6=""),"",YEARFRAC($D6,TODAY())) | H6: =IF($G6="","",MAX(0,INT($G6))) | I6: =IF(OR($F6="",$H6=""),"",$F6*$H6) | J6: =IF(OR($A6="",$E6=""),"",$E6+IF($I6="",0,$I6)) | K6: =IF(OR($J6="",$J6=0),"",$J6/(1-Assumptions!$B$4)) | L6: =IF($K6="","",MAX($K6,$E6*Assumptions!$B$10))
B7: =IF($A7="","",IF(ISERROR(FIND(".",$A7)),"",LOWER(MID($A7,FIND(CHAR(1),SUBSTITUTE($A7,".",CHAR(1),LEN($A7)-LEN(SUBSTITUTE($A7,".",""))))+1,LEN($A7))))) | F7: =IF($B7="","",IFERROR(INDEX(Rubric!$C$14:$C$23,MATCH(LOWER($B7),Rubric!$A$14:$A$23,0)),INDEX(Rubric!$C$14:$C$23,MATCH("other",Rubric!$A$14:$A$23,0)))) | G7: =IF(OR($A7="",$D7=""),"",YEARFRAC($D7,TODAY())) | H7: =IF($G7="","",MAX(0,INT($G7))) | I7: =IF(OR($F7="",$H7=""),"",$F7*$H7) | J7: =IF(OR($A7="",$E7=""),"",$E7+IF($I7="",0,$I7)) | K7: =IF(OR($J7="",$J7=0),"",$J7/(1-Assumptions!$B$4)) | L7: =IF($K7="","",MAX($K7,$E7*Assumptions!$B$10))
B8: =IF($A8="","",IF(ISERROR(FIND(".",$A8)),"",LOWER(MID($A8,FIND(CHAR(1),SUBSTITUTE($A8,".",CHAR(1),LEN($A8)-LEN(SUBSTITUTE($A8,".",""))))+1,LEN($A8))))) | F8: =IF($B8="","",IFERROR(INDEX(Rubric!$C$14:$C$23,MATCH(LOWER($B8),Rubric!$A$14:$A$23,0)),INDEX(Rubric!$C$14:$C$23,MATCH("other",Rubric!$A$14:$A$23,0)))) | G8: =IF(OR($A8="",$D8=""),"",YEARFRAC($D8,TODAY())) | H8: =IF($G8="","",MAX(0,INT($G8))) | I8: =IF(OR($F8="",$H8=""),"",$F8*$H8) | J8: =IF(OR($A8="",$E8=""),"",$E8+IF($I8="",0,$I8)) | K8: =IF(OR($J8="",$J8=0),"",$J8/(1-Assumptions!$B$4)) | L8: =IF($K8="","",MAX($K8,$E8*Assumptions!$B$10))
B9: =IF($A9="","",IF(ISERROR(FIND(".",$A9)),"",LOWER(MID($A9,FIND(CHAR(1),SUBSTITUTE($A9,".",CHAR(1),LEN($A9)-LEN(SUBSTITUTE($A9,".",""))))+1,LEN($A9))))) | F9: =IF($B9="","",IFERROR(INDEX(Rubric!$C$14:$C$23,MATCH(LOWER($B9),Rubric!$A$14:$A$23,0)),INDEX(Rubric!$C$14:$C$23,MATCH("other",Rubric!$A$14:$A$23,0)))) | G9: =IF(OR($A9="",$D9=""),"",YEARFRAC($D9,TODAY())) | H9: =IF($G9="","",MAX(0,INT($G9))) | I9: =IF(OR($F9="",$H9=""),"",$F9*$H9) | J9: =IF(OR($A9="",$E9=""),"",$E9+IF($I9="",0,$I9)) | K9: =IF(OR($J9="",$J9=0),"",$J9/(1-Assumptions!$B$4)) | L9: =IF($K9="","",MAX($K9,$E9*Assumptions!$B$10))
B10: =IF($A10="","",IF(ISERROR(FIND(".",$A10)),"",LOWER(MID($A10,FIND(CHAR(1),SUBSTITUTE($A10,".",CHAR(1),LEN($A10)-LEN(SUBSTITUTE($A10,".",""))))+1,LEN($A10))))) | F10: =IF($B10="","",IFERROR(INDEX(Rubric!$C$14:$C$23,MATCH(LOWER($B10),Rubric!$A$14:$A$23,0)),INDEX(Rubric!$C$14:$C$23,MATCH("other",Rubric!$A$14:$A$23,0)))) | G10: =IF(OR($A10="",$D10=""),"",YEARFRAC($D10,TODAY())) | H10: =IF($G10="","",MAX(0,INT($G10))) | I10: =IF(OR($F10="",$H10=""),"",$F10*$H10) | J10: =IF(OR($A10="",$E10=""),"",$E10+IF($I10="",0,$I10)) | K10: =IF(OR($J10="",$J10=0),"",$J10/(1-Assumptions!$B$4)) | L10: =IF($K10="","",MAX($K10,$E10*Assumptions!$B$10))
B11: =IF($A11="","",IF(ISERROR(FIND(".",$A11)),"",LOWER(MID($A11,FIND(CHAR(1),SUBSTITUTE($A11,".",CHAR(1),LEN($A11)-LEN(SUBSTITUTE($A11,".",""))))+1,LEN($A11))))) | F11: =IF($B11="","",IFERROR(INDEX(Rubric!$C$14:$C$23,MATCH(LOWER($B11),Rubric!$A$14:$A$23,0)),INDEX(Rubric!$C$14:$C$23,MATCH("other",Rubric!$A$14:$A$23,0)))) | G11: =IF(OR($A11="",$D11=""),"",YEARFRAC($D11,TODAY())) | H11: =IF($G11="","",MAX(0,INT($G11))) | I11: =IF(OR($F11="",$H11=""),"",$F11*$H11) | J11: =IF(OR($A11="",$E11=""),"",$E11+IF($I11="",0,$I11)) | K11: =IF(OR($J11="",$J11=0),"",$J11/(1-Assumptions!$B$4)) | L11: =IF($K11="","",MAX($K11,$E11*Assumptions!$B$10))
B12: =IF($A12="","",IF(ISERROR(FIND(".",$A12)),"",LOWER(MID($A12,FIND(CHAR(1),SUBSTITUTE($A12,".",CHAR(1),LEN($A12)-LEN(SUBSTITUTE($A12,".",""))))+1,LEN($A12))))) | F12: =IF($B12="","",IFERROR(INDEX(Rubric!$C$14:$C$23,MATCH(LOWER($B12),Rubric!$A$14:$A$23,0)),INDEX(Rubric!$C$14:$C$23,MATCH("other",Rubric!$A$14:$A$23,0)))) | G12: =IF(OR($A12="",$D12=""),"",YEARFRAC($D12,TODAY())) | H12: =IF($G12="","",MAX(0,INT($G12))) | I12: =IF(OR($F12="",$H12=""),"",$F12*$H12) | J12: =IF(OR($A12="",$E12=""),"",$E12+IF($I12="",0,$I12)) | K12: =IF(OR($J12="",$J12=0),"",$J12/(1-Assumptions!$B$4)) | L12: =IF($K12="","",MAX($K12,$E12*Assumptions!$B$10))
B13: =IF($A13="","",IF(ISERROR(FIND(".",$A13)),"",LOWER(MID($A13,FIND(CHAR(1),SUBSTITUTE($A13,".",CHAR(1),LEN($A13)-LEN(SUBSTITUTE($A13,".",""))))+1,LEN($A13))))) | F13: =IF($B13="","",IFERROR(INDEX(Rubric!$C$14:$C$23,MATCH(LOWER($B13),Rubric!$A$14:$A$23,0)),INDEX(Rubric!$C$14:$C$23,MATCH("other",Rubric!$A$14:$A$23,0)))) | G13: =IF(OR($A13="",$D13=""),"",YEARFRAC($D13,TODAY())) | H13: =IF($G13="","",MAX(0,INT($G13))) | I13: =IF(OR($F13="",$H13=""),"",$F13*$H13) | J13: =IF(OR($A13="",$E13=""),"",$E13+IF($I13="",0,$I13)) | K13: =IF(OR($J13="",$J13=0),"",$J13/(1-Assumptions!$B$4)) | L13: =IF($K13="","",MAX($K13,$E13*Assumptions!$B$10))
